Workbook

Sheet MIS
A1: S.NO | B1: Indent Date | C1: Indent | D1: Allocation Date | E1: Customer Name | F1: Location | G1: Vehicle Model | H1: Vehicle Number | I1: Vehicle Based | J1: LR No. | K1: Material | L1: Load Per bucket (Kgs) | M1: No. of Buckets/Barrels | N1: T. Load (Kgs) | O1: POD Received | P1: Loading Charge (Rs.95 per Ton) | Q1: Unloading Charge | R1: Actual Running | S1: Billable Running | T1: Range | U1: Revenue | V1: Total Cost | W1: PnL
A2: 1 | B2: 45733 | C2: S/Drona/03/25/01 | D2: 45734 | E2: Cargo Motors | F2: Delhi | G2: 1109 | H2: HR38AC7854 | I2: Fixed | J2: 0003 | K2: DEF Buckets | L2: 20 | M2: 200 | N2: =L2*M2 -> 4000 | O2: Yes | P2: =(N2/1000)*'Rate Card'!$L$2 -> 380 | Q2: =M2*5 -> 1000 | R2: 321 | S2: =R2/2 -> 160.5 | V2: =R2*'Vehicle Master'!$F$2+MIS!P2+MIS!Q2 -> 11331 | W2: =U2-V2 -> -11331
A3: =A2+1 -> 2 | B3: 45733 | C3: S/Drona/03/25/01 | D3: 45734 | E3: Cargo Motors | F3: Delhi | G3: 1109 | H3: HR38AC7854 | I3: Fixed | J3: 0003 | K3: Barrels | L3: 210 | M3: 3 | N3: =L3*M3 -> 630 | O3: Yes | P3: =(N3/1000)*'Rate Card'!$L$2 -> 59.85 | Q3: 0 | R3: 0 | S3: 0 | V3: =R3*'Vehicle Master'!$F$2+MIS!P3+MIS!Q3 -> 59.85 | W3: =U3-V3 -> -59.85
A4: =A3+1 -> 3 | B4: 45733 | C4: S/Drona/03/25/02 | D4: 45734 | E4: VLH Marketing | F4: Karnal | G4: 1109 | H4: HR38AC7243 | I4: Fixed | J4: 0001 | K4: DEF Buckets | L4: 20 | M4: 300 | N4: =L4*M4 -> 6000 | O4: Yes | P4: =(N4/1000)*'Rate Card'!$L$2 -> 570 | Q4: =M4*5 -> 1500 | R4: 189 | S4: =R4/2 -> 94.5 | V4: =R4*'Vehicle Master'!$F$2+MIS!P4+MIS!Q4 -> 7929 | W4: =U4-V4 -> -7929
A5: =A4+1 -> 4 | B5: 45734 | C5: S/Drona/03/25/03 | D5: 45734 | E5: Johar Automobiles | F5: Faridabad | G5: 1109 | H5: HR38AC0599 | I5: Fixed | J5: 0002 | K5: DEF Buckets | L5: 20 | M5: 300 | N5: =L5*M5 -> 6000 | O5: Yes | P5: =(N5/1000)*'Rate Card'!$L$2 -> 570 | Q5: =M5*5 -> 1500 | R5: 73 | S5: =R5/2 -> 36.5 | V5: =R5*'Vehicle Master'!$F$2+MIS!P5+MIS!Q5 -> 4333 | W5: =U5-V5 -> -4333
A6: =A5+1 -> 5 | B6: 45734 | C6: S/Drona/03/25/04 | D6: 45734 | E6: Pasco Motors LLP | F6: New Delhi | G6: 1109 | H6: HR38AC0263 | I6: Fixed | J6: 0004 | K6: DEF Buckets | L6: 20 | M6: 300 | N6: =L6*M6 -> 6000 | O6: Yes | P6: =(N6/1000)*'Rate Card'!$L$2 -> 570 | Q6: =M6*5 -> 1500 | R6: 139 | S6: =R6/2 -> 69.5 | V6: =R6*'Vehicle Master'!$F$2+MIS!P6+MIS!Q6 -> 6379 | W6: =U6-V6 -> -6379
A7: =A6+1 -> 6 | B7: 45734 | C7: S/Drona/03/25/06 | D7: 45736 | E7: Pasco Motors LLP | F7: New Delhi | G7: 1109 | H7: HR38AC7243 | I7: Fixed | J7: 0009 | K7: DEF Buckets | L7: 20 | M7: 100 | N7: =L7*M7 -> 2000 | P7: =(N7/1000)*'Rate Card'!$L$2 -> 190 | Q7: =M7*5 -> 500 | S7: =R7/2 -> 0 | V7: =R7*'Vehicle Master'!$F$2+MIS!P7+MIS!Q7 -> 690 | W7: =U7-V7 -> -690
A8: =A7+1 -> 7 | B8: 45734 | C8: S/Drona/03/25/07 | D8: 45735 | E8: Yuvraj Motors | F8: Aligarh | G8: 1109 | H8: HR38AC0263 | I8: Fixed | J8: 0006 | K8: DEF Buckets | L8: 20 | M8: 300 | N8: =L8*M8 -> 6000 | O8: Yes | P8: =(N8/1000)*'Rate Card'!$L$2 -> 570 | Q8: =M8*5 -> 1500 | R8: 372 | S8: =R8/2 -> 186 | V8: =R8*'Vehicle Master'!$F$2+MIS!P8+MIS!Q8 -> 13602 | W8: =U8-V8 -> -13602
A9: =A8+1 -> 8 | B9: 45734 | C9: S/Drona/03/25/08 | D9: 45735 | E9: UP State Road Transport Corporation | F9: Gaziabad | G9: 1109 | H9: HR38AC7854 | I9: Fixed | J9: 0005 | K9: DEF Barrels | L9: 210 | M9: 30 | N9: =L9*M9 -> 6300 | O9: Yes | P9: =(N9/1000)*'Rate Card'!$L$2 -> 598.5 | Q9: =M9*30 -> 900 | R9: 183 | S9: =R9/2 -> 91.5 | V9: =R9*'Vehicle Master'!$F$2+MIS!P9+MIS!Q9 -> 7171.5 | W9: =U9-V9 -> -7171.5
A10: =A9+1 -> 9 | B10: 45734 | C10: S/Drona/03/25/09 | D10: 45735 | E10: UP State Road Transport Corporation | F10: Gaziabad | G10: 1109 | H10: HR38AC7243 | I10: Fixed | J10: 0007 | K10: DEF Barrels | L10: 210 | M10: 30 | N10: =L10*M10 -> 6300 | O10: No | P10: =(N10/1000)*'Rate Card'!$L$2 -> 598.5 | Q10: =M10*30 -> 900 | R10: 166 | S10: =R10/2 -> 83 | V10: =R10*'Vehicle Master'!$F$2+MIS!P10+MIS!Q10 -> 6644.5 | W10: =U10-V10 -> -6644.5
A11: =A10+1 -> 10 | B11: 45735 | C11: S/Drona/03/25/10 | D11: 45736 | E11: Sisothiya Automobile | F11: Dharuhera | G11: 1109 | H11: HR38AC0599 | I11: Fixed | J11: 0008 | K11: DEF Buckets | L11: 20 | M11: 100 | N11: =L11*M11 -> 2000 | O11: Yes | P11: =(N11/1000)*'Rate Card'!$L$2 -> 190 | Q11: =M11*5 -> 500 | R11: 243 | S11: =R11/2 -> 121.5 | V11: =R11*'Vehicle Master'!$F$2+MIS!P11+MIS!Q11 -> 8223 | W11: =U11-V11 -> -8223
A12: =A11+1 -> 11 | B12: 45735 | C12: S/Drona/03/25/11 | D12: 45736 | E12: Sahni Motors | F12: Karnal | G12: 1109 | H12: HR38AC7854 | I12: Fixed | J12: 0010 | K12: DEF Buckets | L12: 20 | M12: 200 | N12: =L12*M12 -> 4000 | O12: No | P12: =(N12/1000)*'Rate Card'!$L$2 -> 380 | Q12: =M12*5 -> 1000 | R12: 177 | S12: =R12/2 -> 88.5 | V12: =R12*'Vehicle Master'!$F$2+MIS!P12+MIS!Q12 -> 6867 | W12: =U12-V12 -> -6867
A13: =A12+1 -> 12 | B13: 45735 | C13: S/Drona/03/25/11 | D13: 45736 | E13: Sahni Motors | F13: Karnal | G13: 1109 | H13: HR38AC7854 | I13: Fixed | J13: 0010 | K13: Jerry Can | L13: 20 | M13: 100 | N13: =L13*M13 -> 2000 | O13: No | P13: =(N13/1000)*'Rate Card'!$L$2 -> 190 | Q13: =M13*5 -> 500 | R13: 0 | S13: =R13/2 -> 0 | V13: =R13*'Vehicle Master'!$F$2+MIS!P13+MIS!Q13 -> 690 | W13: =U13-V13 -> -690

Sheet OPs Data
A1: S.NO | B1: Indent Date | C1: Indent | D1: Allocation Date | E1: Customer Name | F1: Range | G1: Location | H1: Vehicle Number | I1: Vehicle Model | J1: Vehicle Based | K1: LR No. | L1: Material | M1: Load Per bucket (Kgs) | N1: No. of Buckets/Barrels | O1: T. Load (Kgs) | P1: POD Received | Q1: FREIGHT Tiger Number | R1: Freight Tiger Month | S1: REMARKS | U1: Total Km ( TpT) | V1: Rate | W1: Total Cost | X1: =SUBTOTAL(9,W:W) -> 4182101 | Y1: Total Cost(Loading) | Z1: =SUBTOTAL(9,Y:Y) -> 288943.45 | AA1: Criteria | AB1: Total cost Unload | AC1: =SUBTOTAL(9,AB:AB) -> 707255 | AD1: Any Other Cost | AE1: Total Cost | AF1: =SUBTOTAL(9,AE:AE) -> 5209799.4 | AG1: Criteria | AH1: Cost | AI1: Revenue | AJ1: =SUBTOTAL(9,AI:AI) -> 5011717 | AK1: P & L | AL1: =SUBTOTAL(9,AK:AK) -> -198082.45 | AN1: Km/2
A2: 1 | B2: 45733 | C2: S/Drona/03/25/01 | D2: 45734 | E2: Cargo Motors | F2: 0-100Km | G2: Delhi | H2: HR38AC7854 | I2: 1109 | J2: Fixed | K2: 3 | L2: 20L Buckets | M2: =IFERROR(VLOOKUP(L2,'Material Master'!B:C,2,0),"") -> 20 | N2: 200 | O2: =IFERROR(M2*N2,"") -> 4000 | P2: Yes | R2: 45717 | U2: 73 | V2: 31 | W2: =IFERROR(U2*V2,"0") -> 2263 | Y2: =IFERROR((O2/1000)*Masters!$C$3,"0") -> 380 | AA2: =IFERROR(VLOOKUP(L2,Masters!G:H,2,0),"0") -> 5 | AB2: =IFERROR(AA2*N2,"0") -> 1000 | AE2: =W2+Y2+AB2+AD2 -> 3643 | AG2: =M2&"-"&F2 -> 20-0-100Km | AH2: =IFERROR(VLOOKUP(AG2,Masters!N:O,2,0),"0") -> 21 | AI2: =AH2*N2 -> 4200 | AK2: =AI2-AE2 -> 557 | AN2: =IFERROR(U2/2,"0") -> 36.5
A3: =A2+1 -> 2 | B3: 45733 | C3: S/Drona/03/25/01 | D3: 45734 | E3: Cargo Motors | F3: 0-100Km | G3: Delhi | H3: HR38AC7854 | I3: 1109 | J3: Fixed | K3: 3 | L3: 210L Barrels | M3: =IFERROR(VLOOKUP(L3,'Material Master'!B:C,2,0),"") -> 210 | N3: 3 | O3: =IFERROR(M3*N3,"") -> 630 | P3: Yes | R3: 45717 | U3: 0 | V3: 31 | W3: =IFERROR(U3*V3,"0") -> 0 | Y3: =IFERROR((O3/1000)*Masters!$C$3,"0") -> 59.85 | AA3: =IFERROR(VLOOKUP(L3,Masters!G:H,2,0),"0") -> 30 | AB3: =IFERROR(AA3*N3,"0") -> 90 | AE3: =W3+Y3+AB3+AD3 -> 149.85 | AG3: =M3&"-"&F3 -> 210-0-100Km | AH3: =IFERROR(VLOOKUP(AG3,Masters!N:O,2,0),"0") -> 220.5 | AI3: =AH3*N3 -> 661.5 | AK3: =AI3-AE3 -> 511.65 | AN3: =IFERROR(U3/2,"0") -> 0
A4: =A3+1 -> 3 | B4: 45733 | C4: S/Drona/03/25/02 | D4: 45734 | E4: VLH Marketing | F4: 0-100Km | G4: Karnal | H4: HR38AC7243 | I4: 1109 | J4: Fixed | K4: 1 | L4: 20L Buckets | M4: =IFERROR(VLOOKUP(L4,'Material Master'!B:C,2,0),"") -> 20 | N4: 300 | O4: =IFERROR(M4*N4,"") -> 6000 | P4: Yes | R4: 45717 | U4: 189 | V4: 31 | W4: =IFERROR(U4*V4,"0") -> 5859 | Y4: =IFERROR((O4/1000)*Masters!$C$3,"0") -> 570 | AA4: =IFERROR(VLOOKUP(L4,Masters!G:H,2,0),"0") -> 5 | AB4: =IFERROR(AA4*N4,"0") -> 1500 | AE4: =W4+Y4+AB4+AD4 -> 7929 | AG4: =M4&"-"&F4 -> 20-0-100Km | AH4: =IFERROR(VLOOKUP(AG4,Masters!N:O,2,0),"0") -> 21 | AI4: =AH4*N4 -> 6300 | AK4: =AI4-AE4 -> -1629 | AN4: =IFERROR(U4/2,"0") -> 94.5
A5: =A4+1 -> 4 | B5: 45734 | C5: S/Drona/03/25/03 | D5: 45734 | E5: Johar Automobiles | F5: 101-250Km | G5: Faridabad | H5: HR38AC0599 | I5: 1109 | J5: Fixed | K5: 2 | L5: 20L Buckets | M5: =IFERROR(VLOOKUP(L5,'Material Master'!B:C,2,0),"") -> 20 | N5: 300 | O5: =IFERROR(M5*N5,"") -> 6000 | P5: Yes | R5: 45717 | U5: 321 | V5: 31 | W5: =IFERROR(U5*V5,"0") -> 9951 | Y5: =IFERROR((O5/1000)*Masters!$C$3,"0") -> 570 | AA5: =IFERROR(VLOOKUP(L5,Masters!G:H,2,0),"0") -> 5 | AB5: =IFERROR(AA5*N5,"0") -> 1500 | AE5: =W5+Y5+AB5+AD5 -> 12021 | AG5: =M5&"-"&F5 -> 20-101-250Km | AH5: =IFERROR(VLOOKUP(AG5,Masters!N:O,2,0),"0") -> 40 | AI5: =AH5*N5 -> 12000 | AK5: =AI5-AE5 -> -21 | AN5: =IFERROR(U5/2,"0") -> 160.5
A6: =A5+1 -> 5 | B6: 45734 | C6: S/Drona/03/25/04 | D6: 45734 | E6: Pasco Motors LLP | F6: 0-100Km | G6: New Delhi | H6: HR38AC0263 | I6: 1109 | J6: Fixed | K6: 4 | L6: 20L Buckets | M6: =IFERROR(VLOOKUP(L6,'Material Master'!B:C,2,0),"") -> 20 | N6: 300 | O6: =IFERROR(M6*N6,"") -> 6000 | P6: Yes | R6: 45717 | U6: 139 | V6: 31 | W6: =IFERROR(U6*V6,"0") -> 4309 | Y6: =IFERROR((O6/1000)*Masters!$C$3,"0") -> 570 | AA6: =IFERROR(VLOOKUP(L6,Masters!G:H,2,0),"0") -> 5 | AB6: =IFERROR(AA6*N6,"0") -> 1500 | AE6: =W6+Y6+AB6+AD6 -> 6379 | AG6: =M6&"-"&F6 -> 20-0-100Km | AH6: =IFERROR(VLOOKUP(AG6,Masters!N:O,2,0),"0") -> 21 | AI6: =AH6*N6 -> 6300 | AK6: =AI6-AE6 -> -79 | AN6: =IFERROR(U6/2,"0") -> 69.5
A7: =A6+1 -> 6 | B7: 45734 | C7: S/Drona/03/25/06 | D7: 45736 | E7: Pasco Motors LLP | F7: 0-100Km | G7: New Delhi | H7: HR38AC7243 | I7: 1109 | J7: Fixed | K7: 9 | L7: 20L Buckets | M7: =IFERROR(VLOOKUP(L7,'Material Master'!B:C,2,0),"") -> 20 | N7: 100 | O7: =IFERROR(M7*N7,"") -> 2000 | P7: Yes | R7: 45717 | U7: 146 | V7: 31 | W7: =IFERROR(U7*V7,"0") -> 4526 | Y7: =IFERROR((O7/1000)*Masters!$C$3,"0") -> 190 | AA7: =IFERROR(VLOOKUP(L7,Masters!G:H,2,0),"0") -> 5 | AB7: =IFERROR(AA7*N7,"0") -> 500 | AE7: =W7+Y7+AB7+AD7 -> 5216 | AG7: =M7&"-"&F7 -> 20-0-100Km | AH7: =IFERROR(VLOOKUP(AG7,Masters!N:O,2,0),"0") -> 21 | AI7: =AH7*N7 -> 2100 | AK7: =AI7-AE7 -> -3116 | AN7: =IFERROR(U7/2,"0") -> 73
A8: =A7+1 -> 7 | B8: 45734 | C8: S/Drona/03/25/07 | D8: 45735 | E8: Yuvraj Motors | F8: 101-250Km | G8: Aligarh | H8: HR38AC0263 | I8: 1109 | J8: Fixed | K8: 6 | L8: 20L Buckets | M8: =IFERROR(VLOOKUP(L8,'Material Master'!B:C,2,0),"") -> 20 | N8: 300 | O8: =IFERROR(M8*N8,"") -> 6000 | P8: Yes | R8: 45717 | U8: 372 | V8: 31 | W8: =IFERROR(U8*V8,"0") -> 11532 | Y8: =IFERROR((O8/1000)*Masters!$C$3,"0") -> 570 | AA8: =IFERROR(VLOOKUP(L8,Masters!G:H,2,0),"0") -> 5 | AB8: =IFERROR(AA8*N8,"0") -> 1500 | AE8: =W8+Y8+AB8+AD8 -> 13602 | AG8: =M8&"-"&F8 -> 20-101-250Km | AH8: =IFERROR(VLOOKUP(AG8,Masters!N:O,2,0),"0") -> 40 | AI8: =AH8*N8 -> 12000 | AK8: =AI8-AE8 -> -1602 | AN8: =IFERROR(U8/2,"0") -> 186
A9: =A8+1 -> 8 | B9: 45734 | C9: S/Drona/03/25/08 | D9: 45735 | E9: UP State Road Transport Corporation | F9: 0-100Km | G9: Gaziabad | H9: HR38AC7854 | I9: 1109 | J9: Fixed | K9: 5 | L9: 210L Barrels | M9: =IFERROR(VLOOKUP(L9,'Material Master'!B:C,2,0),"") -> 210 | N9: 30 | O9: =IFERROR(M9*N9,"") -> 6300 | P9: Yes | R9: 45717 | U9: 183 | V9: 31 | W9: =IFERROR(U9*V9,"0") -> 5673 | Y9: =IFERROR((O9/1000)*Masters!$C$3,"0") -> 598.5 | AA9: =IFERROR(VLOOKUP(L9,Masters!G:H,2,0),"0") -> 30 | AB9: =IFERROR(AA9*N9,"0") -> 900 | AE9: =W9+Y9+AB9+AD9 -> 7171.5 | AG9: =M9&"-"&F9 -> 210-0-100Km | AH9: =IFERROR(VLOOKUP(AG9,Masters!N:O,2,0),"0") -> 220.5 | AI9: =AH9*N9 -> 6615 | AK9: =AI9-AE9 -> -556.5 | AN9: =IFERROR(U9/2,"0") -> 91.5
A10: =A9+1 -> 9 | B10: 45734 | C10: S/Drona/03/25/09 | D10: 45735 | E10: UP State Road Transport Corporation | F10: 0-100Km | G10: Gaziabad | H10: HR38AC7243 | I10: 1109 | J10: Fixed | K10: 7 | L10: 210L Barrels | M10: =IFERROR(VLOOKUP(L10,'Material Master'!B:C,2,0),"") -> 210 | N10: 30 | O10: =IFERROR(M10*N10,"") -> 6300 | P10: Yes | R10: 45717 | U10: 166 | V10: 31 | W10: =IFERROR(U10*V10,"0") -> 5146 | Y10: =IFERROR((O10/1000)*Masters!$C$3,"0") -> 598.5 | AA10: =IFERROR(VLOOKUP(L10,Masters!G:H,2,0),"0") -> 30 | AB10: =IFERROR(AA10*N10,"0") -> 900 | AE10: =W10+Y10+AB10+AD10 -> 6644.5 | AG10: =M10&"-"&F10 -> 210-0-100Km | AH10: =IFERROR(VLOOKUP(AG10,Masters!N:O,2,0),"0") -> 220.5 | AI10: =AH10*N10 -> 6615 | AK10: =AI10-AE10 -> -29.5 | AN10: =IFERROR(U10/2,"0") -> 83
A11: =A10+1 -> 10 | B11: 45735 | C11: S/Drona/03/25/10 | D11: 45736 | E11: Sisothiya Automobile | F11: 101-250Km | G11: Dharuhera | H11: HR38AC0599 | I11: 1109 | J11: Fixed | K11: 8 | L11: 20L Buckets | M11: =IFERROR(VLOOKUP(L11,'Material Master'!B:C,2,0),"") -> 20 | N11: 100 | O11: =IFERROR(M11*N11,"") -> 2000 | P11: Yes | R11: 45717 | U11: 243 | V11: 31 | W11: =IFERROR(U11*V11,"0") -> 7533 | Y11: =IFERROR((O11/1000)*Masters!$C$3,"0") -> 190 | AA11: =IFERROR(VLOOKUP(L11,Masters!G:H,2,0),"0") -> 5 | AB11: =IFERROR(AA11*N11,"0") -> 500 | AE11: =W11+Y11+AB11+AD11 -> 8223 | AG11: =M11&"-"&F11 -> 20-101-250Km | AH11: =IFERROR(VLOOKUP(AG11,Masters!N:O,2,0),"0") -> 40 | AI11: =AH11*N11 -> 4000 | AK11: =AI11-AE11 -> -4223 | AN11: =IFERROR(U11/2,"0") -> 121.5
A12: =A11+1 -> 11 | B12: 45735 | C12: S/Drona/03/25/11 | D12: 45736 | E12: Sahni Motors | F12: 0-100Km | G12: Karnal | H12: HR38AC7854 | I12: 1109 | J12: Fixed | K12: 10 | L12: 20L Buckets | M12: =IFERROR(VLOOKUP(L12,'Material Master'!B:C,2,0),"") -> 20 | N12: 200 | O12: =IFERROR(M12*N12,"") -> 4000 | P12: Yes | R12: 45717 | U12: 177 | V12: 31 | W12: =IFERROR(U12*V12,"0") -> 5487 | Y12: =IFERROR((O12/1000)*Masters!$C$3,"0") -> 380 | AA12: =IFERROR(VLOOKUP(L12,Masters!G:H,2,0),"0") -> 5 | AB12: =IFERROR(AA12*N12,"0") -> 1000 | AE12: =W12+Y12+AB12+AD12 -> 6867 | AG12: =M12&"-"&F12 -> 20-0-100Km | AH12: =IFERROR(VLOOKUP(AG12,Masters!N:O,2,0),"0") -> 21 | AI12: =AH12*N12 -> 4200 | AK12: =AI12-AE12 -> -2667 | AN12: =IFERROR(U12/2,"0") -> 88.5
A13: =A12+1 -> 12 | B13: 45735 | C13: S/Drona/03/25/11 | D13: 45736 | E13: Sahni Motors | F13: 0-100Km | G13: Karnal | H13: HR38AC7854 | I13: 1109 | J13: Fixed | K13: 10 | L13: 20L Buckets | M13: =IFERROR(VLOOKUP(L13,'Material Master'!B:C,2,0),"") -> 20 | N13: 100 | O13: =IFERROR(M13*N13,"") -> 2000 | P13: Yes | R13: 45717 | S13: DOUBLE CHALLAN | U13: 0 | V13: 31 | W13: =IFERROR(U13*V13,"0") -> 0 | Y13: =IFERROR((O13/1000)*Masters!$C$3,"0") -> 190 | AA13: =IFERROR(VLOOKUP(L13,Masters!G:H,2,0),"0") -> 5 | AB13: =IFERROR(AA13*N13,"0") -> 500 | AE13: =W13+Y13+AB13+AD13 -> 690 | AG13: =M13&"-"&F13 -> 20-0-100Km | AH13: =IFERROR(VLOOKUP(AG13,Masters!N:O,2,0),"0") -> 21 | AI13: =AH13*N13 -> 2100 | AK13: =AI13-AE13 -> 1410 | AN13: =IFERROR(U13/2,"0") -> 0
A14: =A13+1 -> 13 | B14: 45737 | C14: S/Drona/03/25/12 | D14: 45737 | E14: AA Automobiles Pvt. Ltd. | F14: 0-100Km | G14: Karnal | H14: HR38AC0599 | I14: 1109 | J14: Fixed | K14: 11 | L14: 20L Buckets | M14: =IFERROR(VLOOKUP(L14,'Material Master'!B:C,2,0),"") -> 20 | N14: 300 | O14: =IFERROR(M14*N14,"") -> 6000 | P14: Yes | R14: 45717 | U14: 132 | V14: 31 | W14: =IFERROR(U14*V14,"0") -> 4092 | Y14: =IFERROR((O14/1000)*Masters!$C$3,"0") -> 570 | AA14: =IFERROR(VLOOKUP(L14,Masters!G:H,2,0),"0") -> 5 | AB14: =IFERROR(AA14*N14,"0") -> 1500 | AE14: =W14+Y14+AB14+AD14 -> 6162 | AG14: =M14&"-"&F14 -> 20-0-100Km | AH14: =IFERROR(VLOOKUP(AG14,Masters!N:O,2,0),"0") -> 21 | AI14: =AH14*N14 -> 6300 | AK14: =AI14-AE14 -> 138 | AN14: =IFERROR(U14/2,"0") -> 66
A15: =A14+1 -> 14 | B15: 45737 | C15: S/Drona/03/25/13 | D15: 45737 | E15: Jain Motors Srore | F15: 101-250Km | G15: Tohana | H15: HR38AC0263 | I15: 1109 | J15: Fixed | K15: 12 | L15: 20L Buckets | M15: =IFERROR(VLOOKUP(L15,'Material Master'!B:C,2,0),"") -> 20 | N15: 300 | O15: =IFERROR(M15*N15,"") -> 6000 | P15: Yes | R15: 45717 | U15: 371 | V15: 31 | W15: =IFERROR(U15*V15,"0") -> 11501 | Y15: =IFERROR((O15/1000)*Masters!$C$3,"0") -> 570 | AA15: =IFERROR(VLOOKUP(L15,Masters!G:H,2,0),"0") -> 5 | AB15: =IFERROR(AA15*N15,"0") -> 1500 | AE15: =W15+Y15+AB15+AD15 -> 13571 | AG15: =M15&"-"&F15 -> 20-101-250Km | AH15: =IFERROR(VLOOKUP(AG15,Masters!N:O,2,0),"0") -> 40 | AI15: =AH15*N15 -> 12000 | AK15: =AI15-AE15 -> -1571 | AN15: =IFERROR(U15/2,"0") -> 185.5
A16: =A15+1 -> 15 | B16: 45737 | C16: S/Drona/03/25/14 | D16: 45737 | E16: Shree Shyam Automobiles | F16: 251-400Km | G16: Ferozpur | H16: HR38AC7854 | I16: 1109 | J16: Fixed | K16: 13 | L16: 20L Buckets | M16: =IFERROR(VLOOKUP(L16,'Material Master'!B:C,2,0),"") -> 20 | N16: 300 | O16: =IFERROR(M16*N16,"") -> 6000 | P16: Yes | R16: 45717 | U16: 502 | V16: 31 | W16: =IFERROR(U16*V16,"0") -> 15562 | Y16: =IFERROR((O16/1000)*Masters!$C$3,"0") -> 570 | AA16: =IFERROR(VLOOKUP(L16,Masters!G:H,2,0),"0") -> 5 | AB16: =IFERROR(AA16*N16,"0") -> 1500 | AE16: =W16+Y16+AB16+AD16 -> 17632 | AG16: =M16&"-"&F16 -> 20-251-400Km | AH16: =IFERROR(VLOOKUP(AG16,Masters!N:O,2,0),"0") -> 68 | AI16: =AH16*N16 -> 20400 | AK16: =AI16-AE16 -> 2768 | AN16: =IFERROR(U16/2,"0") -> 251
A17: =A16+1 -> 16 | B17: 45737 | C17: S/Drona/03/25/15 | D17: 45737 | E17: RK Automobiles Private Limited | F17: 0-100Km | G17: Sahibabad | H17: HR38AC7243 | I17: 1109 | J17: Fixed | K17: 14 | L17: 210L Barrels | M17: =IFERROR(VLOOKUP(L17,'Material Master'!B:C,2,0),"") -> 210 | N17: 30 | O17: =IFERROR(M17*N17,"") -> 6300 | P17: Yes | R17: 45717 | U17: 159 | V17: 31 | W17: =IFERROR(U17*V17,"0") -> 4929 | Y17: =IFERROR((O17/1000)*Masters!$C$3,"0") -> 598.5 | AA17: =IFERROR(VLOOKUP(L17,Masters!G:H,2,0),"0") -> 30 | AB17: =IFERROR(AA17*N17,"0") -> 900 | AE17: =W17+Y17+AB17+AD17 -> 6427.5 | AG17: =M17&"-"&F17 -> 210-0-100Km | AH17: =IFERROR(VLOOKUP(AG17,Masters!N:O,2,0),"0") -> 220.5 | AI17: =AH17*N17 -> 6615 | AK17: =AI17-AE17 -> 187.5 | AN17: =IFERROR(U17/2,"0") -> 79.5
A18: =A17+1 -> 17 | B18: 45738 | C18: S/Drona/03/25/16 | D18: 45738 | E18: Metro Motors Pvt Ltd. | F18: 0-100Km | G18: Karnal | H18: HR38AC0263 | I18: 909 | J18: Fixed | K18: 15 | L18: 20L Buckets | M18: =IFERROR(VLOOKUP(L18,'Material Master'!B:C,2,0),"") -> 20 | N18: 200 | O18: =IFERROR(M18*N18,"") -> 4000 | P18: Yes | R18: 45717 | U18: 200 | V18: 31 | W18: =IFERROR(U18*V18,"0") -> 6200 | Y18: =IFERROR((O18/1000)*Masters!$C$3,"0") -> 380 | AA18: =IFERROR(VLOOKUP(L18,Masters!G:H,2,0),"0") -> 5 | AB18: =IFERROR(AA18*N18,"0") -> 1000 | AE18: =W18+Y18+AB18+AD18 -> 7580 | AG18: =M18&"-"&F18 -> 20-0-100Km | AH18: =IFERROR(VLOOKUP(AG18,Masters!N:O,2,0),"0") -> 21 | AI18: =AH18*N18 -> 4200 | AK18: =AI18-AE18 -> -3380 | AN18: =IFERROR(U18/2,"0") -> 100
A19: =A18+1 -> 18 | B19: 45738 | C19: S/Drona/03/25/17 | D19: 45738 | E19: Pasco Motors LLP | F19: 0-100Km | G19: New Delhi | H19: HR38AC0599 | I19: 1109 | J19: Fixed | K19: 16 | L19: 20L Buckets | M19: =IFERROR(VLOOKUP(L19,'Material Master'!B:C,2,0),"") -> 20 | N19: 300 | O19: =IFERROR(M19*N19,"") -> 6000 | P19: Yes | R19: 45717 | U19: 171 | V19: 31 | W19: =IFERROR(U19*V19,"0") -> 5301 | Y19: =IFERROR((O19/1000)*Masters!$C$3,"0") -> 570 | AA19: =IFERROR(VLOOKUP(L19,Masters!G:H,2,0),"0") -> 5 | AB19: =IFERROR(AA19*N19,"0") -> 1500 | AE19: =W19+Y19+AB19+AD19 -> 7371 | AG19: =M19&"-"&F19 -> 20-0-100Km | AH19: =IFERROR(VLOOKUP(AG19,Masters!N:O,2,0),"0") -> 21 | AI19: =AH19*N19 -> 6300 | AK19: =AI19-AE19 -> -1071 | AN19: =IFERROR(U19/2,"0") -> 85.5
A20: =A19+1 -> 19 | B20: 45740 | C20: S/Drona/03/25/18 | D20: 45740 | E20: Sahni Motors | F20: 0-100Km | G20: Karnal | H20: HR38AC7243 | I20: 1109 | J20: Fixed | K20: 17 | L20: 20L Buckets | M20: =IFERROR(VLOOKUP(L20,'Material Master'!B:C,2,0),"") -> 20 | N20: 300 | O20: =IFERROR(M20*N20,"") -> 6000 | P20: Yes | R20: 45717 | U20: 179 | V20: 31 | W20: =IFERROR(U20*V20,"0") -> 5549 | Y20: =IFERROR((O20/1000)*Masters!$C$3,"0") -> 570 | AA20: =IFERROR(VLOOKUP(L20,Masters!G:H,2,0),"0") -> 5 | AB20: =IFERROR(AA20*N20,"0") -> 1500 | AE20: =W20+Y20+AB20+AD20 -> 7619 | AG20: =M20&"-"&F20 -> 20-0-100Km | AH20: =IFERROR(VLOOKUP(AG20,Masters!N:O,2,0),"0") -> 21 | AI20: =AH20*N20 -> 6300 | AK20: =AI20-AE20 -> -1319 | AN20: =IFERROR(U20/2,"0") -> 89.5
A21: =A20+1 -> 20 | B21: 45740 | C21: S/Drona/03/25/19 | D21: 45740 | E21: mangalam auto | F21: 101-250Km | G21: Palwal | H21: HR38AC0263 | I21: 1109 | J21: Fixed | K21: 18 | L21: 20L Buckets | M21: =IFERROR(VLOOKUP(L21,'Material Master'!B:C,2,0),"") -> 20 | N21: 300 | O21: =IFERROR(M21*N21,"") -> 6000 | P21: Yes | R21: 45717 | U21: 320 | V21: 31 | W21: =IFERROR(U21*V21,"0") -> 9920 | Y21: =IFERROR((O21/1000)*Masters!$C$3,"0") -> 570 | AA21: =IFERROR(VLOOKUP(L21,Masters!G:H,2,0),"0") -> 5 | AB21: =IFERROR(AA21*N21,"0") -> 1500 | AE21: =W21+Y21+AB21+AD21 -> 11990 | AG21: =M21&"-"&F21 -> 20-101-250Km | AH21: =IFERROR(VLOOKUP(AG21,Masters!N:O,2,0),"0") -> 40 | AI21: =AH21*N21 -> 12000 | AK21: =AI21-AE21 -> 10 | AN21: =IFERROR(U21/2,"0") -> 160
A22: =A21+1 -> 21 | B22: 45740 | C22: S/Drona/03/25/20 | D22: 45740 | E22: UP State Road Transport Corporation | F22: 101-250Km | G22: Saharanpur | H22: HR38AC0599 | I22: 1109 | J22: Fixed | K22: 19 | L22: 210L Barrels | M22: =IFERROR(VLOOKUP(L22,'Material Master'!B:C,2,0),"") -> 210 | N22: 30 | O22: =IFERROR(M22*N22,"") -> 6300 | P22: Yes | R22: 45717 | U22: 388 | V22: 31 | W22: =IFERROR(U22*V22,"0") -> 12028 | Y22: =IFERROR((O22/1000)*Masters!$C$3,"0") -> 598.5 | AA22: =IFERROR(VLOOKUP(L22,Masters!G:H,2,0),"0") -> 30 | AB22: =IFERROR(AA22*N22,"0") -> 900 | AE22: =W22+Y22+AB22+AD22 -> 13526.5 | AG22: =M22&"-"&F22 -> 210-101-250Km | AH22: =IFERROR(VLOOKUP(AG22,Masters!N:O,2,0),"0") -> 420 | AI22: =AH22*N22 -> 12600 | AK22: =AI22-AE22 -> -926.5 | AN22: =IFERROR(U22/2,"0") -> 194
A23: =A22+1 -> 22 | B23: 45741 | C23: S/Drona/03/25/22 | D23: 45741 | E23: Raj Enterprize | F23: 101-250Km | G23: Greater Noida | H23: HR38AC7854 | I23: 1109 | J23: Fixed | K23: 20 | L23: 20L Buckets | M23: =IFERROR(VLOOKUP(L23,'Material Master'!B:C,2,0),"") -> 20 | N23: 100 | O23: =IFERROR(M23*N23,"") -> 2000 | P23: Yes | R23: 45717 | U23: 224 | V23: 31 | W23: =IFERROR(U23*V23,"0") -> 6944 | Y23: =IFERROR((O23/1000)*Masters!$C$3,"0") -> 190 | AA23: =IFERROR(VLOOKUP(L23,Masters!G:H,2,0),"0") -> 5 | AB23: =IFERROR(AA23*N23,"0") -> 500 | AE23: =W23+Y23+AB23+AD23 -> 7634 | AG23: =M23&"-"&F23 -> 20-101-250Km | AH23: =IFERROR(VLOOKUP(AG23,Masters!N:O,2,0),"0") -> 40 | AI23: =AH23*N23 -> 4000 | AK23: =AI23-AE23 -> -3634 | AN23: =IFERROR(U23/2,"0") -> 112
A24: =A23+1 -> 23 | B24: 45741 | C24: S/Drona/03/25/22 | D24: 45741 | E24: Ashok Ventures LLP | F24: 101-250Km | G24: Gautam Buddha Nagar | H24: HR38AC7854 | I24: 1109 | J24: Fixed | K24: 21 | L24: 20L Buckets | M24: =IFERROR(VLOOKUP(L24,'Material Master'!B:C,2,0),"") -> 20 | N24: 100 | O24: =IFERROR(M24*N24,"") -> 2000 | P24: Yes | R24: 45717 | U24: 0 | V24: 31 | W24: =IFERROR(U24*V24,"0") -> 0 | Y24: =IFERROR((O24/1000)*Masters!$C$3,"0") -> 190 | AA24: =IFERROR(VLOOKUP(L24,Masters!G:H,2,0),"0") -> 5 | AB24: =IFERROR(AA24*N24,"0") -> 500 | AE24: =W24+Y24+AB24+AD24 -> 690 | AG24: =M24&"-"&F24 -> 20-101-250Km | AH24: =IFERROR(VLOOKUP(AG24,Masters!N:O,2,0),"0") -> 40 | AI24: =AH24*N24 -> 4000 | AK24: =AI24-AE24 -> 3310 | AN24: =IFERROR(U24/2,"0") -> 0
A25: =A24+1 -> 24 | B25: 45741 | C25: S/Drona/03/25/23 | D25: 45741 | E25: Pasco Motors LLP | F25: 0-100Km | G25: New Delhi | H25: HR38AC7243 | I25: 1109 | J25: Fixed | K25: 22 | L25: 20L Buckets | M25: =IFERROR(VLOOKUP(L25,'Material Master'!B:C,2,0),"") -> 20 | N25: 300 | O25: =IFERROR(M25*N25,"") -> 6000 | P25: Yes | R25: 45717 | U25: 143 | V25: 31 | W25: =IFERROR(U25*V25,"0") -> 4433 | Y25: =IFERROR((O25/1000)*Masters!$C$3,"0") -> 570 | AA25: =IFERROR(VLOOKUP(L25,Masters!G:H,2,0),"0") -> 5 | AB25: =IFERROR(AA25*N25,"0") -> 1500 | AE25: =W25+Y25+AB25+AD25 -> 6503 | AG25: =M25&"-"&F25 -> 20-0-100Km | AH25: =IFERROR(VLOOKUP(AG25,Masters!N:O,2,0),"0") -> 21 | AI25: =AH25*N25 -> 6300 | AK25: =AI25-AE25 -> -203 | AN25: =IFERROR(U25/2,"0") -> 71.5
... A29: =A28+1 -> 28 | B29: 45742 | C29: s/Drona/03/25/30 | D29: 45742 | E29: Anand motors | F29: 0-100Km | G29: gohana | H29: HR38AC7243 | I29: 1109 | J29: Fixed | K29: 26 | L29: 20L Buckets | M29: =IFERROR(VLOOKUP(L29,'Material Master'!B:C,2,0),"") -> 20 | N29: 300 | O29: =IFERROR(M29*N29,"") -> 6000 | P29: Yes | R29: 45717 | U29: 172 | V29: 31 | W29: =IFERROR(U29*V29,"0") -> 5332 | Y29: =IFERROR((O29/1000)*Masters!$C$3,"0") -> 570 | AA29: =IFERROR(VLOOKUP(L29,Masters!G:H,2,0),"0") -> 5 | AB29: =IFERROR(AA29*N29,"0") -> 1500 | AE29: =W29+Y29+AB29+AD29 -> 7402 | AG29: =M29&"-"&F29 -> 20-0-100Km | AH29: =IFERROR(VLOOKUP(AG29,Masters!N:O,2,0),"0") -> 21 | AI29: =AH29*N29 -> 6300 | AK29: =AI29-AE29 -> -1102 | AN29: =IFERROR(U29/2,"0") -> 86
A30: =A29+1 -> 29 | B30: 45742 | C30: s/Drona/03/25/27 | D30: 45742 | E30: Sanghi Automobiles | F30: 101-250Km | G30: Rewari | H30: HR69D3754 | I30: 709 | J30: Market | K30: 24 | L30: 20L Buckets | M30: =IFERROR(VLOOKUP(L30,'Material Master'!B:C,2,0),"") -> 20 | N30: 100 | O30: =IFERROR(M30*N30,"") -> 2000 | P30: Yes | R30: 45717 | S30: Market | U30: 0 | V30: 31 | W30: 4500 | Y30: =IFERROR((O30/1000)*Masters!$C$3,"0") -> 190 | AA30: =IFERROR(VLOOKUP(L30,Masters!G:H,2,0),"0") -> 5 | AB30: =IFERROR(AA30*N30,"0") -> 500 | AE30: =W30+Y30+AB30+AD30 -> 5190 | AG30: =M30&"-"&F30 -> 20-101-250Km | AH30: =IFERROR(VLOOKUP(AG30,Masters!N:O,2,0),"0") -> 40 | AI30: =AH30*N30 -> 4000 | AK30: =AI30-AE30 -> -1190 | AN30: =IFERROR(U30/2,"0") -> 0
A31: =A30+1 -> 30 | B31: 45742 | C31: s/Drona/03/25/28 | D31: 45742 | E31: Hind Motor | F31: 101-250Km | G31: Hisar | H31: HR39F5155 | I31: 1109 | J31: Market | K31: 25 | L31: 20L Buckets | M31: =IFERROR(VLOOKUP(L31,'Material Master'!B:C,2,0),"") -> 20 | N31: 300 | O31: =IFERROR(M31*N31,"") -> 6000 | P31: Yes | R31: 45717 | S31: Market | U31: 0 | V31: 31 | W31: 8500 | Y31: =IFERROR((O31/1000)*Masters!$C$3,"0") -> 570 | AA31: =IFERROR(VLOOKUP(L31,Masters!G:H,2,0),"0") -> 5 | AB31: =IFERROR(AA31*N31,"0") -> 1500 | AE31: =W31+Y31+AB31+AD31 -> 10570 | AG31: =M31&"-"&F31 -> 20-101-250Km | AH31: =IFERROR(VLOOKUP(AG31,Masters!N:O,2,0),"0") -> 40 | AI31: =AH31*N31 -> 12000 | AK31: =AI31-AE31 -> 1430 | AN31: =IFERROR(U31/2,"0") -> 0
A32: =A31+1 -> 31 | B32: 45742 | C32: s/Drona/03/25/31 | D32: 45743 | E32: ganganagar vehicles pvt ltd | F32: 0-100Km | G32: Karnal | H32: HR38AC0263 | I32: 1109 | J32: Fixed | K32: 31 | L32: 210L Barrels | M32: =IFERROR(VLOOKUP(L32,'Material Master'!B:C,2,0),"") -> 210 | N32: 30 | O32: =IFERROR(M32*N32,"") -> 6300 | P32: Yes | R32: 45717 | U32: 180 | V32: 31 | W32: =IFERROR(U32*V32,"0") -> 5580 | Y32: =IFERROR((O32/1000)*Masters!$C$3,"0") -> 598.5 | AA32: =IFERROR(VLOOKUP(L32,Masters!G:H,2,0),"0") -> 30 | AB32: =IFERROR(AA32*N32,"0") -> 900 | AE32: =W32+Y32+AB32+AD32 -> 7078.5 | AG32: =M32&"-"&F32 -> 210-0-100Km | AH32: =IFERROR(VLOOKUP(AG32,Masters!N:O,2,0),"0") -> 220.5 | AI32: =AH32*N32 -> 6615 | AK32: =AI32-AE32 -> -463.5 | AN32: =IFERROR(U32/2,"0") -> 90
A33: =A32+1 -> 32 | B33: 45742 | C33: s/Drona/03/25/32 | D33: 45743 | E33: sumit auto store | F33: 0-100Km | G33: rohtak | H33: HR38AC7854 | I33: 1109 | J33: Fixed | K33: 29 | L33: 20L Buckets | M33: =IFERROR(VLOOKUP(L33,'Material Master'!B:C,2,0),"") -> 20 | N33: 300 | O33: =IFERROR(M33*N33,"") -> 6000 | P33: Yes | R33: 45717 | U33: 179 | V33: 31 | W33: =IFERROR(U33*V33,"0") -> 5549 | Y33: =IFERROR((O33/1000)*Masters!$C$3,"0") -> 570 | AA33: =IFERROR(VLOOKUP(L33,Masters!G:H,2,0),"0") -> 5 | AB33: =IFERROR(AA33*N33,"0") -> 1500 | AE33: =W33+Y33+AB33+AD33 -> 7619 | AG33: =M33&"-"&F33 -> 20-0-100Km | AH33: =IFERROR(VLOOKUP(AG33,Masters!N:O,2,0),"0") -> 21 | AI33: =AH33*N33 -> 6300 | AK33: =AI33-AE33 -> -1319 | AN33: =IFERROR(U33/2,"0") -> 89.5
A34: =A33+1 -> 33 | B34: 45742 | C34: s/Drona/03/25/33 | D34: 45743 | E34: raju motor store | F34: 0-100Km | G34: sonipat | H34: HR38AC0599 | I34: 1109 | J34: Fixed | K34: 30 | L34: 20L Buckets | M34: =IFERROR(VLOOKUP(L34,'Material Master'!B:C,2,0),"") -> 20 | N34: 300 | O34: =IFERROR(M34*N34,"") -> 6000 | P34: Yes | R34: 45717 | U34: 36 | V34: 31 | W34: =IFERROR(U34*V34,"0") -> 1116 | Y34: =IFERROR((O34/1000)*Masters!$C$3,"0") -> 570 | AA34: =IFERROR(VLOOKUP(L34,Masters!G:H,2,0),"0") -> 5 | AB34: =IFERROR(AA34*N34,"0") -> 1500 | AE34: =W34+Y34+AB34+AD34 -> 3186 | AG34: =M34&"-"&F34 -> 20-0-100Km | AH34: =IFERROR(VLOOKUP(AG34,Masters!N:O,2,0),"0") -> 21 | AI34: =AH34*N34 -> 6300 | AK34: =AI34-AE34 -> 3114 | AN34: =IFERROR(U34/2,"0") -> 18
A35: =A34+1 -> 34 | B35: 45743 | C35: s/Drona/03/25/34 | D35: 45756 | E35: hloc auto parts pvt.ltd. | F35: 0-100km | G35: delhi | H35: HR38AC0263 | I35: 1109 | J35: Fixed | K35: 75 | L35: 20L Buckets | M35: =IFERROR(VLOOKUP(L35,'Material Master'!B:C,2,0),"") -> 20 | N35: 300 | O35: =IFERROR(M35*N35,"") -> 6000 | P35: Yes | R35: 45717 | U35: 74 | V35: 31 | W35: =IFERROR(U35*V35,"0") -> 2294 | Y35: =IFERROR((O35/1000)*Masters!$C$3,"0") -> 570 | AA35: =IFERROR(VLOOKUP(L35,Masters!G:H,2,0),"0") -> 5 | AB35: =IFERROR(AA35*N35,"0") -> 1500 | AE35: =W35+Y35+AB35+AD35 -> 4364 | AG35: =M35&"-"&F35 -> 20-0-100km | AH35: =IFERROR(VLOOKUP(AG35,Masters!N:O,2,0),"0") -> 21 | AI35: =AH35*N35 -> 6300 | AK35: =AI35-AE35 -> 1936 | AN35: =IFERROR(U35/2,"0") -> 37
A36: =A35+1 -> 35 | B36: 45743 | C36: s/Drona/03/25/35 | D36: 45757 | E36: hloc auto parts pvt.ltd. | F36: 0-100km | G36: delhi | H36: HR38AC7854 | I36: 1109 | J36: Fixed | K36: 78 | L36: 20L Buckets | M36: =IFERROR(VLOOKUP(L36,'Material Master'!B:C,2,0),"") -> 20 | N36: 300 | O36: =IFERROR(M36*N36,"") -> 6000 | P36: Yes | R36: 45717 | U36: 75 | V36: 31 | W36: =IFERROR(U36*V36,"0") -> 2325 | Y36: =IFERROR((O36/1000)*Masters!$C$3,"0") -> 570 | AA36: =IFERROR(VLOOKUP(L36,Masters!G:H,2,0),"0") -> 5 | AB36: =IFERROR(AA36*N36,"0") -> 1500 | AE36: =W36+Y36+AB36+AD36 -> 4395 | AG36: =M36&"-"&F36 -> 20-0-100km | AH36: =IFERROR(VLOOKUP(AG36,Masters!N:O,2,0),"0") -> 21 | AI36: =AH36*N36 -> 6300 | AK36: =AI36-AE36 -> 1905 | AN36: =IFERROR(U36/2,"0") -> 37.5
A37: =A36+1 -> 36 | B37: 45743 | C37: s/Drona/03/25/36 | D37: 45762 | E37: hloc auto parts pvt.ltd. | F37: 0-100km | G37: delhi | H37: hR38AC7243 | I37: 1109 | J37: Fixed | K37: 88 | L37: 20L Buckets | M37: =IFERROR(VLOOKUP(L37,'Material Master'!B:C,2,0),"") -> 20 | N37: 300 | O37: =IFERROR(M37*N37,"") -> 6000 | P37: Yes | R37: 45717 | U37: 74 | V37: 31 | W37: =IFERROR(U37*V37,"0") -> 2294 | Y37: =IFERROR((O37/1000)*Masters!$C$3,"0") -> 570 | AA37: =IFERROR(VLOOKUP(L37,Masters!G:H,2,0),"0") -> 5 | AB37: =IFERROR(AA37*N37,"0") -> 1500 | AE37: =W37+Y37+AB37+AD37 -> 4364 | AG37: =M37&"-"&F37 -> 20-0-100km | AH37: =IFERROR(VLOOKUP(AG37,Masters!N:O,2,0),"0") -> 21 | AI37: =AH37*N37 -> 6300 | AK37: =AI37-AE37 -> 1936 | AN37: =IFERROR(U37/2,"0") -> 37
A38: =A37+1 -> 37 | B38: 45743 | C38: s/Drona/03/25/37 | D38: 45766 | E38: hloc auto parts pvt.ltd. | F38: 0-100km | G38: delhi | H38: hR38AC7854 | I38: 1109 | J38: Fixed | K38: 100 | L38: 20L Buckets | M38: =IFERROR(VLOOKUP(L38,'Material Master'!B:C,2,0),"") -> 20 | N38: 300 | O38: =IFERROR(M38*N38,"") -> 6000 | P38: Yes | R38: 45717 | U38: 67 | V38: 31 | W38: =IFERROR(U38*V38,"0") -> 2077 | Y38: =IFERROR((O38/1000)*Masters!$C$3,"0") -> 570 | AA38: =IFERROR(VLOOKUP(L38,Masters!G:H,2,0),"0") -> 5 | AB38: =IFERROR(AA38*N38,"0") -> 1500 | AE38: =W38+Y38+AB38+AD38 -> 4147 | AG38: =M38&"-"&F38 -> 20-0-100km | AH38: =IFERROR(VLOOKUP(AG38,Masters!N:O,2,0),"0") -> 21 | AI38: =AH38*N38 -> 6300 | AK38: =AI38-AE38 -> 2153 | AN38: =IFERROR(U38/2,"0") -> 33.5
A39: =A38+1 -> 38 | B39: 45743 | C39: s/Drona/03/25/38 | D39: 45769 | E39: hloc auto parts pvt.ltd. | F39: 0-100km | G39: delhi | H39: hR38AC0263 | I39: 1109 | J39: Fixed | K39: 105 | L39: 20L Buckets | M39: =IFERROR(VLOOKUP(L39,'Material Master'!B:C,2,0),"") -> 20 | N39: 300 | O39: =IFERROR(M39*N39,"") -> 6000 | P39: Yes | R39: 45717 | U39: 90 | V39: 31 | W39: =IFERROR(U39*V39,"0") -> 2790 | Y39: =IFERROR((O39/1000)*Masters!$C$3,"0") -> 570 | AA39: =IFERROR(VLOOKUP(L39,Masters!G:H,2,0),"0") -> 5 | AB39: =IFERROR(AA39*N39,"0") -> 1500 | AE39: =W39+Y39+AB39+AD39 -> 4860 | AG39: =M39&"-"&F39 -> 20-0-100km | AH39: =IFERROR(VLOOKUP(AG39,Masters!N:O,2,0),"0") -> 21 | AI39: =AH39*N39 -> 6300 | AK39: =AI39-AE39 -> 1440 | AN39: =IFERROR(U39/2,"0") -> 45
A40: =A39+1 -> 39 | B40: 45744 | C40: s/Drona/03/25/39 | D40: 45744 | E40: ashoka motors | F40: 101-250Km | G40: Hisar | H40: HR38AC0599 | I40: 1109 | J40: Fixed | K40: 35 | L40: 20L Buckets | M40: =IFERROR(VLOOKUP(L40,'Material Master'!B:C,2,0),"") -> 20 | N40: 300 | O40: =IFERROR(M40*N40,"") -> 6000 | P40: Yes | R40: 45717 | U40: 372 | V40: 31 | W40: =IFERROR(U40*V40,"0") -> 11532 | Y40: =IFERROR((O40/1000)*Masters!$C$3,"0") -> 570 | AA40: =IFERROR(VLOOKUP(L40,Masters!G:H,2,0),"0") -> 5 | AB40: =IFERROR(AA40*N40,"0") -> 1500 | AE40: =W40+Y40+AB40+AD40 -> 13602 | AG40: =M40&"-"&F40 -> 20-101-250Km | AH40: =IFERROR(VLOOKUP(AG40,Masters!N:O,2,0),"0") -> 40 | AI40: =AH40*N40 -> 12000 | AK40: =AI40-AE40 -> -1602 | AN40: =IFERROR(U40/2,"0") -> 186
A41: =A40+1 -> 40 | B41: 45744 | C41: s/Drona/03/25/40 | D41: 45744 | E41: pcj motors | F41: 101-250Km | G41: muzaffarnagar | H41: HR38X6465 | I41: 709 | J41: Fixed | K41: 33 | L41: 20L Buckets | M41: =IFERROR(VLOOKUP(L41,'Material Master'!B:C,2,0),"") -> 20 | N41: 100 | O41: =IFERROR(M41*N41,"") -> 2000 | P41: Yes | R41: 45717 | U41: 280 | V41: 31 | W41: =IFERROR(U41*V41,"0") -> 8680 | Y41: =IFERROR((O41/1000)*Masters!$C$3,"0") -> 190 | AA41: =IFERROR(VLOOKUP(L41,Masters!G:H,2,0),"0") -> 5 | AB41: =IFERROR(AA41*N41,"0") -> 500 | AE41: =W41+Y41+AB41+AD41 -> 9370 | AG41: =M41&"-"&F41 -> 20-101-250Km | AH41: =IFERROR(VLOOKUP(AG41,Masters!N:O,2,0),"0") -> 40 | AI41: =AH41*N41 -> 4000 | AK41: =AI41-AE41 -> -5370 | AN41: =IFERROR(U41/2,"0") -> 140
A42: =A41+1 -> 41 | B42: 45744 | C42: s/Drona/03/25/41 | D42: 45744 | E42: Sahni Motors | F42: 0-100Km | G42: Karnal | H42: HR38AC7243 | I42: 1109 | J42: Fixed | K42: 34 | L42: 20L Buckets | M42: =IFERROR(VLOOKUP(L42,'Material Master'!B:C,2,0),"") -> 20 | N42: 300 | O42: =IFERROR(M42*N42,"") -> 6000 | P42: Yes | R42: 45717 | U42: 179 | V42: 31 | W42: =IFERROR(U42*V42,"0") -> 5549 | Y42: =IFERROR((O42/1000)*Masters!$C$3,"0") -> 570 | AA42: =IFERROR(VLOOKUP(L42,Masters!G:H,2,0),"0") -> 5 | AB42: =IFERROR(AA42*N42,"0") -> 1500 | AE42: =W42+Y42+AB42+AD42 -> 7619 | AG42: =M42&"-"&F42 -> 20-0-100Km | AH42: =IFERROR(VLOOKUP(AG42,Masters!N:O,2,0),"0") -> 21 | AI42: =AH42*N42 -> 6300 | AK42: =AI42-AE42 -> -1319 | AN42: =IFERROR(U42/2,"0") -> 89.5
A43: =A42+1 -> 42 | B43: 45744 | C43: s/Drona/03/25/42 | D43: 45744 | E43: laxmi agencies | F43: 0-100Km | G43: pilkhuwa | H43: HR38AC7854 | I43: 909 | J43: Fixed | K43: 32 | L43: 20L Buckets | M43: =IFERROR(VLOOKUP(L43,'Material Master'!B:C,2,0),"") -> 20 | N43: 200 | O43: =IFERROR(M43*N43,"") -> 4000 | P43: Yes | R43: 45717 | U43: 175 | V43: 31 | W43: =IFERROR(U43*V43,"0") -> 5425 | Y43: =IFERROR((O43/1000)*Masters!$C$3,"0") -> 380 | AA43: =IFERROR(VLOOKUP(L43,Masters!G:H,2,0),"0") -> 5 | AB43: =IFERROR(AA43*N43,"0") -> 1000 | AE43: =W43+Y43+AB43+AD43 -> 6805 | AG43: =M43&"-"&F43 -> 20-0-100Km | AH43: =IFERROR(VLOOKUP(AG43,Masters!N:O,2,0),"0") -> 21 | AI43: =AH43*N43 -> 4200 | AK43: =AI43-AE43 -> -2605 | AN43: =IFERROR(U43/2,"0") -> 87.5
... A61: =A60+1 -> 60 | B61: 45747 | C61: s/Drona/03/25/61 | D61: 45749 | E61: ashoka motors | F61: 101-250Km | G61: Hisar | H61: HR38AC7243 | I61: 1109 | J61: Fixed | K61: 58 | L61: 20L Buckets | M61: =IFERROR(VLOOKUP(L61,'Material Master'!B:C,2,0),"") -> 20 | N61: 300 | O61: =IFERROR(M61*N61,"") -> 6000 | P61: Yes | R61: 45717 | U61: 308 | V61: 31 | W61: =IFERROR(U61*V61,"0") -> 9548 | Y61: =IFERROR((O61/1000)*Masters!$C$3,"0") -> 570 | AA61: =IFERROR(VLOOKUP(L61,Masters!G:H,2,0),"0") -> 5 | AB61: =IFERROR(AA61*N61,"0") -> 1500 | AE61: =W61+Y61+AB61+AD61 -> 11618 | AG61: =M61&"-"&F61 -> 20-101-250Km | AH61: =IFERROR(VLOOKUP(AG61,Masters!N:O,2,0),"0") -> 40 | AI61: =AH61*N61 -> 12000 | AK61: =AI61-AE61 -> 382 | AN61: =IFERROR(U61/2,"0") -> 154
A62: =A61+1 -> 61 | B62: 45747 | C62: s/Drona/03/25/62 | D62: 45748 | E62: vijay automobile | F62: 101-250Km | G62: shahpura | H62: RJ32GB5198 | I62: 2515 | J62: Market | K62: 50 | L62: 20L Buckets | M62: =IFERROR(VLOOKUP(L62,'Material Master'!B:C,2,0),"") -> 20 | N62: 600 | O62: =IFERROR(M62*N62,"") -> 12000 | P62: Yes | R62: 45717 | S62: Market | U62: 0 | V62: 31 | W62: 15000 | Y62: =IFERROR((O62/1000)*Masters!$C$3,"0") -> 1140 | AA62: =IFERROR(VLOOKUP(L62,Masters!G:H,2,0),"0") -> 5 | AB62: =IFERROR(AA62*N62,"0") -> 3000 | AE62: =W62+Y62+AB62+AD62 -> 19140 | AG62: =M62&"-"&F62 -> 20-101-250Km | AH62: =IFERROR(VLOOKUP(AG62,Masters!N:O,2,0),"0") -> 40 | AI62: =AH62*N62 -> 24000 | AK62: =AI62-AE62 -> 4860 | AN62: =IFERROR(U62/2,"0") -> 0
A63: =A62+1 -> 62 | B63: 45747 | C63: s/Drona/03/25/63 | D63: 45750 | E63: vijay automobile | F63: 101-250Km | G63: shahpura | H63: Gj02xx9199 | I63: 2515 | J63: Market | K63: 59 | L63: 20L Buckets | M63: =IFERROR(VLOOKUP(L63,'Material Master'!B:C,2,0),"") -> 20 | N63: 600 | O63: =IFERROR(M63*N63,"") -> 12000 | P63: Yes | R63: 45717 | S63: Market | U63: 0 | V63: 31 | W63: 15000 | Y63: =IFERROR((O63/1000)*Masters!$C$3,"0") -> 1140 | AA63: =IFERROR(VLOOKUP(L63,Masters!G:H,2,0),"0") -> 5 | AB63: =IFERROR(AA63*N63,"0") -> 3000 | AE63: =W63+Y63+AB63+AD63 -> 19140 | AG63: =M63&"-"&F63 -> 20-101-250Km | AH63: =IFERROR(VLOOKUP(AG63,Masters!N:O,2,0),"0") -> 40 | AI63: =AH63*N63 -> 24000 | AK63: =AI63-AE63 -> 4860 | AN63: =IFERROR(U63/2,"0") -> 0
A64: =A63+1 -> 63 | B64: 45747 | C64: s/Drona/03/25/64 | D64: 45748 | E64: vijay automobile | F64: 101-250Km | G64: shahpura | H64: RJ14GK8841 | I64: 2515 | J64: Market | K64: 51 | L64: 20L Buckets | M64: =IFERROR(VLOOKUP(L64,'Material Master'!B:C,2,0),"") -> 20 | N64: 600 | O64: =IFERROR(M64*N64,"") -> 12000 | P64: Yes | R64: 45717 | S64: Market | U64: 0 | V64: 31 | W64: 15000 | Y64: =IFERROR((O64/1000)*Masters!$C$3,"0") -> 1140 | AA64: =IFERROR(VLOOKUP(L64,Masters!G:H,2,0),"0") -> 5 | AB64: =IFERROR(AA64*N64,"0") -> 3000 | AE64: =W64+Y64+AB64+AD64 -> 19140 | AG64: =M64&"-"&F64 -> 20-101-250Km | AH64: =IFERROR(VLOOKUP(AG64,Masters!N:O,2,0),"0") -> 40 | AI64: =AH64*N64 -> 24000 | AK64: =AI64-AE64 -> 4860 | AN64: =IFERROR(U64/2,"0") -> 0
A65: =A64+1 -> 64 | B65: 45747 | C65: s/Drona/03/25/65 | D65: 45751 | E65: vijay automobile | F65: 101-250Km | G65: shahpura | H65: RJ14GQ2021 | I65: 2515 | J65: Market | K65: 64 | L65: 20L Buckets | M65: =IFERROR(VLOOKUP(L65,'Material Master'!B:C,2,0),"") -> 20 | N65: 600 | O65: =IFERROR(M65*N65,"") -> 12000 | P65: Yes | R65: 45717 | S65: Market | U65: 0 | V65: 31 | W65: 15000 | Y65: =IFERROR((O65/1000)*Masters!$C$3,"0") -> 1140 | AA65: =IFERROR(VLOOKUP(L65,Masters!G:H,2,0),"0") -> 5 | AB65: =IFERROR(AA65*N65,"0") -> 3000 | AE65: =W65+Y65+AB65+AD65 -> 19140 | AG65: =M65&"-"&F65 -> 20-101-250Km | AH65: =IFERROR(VLOOKUP(AG65,Masters!N:O,2,0),"0") -> 40 | AI65: =AH65*N65 -> 24000 | AK65: =AI65-AE65 -> 4860 | AN65: =IFERROR(U65/2,"0") -> 0
A66: =A65+1 -> 65 | B66: 45747 | C66: s/Drona/03/25/66 | D66: 45751 | E66: vijay automobile | F66: 101-250Km | G66: shahpura | H66: RJ32GC7626 | I66: 2515 | J66: Market | K66: 62 | L66: 20L Buckets | M66: =IFERROR(VLOOKUP(L66,'Material Master'!B:C,2,0),"") -> 20 | N66: 600 | O66: =IFERROR(M66*N66,"") -> 12000 | P66: Yes | R66: 45717 | S66: Market | U66: 0 | V66: 31 | W66: 15000 | Y66: =IFERROR((O66/1000)*Masters!$C$3,"0") -> 1140 | AA66: =IFERROR(VLOOKUP(L66,Masters!G:H,2,0),"0") -> 5 | AB66: =IFERROR(AA66*N66,"0") -> 3000 | AE66: =W66+Y66+AB66+AD66 -> 19140 | AG66: =M66&"-"&F66 -> 20-101-250Km | AH66: =IFERROR(VLOOKUP(AG66,Masters!N:O,2,0),"0") -> 40 | AI66: =AH66*N66 -> 24000 | AK66: =AI66-AE66 -> 4860 | AN66: =IFERROR(U66/2,"0") -> 0
A67: =A66+1 -> 66 | B67: 45747 | C67: s/Drona/03/25/67 | D67: 45752 | E67: vijay automobile | F67: 101-250Km | G67: shahpura | H67: HR38AC0599 | I67: 1109 | J67: Fixed | K67: 68 | L67: 20L Buckets | M67: =IFERROR(VLOOKUP(L67,'Material Master'!B:C,2,0),"") -> 20 | N67: 300 | O67: =IFERROR(M67*N67,"") -> 6000 | P67: Yes | R67: 45717 | U67: 485 | V67: 31 | W67: =IFERROR(U67*V67,"0") -> 15035 | Y67: =IFERROR((O67/1000)*Masters!$C$3,"0") -> 570 | AA67: =IFERROR(VLOOKUP(L67,Masters!G:H,2,0),"0") -> 5 | AB67: =IFERROR(AA67*N67,"0") -> 1500 | AE67: =W67+Y67+AB67+AD67 -> 17105 | AG67: =M67&"-"&F67 -> 20-101-250Km | AH67: =IFERROR(VLOOKUP(AG67,Masters!N:O,2,0),"0") -> 40 | AI67: =AH67*N67 -> 12000 | AK67: =AI67-AE67 -> -5105 | AN67: =IFERROR(U67/2,"0") -> 242.5
A68: =A67+1 -> 67 | B68: 45747 | C68: s/Drona/03/25/68 | D68: 45751 | E68: vijay automobile | F68: 251-400Km | G68: bharatpur | H68: HR38AC7243 | I68: 1109 | J68: Fixed | K68: 65 | L68: 20L Buckets | M68: =IFERROR(VLOOKUP(L68,'Material Master'!B:C,2,0),"") -> 20 | N68: 300 | O68: =IFERROR(M68*N68,"") -> 6000 | P68: Yes | R68: 45717 | U68: 658 | V68: 31 | W68: =IFERROR(U68*V68,"0") -> 20398 | Y68: =IFERROR((O68/1000)*Masters!$C$3,"0") -> 570 | AA68: =IFERROR(VLOOKUP(L68,Masters!G:H,2,0),"0") -> 5 | AB68: =IFERROR(AA68*N68,"0") -> 1500 | AE68: =W68+Y68+AB68+AD68 -> 22468 | AG68: =M68&"-"&F68 -> 20-251-400Km | AH68: =IFERROR(VLOOKUP(AG68,Masters!N:O,2,0),"0") -> 68 | AI68: =AH68*N68 -> 20400 | AK68: =AI68-AE68 -> -2068 | AN68: =IFERROR(U68/2,"0") -> 329
A69: =A68+1 -> 68 | B69: 45747 | C69: s/Drona/03/25/69 | D69: 45750 | E69: abc motors | F69: 101-250Km | G69: fatehabad | H69: HR38AC0599 | I69: 1109 | J69: Fixed | K69: 60 | L69: 20L Buckets | M69: =IFERROR(VLOOKUP(L69,'Material Master'!B:C,2,0),"") -> 20 | N69: 300 | O69: =IFERROR(M69*N69,"") -> 6000 | P69: Yes | R69: 45717 | U69: 434 | V69: 31 | W69: =IFERROR(U69*V69,"0") -> 13454 | Y69: =IFERROR((O69/1000)*Masters!$C$3,"0") -> 570 | AA69: =IFERROR(VLOOKUP(L69,Masters!G:H,2,0),"0") -> 5 | AB69: =IFERROR(AA69*N69,"0") -> 1500 | AE69: =W69+Y69+AB69+AD69 -> 15524 | AG69: =M69&"-"&F69 -> 20-101-250Km | AH69: =IFERROR(VLOOKUP(AG69,Masters!N:O,2,0),"0") -> 40 | AI69: =AH69*N69 -> 12000 | AK69: =AI69-AE69 -> -3524 | AN69: =IFERROR(U69/2,"0") -> 217
A70: =A69+1 -> 69 | B70: 45747 | C70: s/Drona/03/25/70 | D70: 45754 | E70: abc motors | F70: 101-250km | G70: fatehabad | H70: HR38AC0599 | I70: 1109 | J70: Fixed | K70: 70 | L70: 20L Buckets | M70: =IFERROR(VLOOKUP(L70,'Material Master'!B:C,2,0),"") -> 20 | N70: 300 | O70: =IFERROR(M70*N70,"") -> 6000 | P70: Yes | R70: 45717 | U70: 433 | V70: 31 | W70: =IFERROR(U70*V70,"0") -> 13423 | Y70: =IFERROR((O70/1000)*Masters!$C$3,"0") -> 570 | AA70: =IFERROR(VLOOKUP(L70,Masters!G:H,2,0),"0") -> 5 | AB70: =IFERROR(AA70*N70,"0") -> 1500 | AE70: =W70+Y70+AB70+AD70 -> 15493 | AG70: =M70&"-"&F70 -> 20-101-250km | AH70: =IFERROR(VLOOKUP(AG70,Masters!N:O,2,0),"0") -> 40 | AI70: =AH70*N70 -> 12000 | AK70: =AI70-AE70 -> -3493 | AN70: =IFERROR(U70/2,"0") -> 216.5
A71: =A70+1 -> 70 | B71: 45747 | C71: s/Drona/03/25/71 | D71: 45748 | E71: Sahni Motors | F71: 0-100Km | G71: Karnal | H71: HR38AC0263 | I71: 1109 | J71: Fixed | K71: 52 | L71: 20L Buckets | M71: =IFERROR(VLOOKUP(L71,'Material Master'!B:C,2,0),"") -> 20 | N71: 300 | O71: =IFERROR(M71*N71,"") -> 6000 | P71: Yes | R71: 45717 | U71: 176 | V71: 31 | W71: =IFERROR(U71*V71,"0") -> 5456 | Y71: =IFERROR((O71/1000)*Masters!$C$3,"0") -> 570 | AA71: =IFERROR(VLOOKUP(L71,Masters!G:H,2,0),"0") -> 5 | AB71: =IFERROR(AA71*N71,"0") -> 1500 | AE71: =W71+Y71+AB71+AD71 -> 7526 | AG71: =M71&"-"&F71 -> 20-0-100Km | AH71: =IFERROR(VLOOKUP(AG71,Masters!N:O,2,0),"0") -> 21 | AI71: =AH71*N71 -> 6300 | AK71: =AI71-AE71 -> -1226 | AN71: =IFERROR(U71/2,"0") -> 88
A72: =A71+1 -> 71 | B72: 45747 | C72: s/Drona/03/25/72 | D72: 45749 | E72: Sahni Motors | F72: 0-100Km | G72: Karnal | H72: HR38AC0263 | I72: 1109 | J72: Fixed | K72: 56 | L72: 20L Buckets | M72: =IFERROR(VLOOKUP(L72,'Material Master'!B:C,2,0),"") -> 20 | N72: 300 | O72: =IFERROR(M72*N72,"") -> 6000 | P72: Yes | R72: 45717 | U72: 179 | V72: 31 | W72: =IFERROR(U72*V72,"0") -> 5549 | Y72: =IFERROR((O72/1000)*Masters!$C$3,"0") -> 570 | AA72: =IFERROR(VLOOKUP(L72,Masters!G:H,2,0),"0") -> 5 | AB72: =IFERROR(AA72*N72,"0") -> 1500 | AE72: =W72+Y72+AB72+AD72 -> 7619 | AG72: =M72&"-"&F72 -> 20-0-100Km | AH72: =IFERROR(VLOOKUP(AG72,Masters!N:O,2,0),"0") -> 21 | AI72: =AH72*N72 -> 6300 | AK72: =AI72-AE72 -> -1319 | AN72: =IFERROR(U72/2,"0") -> 89.5
A73: =A72+1 -> 72 | B73: 45747 | C73: s/Drona/03/25/73 | D73: 45748 | E73: shanti autosales pvt ltd | F73: 0-100Km | G73: Gautam budh nagar | H73: HR38AC7854 | I73: 1109 | J73: Fixed | K73: 53 | L73: 20L Buckets | M73: =IFERROR(VLOOKUP(L73,'Material Master'!B:C,2,0),"") -> 20 | N73: 300 | O73: =IFERROR(M73*N73,"") -> 6000 | P73: Yes | R73: 45717 | U73: 194 | V73: 31 | W73: =IFERROR(U73*V73,"0") -> 6014 | Y73: =IFERROR((O73/1000)*Masters!$C$3,"0") -> 570 | AA73: =IFERROR(VLOOKUP(L73,Masters!G:H,2,0),"0") -> 5 | AB73: =IFERROR(AA73*N73,"0") -> 1500 | AE73: =W73+Y73+AB73+AD73 -> 8084 | AG73: =M73&"-"&F73 -> 20-0-100Km | AH73: =IFERROR(VLOOKUP(AG73,Masters!N:O,2,0),"0") -> 21 | AI73: =AH73*N73 -> 6300 | AK73: =AI73-AE73 -> -1784 | AN73: =IFERROR(U73/2,"0") -> 97
A74: =A73+1 -> 73 | B74: 45747 | C74: s/Drona/03/25/74 | D74: 45750 | E74: cns motors pvt ltd | F74: 101-250Km | G74: Bijnor | H74: HR38AC0263 | I74: 1109 | J74: Fixed | K74: 63 | L74: 20L Buckets | M74: =IFERROR(VLOOKUP(L74,'Material Master'!B:C,2,0),"") -> 20 | N74: 300 | O74: =IFERROR(M74*N74,"") -> 6000 | P74: Yes | R74: 45717 | U74: 308 | V74: 31 | W74: =IFERROR(U74*V74,"0") -> 9548 | Y74: =IFERROR((O74/1000)*Masters!$C$3,"0") -> 570 | AA74: =IFERROR(VLOOKUP(L74,Masters!G:H,2,0),"0") -> 5 | AB74: =IFERROR(AA74*N74,"0") -> 1500 | AE74: =W74+Y74+AB74+AD74 -> 11618 | AG74: =M74&"-"&F74 -> 20-101-250Km | AH74: =IFERROR(VLOOKUP(AG74,Masters!N:O,2,0),"0") -> 40 | AI74: =AH74*N74 -> 12000 | AK74: =AI74-AE74 -> 382 | AN74: =IFERROR(U74/2,"0") -> 154
A75: =A74+1 -> 74 | B75: 45747 | C75: s/Drona/03/25/75 | D75: 45754 | E75: mg motors | F75: 101-250km | G75: Hisar | H75: HR38AC0263 | I75: 1109 | J75: Fixed | K75: 69 | L75: 20L Buckets | M75: =IFERROR(VLOOKUP(L75,'Material Master'!B:C,2,0),"") -> 20 | N75: 300 | O75: =IFERROR(M75*N75,"") -> 6000 | P75: Yes | R75: 45717 | U75: 309 | V75: 31 | W75: =IFERROR(U75*V75,"0") -> 9579 | Y75: =IFERROR((O75/1000)*Masters!$C$3,"0") -> 570 | AA75: =IFERROR(VLOOKUP(L75,Masters!G:H,2,0),"0") -> 5 | AB75: =IFERROR(AA75*N75,"0") -> 1500 | AE75: =W75+Y75+AB75+AD75 -> 11649 | AG75: =M75&"-"&F75 -> 20-101-250km | AH75: =IFERROR(VLOOKUP(AG75,Masters!N:O,2,0),"0") -> 40 | AI75: =AH75*N75 -> 12000 | AK75: =AI75-AE75 -> 351 | AN75: =IFERROR(U75/2,"0") -> 154.5
A76: =A75+1 -> 75 | B76: 45747 | C76: s/Drona/03/25/76 | D76: 45752 | E76: mg motors | F76: 101-250km | G76: Rewari | H76: HR38AC0263 | I76: 1109 | J76: Fixed | K76: 67 | L76: 20L Buckets | M76: =IFERROR(VLOOKUP(L76,'Material Master'!B:C,2,0),"") -> 20 | N76: 300 | O76: =IFERROR(M76*N76,"") -> 6000 | P76: Yes | R76: 45717 | U76: 389 | V76: 31 | W76: =IFERROR(U76*V76,"0") -> 12059 | Y76: =IFERROR((O76/1000)*Masters!$C$3,"0") -> 570 | AA76: =IFERROR(VLOOKUP(L76,Masters!G:H,2,0),"0") -> 5 | AB76: =IFERROR(AA76*N76,"0") -> 1500 | AE76: =W76+Y76+AB76+AD76 -> 14129 | AG76: =M76&"-"&F76 -> 20-101-250km | AH76: =IFERROR(VLOOKUP(AG76,Masters!N:O,2,0),"0") -> 40 | AI76: =AH76*N76 -> 12000 | AK76: =AI76-AE76 -> -2129 | AN76: =IFERROR(U76/2,"0") -> 194.5
A77: =A76+1 -> 76 | B77: 45750 | C77: S/Drona/04/25/01 | D77: 45752 | E77: ashok auto sales ltd | F77: 251-400Km | G77: mathura | H77: HR38AC7854 | I77: 1109 | J77: Fixed | K77: 66 | L77: 20L Buckets | M77: =IFERROR(VLOOKUP(L77,'Material Master'!B:C,2,0),"") -> 20 | N77: 300 | O77: =IFERROR(M77*N77,"") -> 6000 | P77: Yes | R77: 45748 | S77: AS PER GOOGLE 101-250KM | U77: 530 | V77: 31 | W77: =IFERROR(U77*V77,"0") -> 16430 | Y77: =IFERROR((O77/1000)*Masters!$C$3,"0") -> 570 | AA77: =IFERROR(VLOOKUP(L77,Masters!G:H,2,0),"0") -> 5 | AB77: =IFERROR(AA77*N77,"0") -> 1500 | AE77: =W77+Y77+AB77+AD77 -> 18500 | AG77: =M77&"-"&F77 -> 20-251-400Km | AH77: =IFERROR(VLOOKUP(AG77,Masters!N:O,2,0),"0") -> 68 | AI77: =AH77*N77 -> 20400 | AK77: =AI77-AE77 -> 1900 | AN77: =IFERROR(U77/2,"0") -> 265
A78: =A77+1 -> 77 | B78: 45750 | C78: S/Drona/04/25/02 | D78: 45750 | E78: Ashok auto Ventures LLP | F78: 0-100Km | G78: gautam Buddha Nagar | H78: HR38X6465 | I78: 909 | J78: Fixed | K78: 61 | L78: 20L Buckets | M78: =IFERROR(VLOOKUP(L78,'Material Master'!B:C,2,0),"") -> 20 | N78: 200 | O78: =IFERROR(M78*N78,"") -> 4000 | P78: Yes | R78: 45748 | U78: 181 | V78: 31 | W78: =IFERROR(U78*V78,"0") -> 5611 | Y78: =IFERROR((O78/1000)*Masters!$C$3,"0") -> 380 | AA78: =IFERROR(VLOOKUP(L78,Masters!G:H,2,0),"0") -> 5 | AB78: =IFERROR(AA78*N78,"0") -> 1000 | AE78: =W78+Y78+AB78+AD78 -> 6991 | AG78: =M78&"-"&F78 -> 20-0-100Km | AH78: =IFERROR(VLOOKUP(AG78,Masters!N:O,2,0),"0") -> 21 | AI78: =AH78*N78 -> 4200 | AK78: =AI78-AE78 -> -2791 | AN78: =IFERROR(U78/2,"0") -> 90.5
A79: =A78+1 -> 78 | B79: 45750 | C79: S/Drona/04/25/03 | D79: 45755 | E79: Pasco Motors LLP | F79: 101-250Km | G79: faridabad | H79: HR38AC0599 | I79: 1109 | J79: Fixed | K79: 74 | L79: 20L Buckets | M79: =IFERROR(VLOOKUP(L79,'Material Master'!B:C,2,0),"") -> 20 | N79: 300 | O79: =IFERROR(M79*N79,"") -> 6000 | P79: Yes | R79: 45748 | U79: 296 | V79: 31 | W79: =IFERROR(U79*V79,"0") -> 9176 | Y79: =IFERROR((O79/1000)*Masters!$C$3,"0") -> 570 | AA79: =IFERROR(VLOOKUP(L79,Masters!G:H,2,0),"0") -> 5 | AB79: =IFERROR(AA79*N79,"0") -> 1500 | AE79: =W79+Y79+AB79+AD79 -> 11246 | AG79: =M79&"-"&F79 -> 20-101-250Km | AH79: =IFERROR(VLOOKUP(AG79,Masters!N:O,2,0),"0") -> 40 | AI79: =AH79*N79 -> 12000 | AJ79: 722450 | AK79: =AI79-AE79 -> 754 | AN79: =IFERROR(U79/2,"0") -> 148
A80: =A79+1 -> 79 | B80: 45752 | C80: s/Drona/04/25/05 | D80: 45755 | E80: triumph auto parts distr pvt ltd | F80: 101-250Km | G80: palwal | H80: HR38AC7243 | I80: 1109 | J80: Fixed | K80: 72 | L80: 20L Buckets | M80: =IFERROR(VLOOKUP(L80,'Material Master'!B:C,2,0),"") -> 20 | N80: 300 | O80: =IFERROR(M80*N80,"") -> 6000 | P80: Yes | R80: 45748 | U80: 315 | V80: 31 | W80: =IFERROR(U80*V80,"0") -> 9765 | Y80: =IFERROR((O80/1000)*Masters!$C$3,"0") -> 570 | AA80: =IFERROR(VLOOKUP(L80,Masters!G:H,2,0),"0") -> 5 | AB80: =IFERROR(AA80*N80,"0") -> 1500 | AE80: =W80+Y80+AB80+AD80 -> 11835 | AG80: =M80&"-"&F80 -> 20-101-250Km | AH80: =IFERROR(VLOOKUP(AG80,Masters!N:O,2,0),"0") -> 40 | AI80: =AH80*N80 -> 12000 | AK80: =AI80-AE80 -> 165 | AN80: =IFERROR(U80/2,"0") -> 157.5
A81: =A80+1 -> 80 | B81: 45754 | C81: S/Drona/04/25/07 | D81: 45756 | E81: oberai motors ltd | F81: 101-250Km | G81: KOTDWARA | H81: HR38AC0263 | I81: 909 | J81: Fixed | K81: 76 | L81: 20L Buckets | M81: =IFERROR(VLOOKUP(L81,'Material Master'!B:C,2,0),"") -> 20 | N81: 200 | O81: =IFERROR(M81*N81,"") -> 4000 | P81: Yes | R81: 45748 | S81: 2nd trip | U81: 435 | V81: 31 | W81: =IFERROR(U81*V81,"0") -> 13485 | Y81: =IFERROR((O81/1000)*Masters!$C$3,"0") -> 380 | AA81: =IFERROR(VLOOKUP(L81,Masters!G:H,2,0),"0") -> 5 | AB81: =IFERROR(AA81*N81,"0") -> 1000 | AE81: =W81+Y81+AB81+AD81 -> 14865 | AG81: =M81&"-"&F81 -> 20-101-250Km | AH81: =IFERROR(VLOOKUP(AG81,Masters!N:O,2,0),"0") -> 40 | AI81: =AH81*N81 -> 8000 | AK81: =AI81-AE81 -> -6865 | AN81: =IFERROR(U81/2,"0") -> 217.5
A82: =A81+1 -> 81 | B82: 45754 | C82: s/Drona/04/25/08 | D82: 45755 | E82: Pasco Motors LLP | F82: 101-250Km | G82: gurgaon | H82: HR38AC7854 | I82: 1109 | J82: Fixed | K82: 71 | L82: 20L Buckets | M82: =IFERROR(VLOOKUP(L82,'Material Master'!B:C,2,0),"") -> 20 | N82: 300 | O82: =IFERROR(M82*N82,"") -> 6000 | P82: Yes | R82: 45748 | U82: 214 | V82: 31 | W82: =IFERROR(U82*V82,"0") -> 6634 | Y82: =IFERROR((O82/1000)*Masters!$C$3,"0") -> 570 | AA82: =IFERROR(VLOOKUP(L82,Masters!G:H,2,0),"0") -> 5 | AB82: =IFERROR(AA82*N82,"0") -> 1500 | AE82: =W82+Y82+AB82+AD82 -> 8704 | AG82: =M82&"-"&F82 -> 20-101-250Km | AH82: =IFERROR(VLOOKUP(AG82,Masters!N:O,2,0),"0") -> 40 | AI82: =AH82*N82 -> 12000 | AK82: =AI82-AE82 -> 3296 | AN82: =IFERROR(U82/2,"0") -> 107
A83: =A82+1 -> 82 | B83: 45754 | C83: s/Drona/04/25/09 | D83: 45755 | E83: mona generator services pvt ltd | F83: 0-100Km | G83: new Delhi | H83: HR38AC0263 | I83: 709 | J83: Fixed | K83: 73 | L83: 20L Buckets | M83: =IFERROR(VLOOKUP(L83,'Material Master'!B:C,2,0),"") -> 20 | N83: 100 | O83: =IFERROR(M83*N83,"") -> 2000 | P83: Yes | R83: 45748 | U83: 141 | V83: 31 | W83: =IFERROR(U83*V83,"0") -> 4371 | Y83: =IFERROR((O83/1000)*Masters!$C$3,"0") -> 190 | AA83: =IFERROR(VLOOKUP(L83,Masters!G:H,2,0),"0") -> 5 | AB83: =IFERROR(AA83*N83,"0") -> 500 | AE83: =W83+Y83+AB83+AD83 -> 5061 | AG83: =M83&"-"&F83 -> 20-0-100Km | AH83: =IFERROR(VLOOKUP(AG83,Masters!N:O,2,0),"0") -> 21 | AI83: =AH83*N83 -> 2100 | AK83: =AI83-AE83 -> -2961 | AN83: =IFERROR(U83/2,"0") -> 70.5
A84: =A83+1 -> 83 | B84: 45755 | C84: s/Drona/04/25/10 | D84: 45757 | E84: sjs motors | F84: 101-250Km | G84: saharanpur | H84: HR38AC7854 | I84: 909 | J84: Fixed | K84: 81 | L84: 20L Buckets | M84: =IFERROR(VLOOKUP(L84,'Material Master'!B:C,2,0),"") -> 20 | N84: 200 | O84: =IFERROR(M84*N84,"") -> 4000 | P84: Yes | R84: 45748 | S84: 2nd trip | U84: 294 | V84: 31 | W84: =IFERROR(U84*V84,"0") -> 9114 | Y84: =IFERROR((O84/1000)*Masters!$C$3,"0") -> 380 | AA84: =IFERROR(VLOOKUP(L84,Masters!G:H,2,0),"0") -> 5 | AB84: =IFERROR(AA84*N84,"0") -> 1000 | AE84: =W84+Y84+AB84+AD84 -> 10494 | AG84: =M84&"-"&F84 -> 20-101-250Km | AH84: =IFERROR(VLOOKUP(AG84,Masters!N:O,2,0),"0") -> 40 | AI84: =AH84*N84 -> 8000 | AK84: =AI84-AE84 -> -2494 | AN84: =IFERROR(U84/2,"0") -> 147
A85: =A84+1 -> 84 | B85: 45755 | C85: s/Drona/04/25/11 | D85: 45756 | E85: sjs motors | F85: 0-100Km | G85: tatarpur | H85: HR38AC7243 | I85: 1109 | J85: Fixed | K85: 77 | L85: 20L Buckets | M85: =IFERROR(VLOOKUP(L85,'Material Master'!B:C,2,0),"") -> 20 | N85: 300 | O85: =IFERROR(M85*N85,"") -> 6000 | P85: Yes | R85: 45748 | U85: 192 | V85: 31 | W85: =IFERROR(U85*V85,"0") -> 5952 | Y85: =IFERROR((O85/1000)*Masters!$C$3,"0") -> 570 | AA85: =IFERROR(VLOOKUP(L85,Masters!G:H,2,0),"0") -> 5 | AB85: =IFERROR(AA85*N85,"0") -> 1500 | AE85: =W85+Y85+AB85+AD85 -> 8022 | AG85: =M85&"-"&F85 -> 20-0-100Km | AH85: =IFERROR(VLOOKUP(AG85,Masters!N:O,2,0),"0") -> 21 | AI85: =AH85*N85 -> 6300 | AK85: =AI85-AE85 -> -1722 | AN85: =IFERROR(U85/2,"0") -> 96
A86: =A85+1 -> 85 | B86: 45755 | C86: s/Drona/04/25/12 | D86: 45757 | E86: ra motors pvt ltd | F86: 101-250Km | G86: moradabad | H86: HR38AC0599 | I86: 1109 | J86: Fixed | K86: 79 | L86: 20L Buckets | M86: =IFERROR(VLOOKUP(L86,'Material Master'!B:C,2,0),"") -> 20 | N86: 300 | O86: =IFERROR(M86*N86,"") -> 6000 | P86: Yes | R86: 45748 | U86: 416 | V86: 31 | W86: =IFERROR(U86*V86,"0") -> 12896 | Y86: =IFERROR((O86/1000)*Masters!$C$3,"0") -> 570 | AA86: =IFERROR(VLOOKUP(L86,Masters!G:H,2,0),"0") -> 5 | AB86: =IFERROR(AA86*N86,"0") -> 1500 | AE86: =W86+Y86+AB86+AD86 -> 14966 | AG86: =M86&"-"&F86 -> 20-101-250Km | AH86: =IFERROR(VLOOKUP(AG86,Masters!N:O,2,0),"0") -> 40 | AI86: =AH86*N86 -> 12000 | AK86: =AI86-AE86 -> -2966 | AN86: =IFERROR(U86/2,"0") -> 208
A87: =A86+1 -> 86 | B87: 45756 | C87: s/Drona/04/25/13 | D87: 45757 | E87: mangalam auto | F87: 101-250Km | G87: Palwal | H87: HR38AC7243 | I87: 1109 | J87: Fixed | K87: 80 | L87: 20L Buckets | M87: =IFERROR(VLOOKUP(L87,'Material Master'!B:C,2,0),"") -> 20 | N87: 300 | O87: =IFERROR(M87*N87,"") -> 6000 | P87: Yes | R87: 45748 | U87: 324 | V87: 31 | W87: =IFERROR(U87*V87,"0") -> 10044 | Y87: =IFERROR((O87/1000)*Masters!$C$3,"0") -> 570 | AA87: =IFERROR(VLOOKUP(L87,Masters!G:H,2,0),"0") -> 5 | AB87: =IFERROR(AA87*N87,"0") -> 1500 | AE87: =W87+Y87+AB87+AD87 -> 12114 | AG87: =M87&"-"&F87 -> 20-101-250Km | AH87: =IFERROR(VLOOKUP(AG87,Masters!N:O,2,0),"0") -> 40 | AI87: =AH87*N87 -> 12000 | AK87: =AI87-AE87 -> -114 | AN87: =IFERROR(U87/2,"0") -> 162
A88: =A87+1 -> 87 | B88: 45758 | C88: s/Drona/04/25/14 | D88: 45758 | E88: abhishek automobiles | F88: 101-250Km | G88: Rewari | H88: HR38AC0263 | I88: 1109 | J88: Fixed | K88: 82 | L88: 20L Buckets | M88: =IFERROR(VLOOKUP(L88,'Material Master'!B:C,2,0),"") -> 20 | N88: 300 | O88: =IFERROR(M88*N88,"") -> 6000 | P88: Yes | R88: 45748 | U88: 225 | V88: 31 | W88: =IFERROR(U88*V88,"0") -> 6975 | Y88: =IFERROR((O88/1000)*Masters!$C$3,"0") -> 570 | AA88: =IFERROR(VLOOKUP(L88,Masters!G:H,2,0),"0") -> 5 | AB88: =IFERROR(AA88*N88,"0") -> 1500 | AE88: =W88+Y88+AB88+AD88 -> 9045 | AG88: =M88&"-"&F88 -> 20-101-250Km | AH88: =IFERROR(VLOOKUP(AG88,Masters!N:O,2,0),"0") -> 40 | AI88: =AH88*N88 -> 12000 | AK88: =AI88-AE88 -> 2955 | AN88: =IFERROR(U88/2,"0") -> 112.5
A89: =A88+1 -> 88 | B89: 45758 | C89: s/Drona/04/25/15 | D89: 45758 | E89: shri shyam automobiles | F89: 101-250Km | G89: ferozpur jhirka | H89: HR38AC7854 | I89: 1109 | J89: Fixed | K89: 83 | L89: 20L Buckets | M89: =IFERROR(VLOOKUP(L89,'Material Master'!B:C,2,0),"") -> 20 | N89: 300 | O89: =IFERROR(M89*N89,"") -> 6000 | P89: Yes | R89: 45748 | U89: 333 | V89: 31 | W89: =IFERROR(U89*V89,"0") -> 10323 | Y89: =IFERROR((O89/1000)*Masters!$C$3,"0") -> 570 | AA89: =IFERROR(VLOOKUP(L89,Masters!G:H,2,0),"0") -> 5 | AB89: =IFERROR(AA89*N89,"0") -> 1500 | AE89: =W89+Y89+AB89+AD89 -> 12393 | AG89: =M89&"-"&F89 -> 20-101-250Km | AH89: =IFERROR(VLOOKUP(AG89,Masters!N:O,2,0),"0") -> 40 | AI89: =AH89*N89 -> 12000 | AK89: =AI89-AE89 -> -393 | AN89: =IFERROR(U89/2,"0") -> 166.5
A90: =A89+1 -> 89 | B90: 45758 | C90: s/Drona/04/25/16 | D90: 45759 | E90: a&a automobiles pvt ltd | F90: 0-100Km | G90: ghaziabad | H90: HR38AC7243 | I90: 1109 | J90: Fixed | K90: 86 | L90: 20L Buckets | M90: =IFERROR(VLOOKUP(L90,'Material Master'!B:C,2,0),"") -> 20 | N90: 300 | O90: =IFERROR(M90*N90,"") -> 6000 | P90: Yes | R90: 45748 | U90: 124 | V90: 31 | W90: =IFERROR(U90*V90,"0") -> 3844 | Y90: =IFERROR((O90/1000)*Masters!$C$3,"0") -> 570 | AA90: =IFERROR(VLOOKUP(L90,Masters!G:H,2,0),"0") -> 5 | AB90: =IFERROR(AA90*N90,"0") -> 1500 | AE90: =W90+Y90+AB90+AD90 -> 5914 | AG90: =M90&"-"&F90 -> 20-0-100Km | AH90: =IFERROR(VLOOKUP(AG90,Masters!N:O,2,0),"0") -> 21 | AI90: =AH90*N90 -> 6300 | AK90: =AI90-AE90 -> 386 | AN90: =IFERROR(U90/2,"0") -> 62
A91: =A90+1 -> 90 | B91: 45758 | C91: s/Drona/04/25/17 | D91: 45759 | E91: patricia holdings pvt ltd | F91: 101-250Km | G91: roorkee | H91: HR38AC0263 | I91: 1109 | J91: Fixed | K91: 85 | L91: 20L Buckets | M91: =IFERROR(VLOOKUP(L91,'Material Master'!B:C,2,0),"") -> 20 | N91: 300 | O91: =IFERROR(M91*N91,"") -> 6000 | P91: Yes | R91: 45748 | U91: 342 | V91: 31 | W91: =IFERROR(U91*V91,"0") -> 10602 | Y91: =IFERROR((O91/1000)*Masters!$C$3,"0") -> 570 | AA91: =IFERROR(VLOOKUP(L91,Masters!G:H,2,0),"0") -> 5 | AB91: =IFERROR(AA91*N91,"0") -> 1500 | AE91: =W91+Y91+AB91+AD91 -> 12672 | AG91: =M91&"-"&F91 -> 20-101-250Km | AH91: =IFERROR(VLOOKUP(AG91,Masters!N:O,2,0),"0") -> 40 | AI91: =AH91*N91 -> 12000 | AK91: =AI91-AE91 -> -672 | AN91: =IFERROR(U91/2,"0") -> 171
A92: =A91+1 -> 91 | B92: 45758 | C92: s/Drona/04/25/18 | E92: patricia holdings pvt ltd | G92: rudraprayag | I92: 709 | M92: =IFERROR(VLOOKUP(L92,'Material Master'!B:C,2,0),"") | O92: =IFERROR(M92*N92,"") | R92: 45748 | S92: CANCEL BY DRONA ( 20 L- 100 pcs) | V92: 31 | W92: =IFERROR(U92*V92,"0") -> 0 | Y92: =IFERROR((O92/1000)*Masters!$C$3,"0") -> 0 | AA92: =IFERROR(VLOOKUP(L92,Masters!G:H,2,0),"0") -> 0 | AB92: =IFERROR(AA92*N92,"0") -> 0 | AE92: =W92+Y92+AB92+AD92 -> 0 | AG92: =M92&"-"&F92 -> - | AH92: =IFERROR(VLOOKUP(AG92,Masters!N:O,2,0),"0") -> 0 | AI92: =AH92*N92 -> 0 | AK92: =AI92-AE92 -> 0 | AN92: =IFERROR(U92/2,"0") -> 0
A93: =A92+1 -> 92 | B93: 45758 | C93: s/Drona/04/25/19 | D93: 45759 | E93: haryana motor | F93: 0-100Km | G93: jhajjar | H93: HR38AC0599 | I93: 1109 | J93: Fixed | K93: 84 | L93: 20L Buckets | M93: =IFERROR(VLOOKUP(L93,'Material Master'!B:C,2,0),"") -> 20 | N93: 300 | O93: =IFERROR(M93*N93,"") -> 6000 | P93: Yes | R93: 45748 | U93: 161 | V93: 31 | W93: =IFERROR(U93*V93,"0") -> 4991 | Y93: =IFERROR((O93/1000)*Masters!$C$3,"0") -> 570 | AA93: =IFERROR(VLOOKUP(L93,Masters!G:H,2,0),"0") -> 5 | AB93: =IFERROR(AA93*N93,"0") -> 1500 | AE93: =W93+Y93+AB93+AD93 -> 7061 | AG93: =M93&"-"&F93 -> 20-0-100Km | AH93: =IFERROR(VLOOKUP(AG93,Masters!N:O,2,0),"0") -> 21 | AI93: =AH93*N93 -> 6300 | AK93: =AI93-AE93 -> -761 | AN93: =IFERROR(U93/2,"0") -> 80.5
A94: =A93+1 -> 93 | B94: 45759 | C94: s/Drona/04/25/20 | D94: 45761 | E94: Yuvraj Motors | F94: 101-250Km | G94: aligarh | H94: HR38AC0599 | I94: 1109 | J94: Fixed | K94: 87 | L94: 20L Buckets | M94: =IFERROR(VLOOKUP(L94,'Material Master'!B:C,2,0),"") -> 20 | N94: 300 | O94: =IFERROR(M94*N94,"") -> 6000 | P94: Yes | R94: 45748 | U94: 369 | V94: 31 | W94: =IFERROR(U94*V94,"0") -> 11439 | Y94: =IFERROR((O94/1000)*Masters!$C$3,"0") -> 570 | AA94: =IFERROR(VLOOKUP(L94,Masters!G:H,2,0),"0") -> 5 | AB94: =IFERROR(AA94*N94,"0") -> 1500 | AE94: =W94+Y94+AB94+AD94 -> 13509 | AG94: =M94&"-"&F94 -> 20-101-250Km | AH94: =IFERROR(VLOOKUP(AG94,Masters!N:O,2,0),"0") -> 40 | AI94: =AH94*N94 -> 12000 | AK94: =AI94-AE94 -> -1509 | AN94: =IFERROR(U94/2,"0") -> 184.5
A95: =A94+1 -> 94 | B95: 45761 | C95: s/Drona/04/25/21 | D95: 45762 | E95: triumph auto parts distr pvt ltd | F95: 0-100Km | G95: delhi | H95: HR38AC0263 | I95: 1109 | J95: Fixed | K95: 89 | L95: 20L Buckets | M95: =IFERROR(VLOOKUP(L95,'Material Master'!B:C,2,0),"") -> 20 | N95: 300 | O95: =IFERROR(M95*N95,"") -> 6000 | P95: Yes | R95: 45748 | U95: 63 | V95: 31 | W95: =IFERROR(U95*V95,"0") -> 1953 | Y95: =IFERROR((O95/1000)*Masters!$C$3,"0") -> 570 | AA95: =IFERROR(VLOOKUP(L95,Masters!G:H,2,0),"0") -> 5 | AB95: =IFERROR(AA95*N95,"0") -> 1500 | AE95: =W95+Y95+AB95+AD95 -> 4023 | AG95: =M95&"-"&F95 -> 20-0-100Km | AH95: =IFERROR(VLOOKUP(AG95,Masters!N:O,2,0),"0") -> 21 | AI95: =AH95*N95 -> 6300 | AK95: =AI95-AE95 -> 2277 | AN95: =IFERROR(U95/2,"0") -> 31.5
A96: =A95+1 -> 95 | B96: 45761 | C96: s/Drona/04/25/22 | D96: 45762 | E96: amit auto wheels pvt ltd | F96: 251-400Km | G96: rudrapur | H96: HR38AC7854 | I96: 1109 | J96: Fixed | K96: 90 | L96: 20L Buckets | M96: =IFERROR(VLOOKUP(L96,'Material Master'!B:C,2,0),"") -> 20 | N96: 200 | O96: =IFERROR(M96*N96,"") -> 4000 | P96: Yes | R96: 45748 | U96: 623 | V96: 31 | W96: =IFERROR(U96*V96,"0") -> 19313 | Y96: =IFERROR((O96/1000)*Masters!$C$3,"0") -> 380 | AA96: =IFERROR(VLOOKUP(L96,Masters!G:H,2,0),"0") -> 5 | AB96: =IFERROR(AA96*N96,"0") -> 1000 | AE96: =W96+Y96+AB96+AD96 -> 20693 | AG96: =M96&"-"&F96 -> 20-251-400Km | AH96: =IFERROR(VLOOKUP(AG96,Masters!N:O,2,0),"0") -> 68 | AI96: =AH96*N96 -> 13600 | AK96: =AI96-AE96 -> -7093 | AN96: =IFERROR(U96/2,"0") -> 311.5
A97: =A96+1 -> 96 | B97: 45761 | C97: s/Drona/04/25/22 | D97: 45762 | E97: amit auto wheels pvt ltd | F97: 251-400Km | G97: haldwani | H97: HR38AC7854 | I97: 1109 | J97: Fixed | K97: 91 | L97: 20L Buckets | M97: =IFERROR(VLOOKUP(L97,'Material Master'!B:C,2,0),"") -> 20 | N97: 100 | O97: =IFERROR(M97*N97,"") -> 2000 | P97: Yes | R97: 45748 | U97: 0 | V97: 31 | W97: =IFERROR(U97*V97,"0") -> 0 | Y97: =IFERROR((O97/1000)*Masters!$C$3,"0") -> 190 | AA97: =IFERROR(VLOOKUP(L97,Masters!G:H,2,0),"0") -> 5 | AB97: =IFERROR(AA97*N97,"0") -> 500 | AE97: =W97+Y97+AB97+AD97 -> 690 | AG97: =M97&"-"&F97 -> 20-251-400Km | AH97: =IFERROR(VLOOKUP(AG97,Masters!N:O,2,0),"0") -> 68 | AI97: =AH97*N97 -> 6800 | AK97: =AI97-AE97 -> 6110 | AN97: =IFERROR(U97/2,"0") -> 0
A98: =A97+1 -> 97 | B98: 45762 | C98: s/Drona/04/25/23 | E98: farswan tyres | G98: chamoli | I98: 709 | M98: =IFERROR(VLOOKUP(L98,'Material Master'!B:C,2,0),"") | O98: =IFERROR(M98*N98,"") | R98: 45748 | S98: CANCEL BY DRONA ( 20 L- 100 pcs) | V98: 31 | W98: =IFERROR(U98*V98,"0") -> 0 | Y98: =IFERROR((O98/1000)*Masters!$C$3,"0") -> 0 | AA98: =IFERROR(VLOOKUP(L98,Masters!G:H,2,0),"0") -> 0 | AB98: =IFERROR(AA98*N98,"0") -> 0 | AE98: =W98+Y98+AB98+AD98 -> 0 | AG98: =M98&"-"&F98 -> - | AH98: =IFERROR(VLOOKUP(AG98,Masters!N:O,2,0),"0") -> 0 | AI98: =AH98*N98 -> 0 | AK98: =AI98-AE98 -> 0 | AN98: =IFERROR(U98/2,"0") -> 0
A99: =A98+1 -> 98 | B99: 45762 | C99: s/Drona/04/25/24 | D99: 45762 | E99: singhal enterprises | F99: 101-250Km | G99: manglaur | H99: HR38AC0263 | I99: 709 | J99: Fixed | K99: 93 | L99: 20L Buckets | M99: =IFERROR(VLOOKUP(L99,'Material Master'!B:C,2,0),"") -> 20 | N99: 100 | O99: =IFERROR(M99*N99,"") -> 2000 | P99: Yes | R99: 45748 | U99: 308 | V99: 31 | W99: =IFERROR(U99*V99,"0") -> 9548 | Y99: =IFERROR((O99/1000)*Masters!$C$3,"0") -> 190 | AA99: =IFERROR(VLOOKUP(L99,Masters!G:H,2,0),"0") -> 5 | AB99: =IFERROR(AA99*N99,"0") -> 500 | AE99: =W99+Y99+AB99+AD99 -> 10238 | AG99: =M99&"-"&F99 -> 20-101-250Km | AH99: =IFERROR(VLOOKUP(AG99,Masters!N:O,2,0),"0") -> 40 | AI99: =AH99*N99 -> 4000 | AK99: =AI99-AE99 -> -6238 | AN99: =IFERROR(U99/2,"0") -> 154
A100: =A99+1 -> 99 | B100: 45762 | C100: s/Drona/04/25/25 | D100: 45762 | E100: Metro Motors Pvt Ltd. | F100: 0-100Km | G100: Karnal | H100: HR38AC7243 | I100: 909 | J100: Fixed | K100: 92 | L100: 20L Buckets | M100: =IFERROR(VLOOKUP(L100,'Material Master'!B:C,2,0),"") -> 20 | N100: 200 | O100: =IFERROR(M100*N100,"") -> 4000 | P100: Yes | R100: 45748 | U100: 192 | V100: 31 | W100: =IFERROR(U100*V100,"0") -> 5952 | Y100: =IFERROR((O100/1000)*Masters!$C$3,"0") -> 380 | AA100: =IFERROR(VLOOKUP(L100,Masters!G:H,2,0),"0") -> 5 | AB100: =IFERROR(AA100*N100,"0") -> 1000 | AE100: =W100+Y100+AB100+AD100 -> 7332 | AG100: =M100&"-"&F100 -> 20-0-100Km | AH100: =IFERROR(VLOOKUP(AG100,Masters!N:O,2,0),"0") -> 21 | AI100: =AH100*N100 -> 4200 | AK100: =AI100-AE100 -> -3132 | AN100: =IFERROR(U100/2,"0") -> 96
A101: =A100+1 -> 100 | B101: 45763 | C101: s/Drona/04/25/26 | E101: Cargo Motors | G101: shimla | I101: 709 | M101: =IFERROR(VLOOKUP(L101,'Material Master'!B:C,2,0),"") | O101: =IFERROR(M101*N101,"") | R101: 45748 | S101: CANCEL BY DRONA ( 20 L- 100 pcs) | V101: 31 | W101: =IFERROR(U101*V101,"0") -> 0 | Y101: =IFERROR((O101/1000)*Masters!$C$3,"0") -> 0 | AA101: =IFERROR(VLOOKUP(L101,Masters!G:H,2,0),"0") -> 0 | AB101: =IFERROR(AA101*N101,"0") -> 0 | AE101: =W101+Y101+AB101+AD101 -> 0 | AG101: =M101&"-"&F101 -> - | AH101: =IFERROR(VLOOKUP(AG101,Masters!N:O,2,0),"0") -> 0 | AI101: =AH101*N101 -> 0 | AK101: =AI101-AE101 -> 0 | AN101: =IFERROR(U101/2,"0") -> 0
A102: =A101+1 -> 101 | B102: 45763 | C102: s/Drona/04/25/27 | D102: 45763 | E102: saawariya automobiles | F102: 101-250Km | G102: sohna | H102: HR38AC0599 | I102: 1109 | J102: Fixed | K102: 94 | L102: 20L Buckets | M102: =IFERROR(VLOOKUP(L102,'Material Master'!B:C,2,0),"") -> 20 | N102: 300 | O102: =IFERROR(M102*N102,"") -> 6000 | P102: Yes | R102: 45748 | U102: 250 | V102: 31 | W102: =IFERROR(U102*V102,"0") -> 7750 | Y102: =IFERROR((O102/1000)*Masters!$C$3,"0") -> 570 | AA102: =IFERROR(VLOOKUP(L102,Masters!G:H,2,0),"0") -> 5 | AB102: =IFERROR(AA102*N102,"0") -> 1500 | AE102: =W102+Y102+AB102+AD102 -> 9820 | AG102: =M102&"-"&F102 -> 20-101-250Km | AH102: =IFERROR(VLOOKUP(AG102,Masters!N:O,2,0),"0") -> 40 | AI102: =AH102*N102 -> 12000 | AK102: =AI102-AE102 -> 2180 | AN102: =IFERROR(U102/2,"0") -> 125
A103: =A102+1 -> 102 | B103: 45764 | C103: s/Drona/04/25/28 | D103: 45764 | E103: rishabh engineering company | F103: 0-100Km | G103: ghaziabad | H103: HR38AC7243 | I103: 909 | J103: Fixed | K103: 95 | L103: 20L Buckets | M103: =IFERROR(VLOOKUP(L103,'Material Master'!B:C,2,0),"") -> 20 | N103: 100 | O103: =IFERROR(M103*N103,"") -> 2000 | P103: Yes | R103: 45748 | U103: 145 | V103: 31 | W103: =IFERROR(U103*V103,"0") -> 4495 | Y103: =IFERROR((O103/1000)*Masters!$C$3,"0") -> 190 | AA103: =IFERROR(VLOOKUP(L103,Masters!G:H,2,0),"0") -> 5 | AB103: =IFERROR(AA103*N103,"0") -> 500 | AE103: =W103+Y103+AB103+AD103 -> 5185 | AG103: =M103&"-"&F103 -> 20-0-100Km | AH103: =IFERROR(VLOOKUP(AG103,Masters!N:O,2,0),"0") -> 21 | AI103: =AH103*N103 -> 2100 | AK103: =AI103-AE103 -> -3085 | AN103: =IFERROR(U103/2,"0") -> 72.5
A104: =A103+1 -> 103 | B104: 45765 | C104: s/Drona/04/25/29 | D104: 45765 | E104: kumanu diesel services center (p) ltd | F104: 101-250Km | G104: rampur | H104: HR38AC0599 | I104: 1109 | J104: Fixed | K104: 98 | L104: 20L Buckets | M104: =IFERROR(VLOOKUP(L104,'Material Master'!B:C,2,0),"") -> 20 | N104: 300 | O104: =IFERROR(M104*N104,"") -> 6000 | P104: Yes | R104: 45748 | U104: 478 | V104: 31 | W104: =IFERROR(U104*V104,"0") -> 14818 | Y104: =IFERROR((O104/1000)*Masters!$C$3,"0") -> 570 | AA104: =IFERROR(VLOOKUP(L104,Masters!G:H,2,0),"0") -> 5 | AB104: =IFERROR(AA104*N104,"0") -> 1500 | AE104: =W104+Y104+AB104+AD104 -> 16888 | AG104: =M104&"-"&F104 -> 20-101-250Km | AH104: =IFERROR(VLOOKUP(AG104,Masters!N:O,2,0),"0") -> 40 | AI104: =AH104*N104 -> 12000 | AK104: =AI104-AE104 -> -4888 | AN104: =IFERROR(U104/2,"0") -> 239
A105: =A104+1 -> 104 | B105: 45765 | C105: s/Drona/04/25/30 | D105: 45765 | E105: om sai ram motros | F105: 0-100Km | G105: baghpat | H105: HR38AC0263 | I105: 1109 | J105: Fixed | K105: 96 | L105: 20L Buckets | M105: =IFERROR(VLOOKUP(L105,'Material Master'!B:C,2,0),"") -> 20 | N105: 300 | O105: =IFERROR(M105*N105,"") -> 6000 | P105: Yes | R105: 45748 | U105: 63 | V105: 31 | W105: =IFERROR(U105*V105,"0") -> 1953 | Y105: =IFERROR((O105/1000)*Masters!$C$3,"0") -> 570 | AA105: =IFERROR(VLOOKUP(L105,Masters!G:H,2,0),"0") -> 5 | AB105: =IFERROR(AA105*N105,"0") -> 1500 | AE105: =W105+Y105+AB105+AD105 -> 4023 | AG105: =M105&"-"&F105 -> 20-0-100Km | AH105: =IFERROR(VLOOKUP(AG105,Masters!N:O,2,0),"0") -> 21 | AI105: =AH105*N105 -> 6300 | AK105: =AI105-AE105 -> 2277 | AN105: =IFERROR(U105/2,"0") -> 31.5
A106: =A105+1 -> 105 | B106: 45765 | C106: s/Drona/04/25/31 | D106: 45765 | E106: vardhman motors | F106: 101-250Km | G106: sikandrabad | H106: HR38AC7854 | I106: 1109 | J106: Fixed | K106: 97 | L106: 20L Buckets | M106: =IFERROR(VLOOKUP(L106,'Material Master'!B:C,2,0),"") -> 20 | N106: 300 | O106: =IFERROR(M106*N106,"") -> 6000 | P106: Yes | R106: 45748 | U106: 210 | V106: 31 | W106: =IFERROR(U106*V106,"0") -> 6510 | Y106: =IFERROR((O106/1000)*Masters!$C$3,"0") -> 570 | AA106: =IFERROR(VLOOKUP(L106,Masters!G:H,2,0),"0") -> 5 | AB106: =IFERROR(AA106*N106,"0") -> 1500 | AE106: =W106+Y106+AB106+AD106 -> 8580 | AG106: =M106&"-"&F106 -> 20-101-250Km | AH106: =IFERROR(VLOOKUP(AG106,Masters!N:O,2,0),"0") -> 40 | AI106: =AH106*N106 -> 12000 | AK106: =AI106-AE106 -> 3420 | AN106: =IFERROR(U106/2,"0") -> 105
A107: =A106+1 -> 106 | B107: 45765 | C107: s/Drona/04/25/32 | D107: 45765 | E107: kumanu diesel services center (p) ltd | F107: 101-250Km | G107: rampur | H107: HR38AC0263 | I107: 1109 | J107: Fixed | K107: 99 | L107: 20L Buckets | M107: =IFERROR(VLOOKUP(L107,'Material Master'!B:C,2,0),"") -> 20 | N107: 300 | O107: =IFERROR(M107*N107,"") -> 6000 | P107: Yes | R107: 45748 | U107: 476 | V107: 31 | W107: =IFERROR(U107*V107,"0") -> 14756 | Y107: =IFERROR((O107/1000)*Masters!$C$3,"0") -> 570 | AA107: =IFERROR(VLOOKUP(L107,Masters!G:H,2,0),"0") -> 5 | AB107: =IFERROR(AA107*N107,"0") -> 1500 | AE107: =W107+Y107+AB107+AD107 -> 16826 | AG107: =M107&"-"&F107 -> 20-101-250Km | AH107: =IFERROR(VLOOKUP(AG107,Masters!N:O,2,0),"0") -> 40 | AI107: =AH107*N107 -> 12000 | AK107: =AI107-AE107 -> -4826 | AN107: =IFERROR(U107/2,"0") -> 238
A108: =A107+1 -> 107 | B108: 45766 | C108: s/Drona/04/25/33 | D108: 45766 | E108: shyam automobiles | F108: 101-250Km | G108: roorkee | H108: HR38AC7243 | I108: 909 | J108: Fixed | K108: 101 | L108: 20L Buckets | M108: =IFERROR(VLOOKUP(L108,'Material Master'!B:C,2,0),"") -> 20 | N108: 200 | O108: =IFERROR(M108*N108,"") -> 4000 | P108: Yes | R108: 45748 | U108: 350 | V108: 31 | W108: =IFERROR(U108*V108,"0") -> 10850 | Y108: =IFERROR((O108/1000)*Masters!$C$3,"0") -> 380 | AA108: =IFERROR(VLOOKUP(L108,Masters!G:H,2,0),"0") -> 5 | AB108: =IFERROR(AA108*N108,"0") -> 1000 | AE108: =W108+Y108+AB108+AD108 -> 12230 | AG108: =M108&"-"&F108 -> 20-101-250Km | AH108: =IFERROR(VLOOKUP(AG108,Masters!N:O,2,0),"0") -> 40 | AI108: =AH108*N108 -> 8000 | AK108: =AI108-AE108 -> -4230 | AN108: =IFERROR(U108/2,"0") -> 175
A109: =A108+1 -> 108 | B109: 45768 | C109: s/Drona/04/25/34 | D109: 45768 | E109: Ashok auto Ventures LLP | F109: 0-100Km | G109: gautam Buddha Nagar | H109: HR38AC7243 | I109: 1109 | J109: Fixed | K109: 104 | L109: 20L Buckets | M109: =IFERROR(VLOOKUP(L109,'Material Master'!B:C,2,0),"") -> 20 | N109: 300 | O109: =IFERROR(M109*N109,"") -> 6000 | P109: Yes | R109: 45748 | U109: 170 | V109: 31 | W109: =IFERROR(U109*V109,"0") -> 5270 | Y109: =IFERROR((O109/1000)*Masters!$C$3,"0") -> 570 | AA109: =IFERROR(VLOOKUP(L109,Masters!G:H,2,0),"0") -> 5 | AB109: =IFERROR(AA109*N109,"0") -> 1500 | AE109: =W109+Y109+AB109+AD109 -> 7340 | AG109: =M109&"-"&F109 -> 20-0-100Km | AH109: =IFERROR(VLOOKUP(AG109,Masters!N:O,2,0),"0") -> 21 | AI109: =AH109*N109 -> 6300 | AK109: =AI109-AE109 -> -1040 | AN109: =IFERROR(U109/2,"0") -> 85
A110: =A109+1 -> 109 | B110: 45768 | C110: s/Drona/04/25/35 | D110: 45768 | E110: sahib auto pvt ltd | F110: 0-100Km | G110: sonipat | H110: HR38AC7854 | I110: 709 | J110: Fixed | K110: 102 | L110: 20L Buckets | M110: =IFERROR(VLOOKUP(L110,'Material Master'!B:C,2,0),"") -> 20 | N110: 100 | O110: =IFERROR(M110*N110,"") -> 2000 | P110: Yes | R110: 45748 | U110: 26 | V110: 31 | W110: =IFERROR(U110*V110,"0") -> 806 | Y110: =IFERROR((O110/1000)*Masters!$C$3,"0") -> 190 | AA110: =IFERROR(VLOOKUP(L110,Masters!G:H,2,0),"0") -> 5 | AB110: =IFERROR(AA110*N110,"0") -> 500 | AE110: =W110+Y110+AB110+AD110 -> 1496 | AG110: =M110&"-"&F110 -> 20-0-100Km | AH110: =IFERROR(VLOOKUP(AG110,Masters!N:O,2,0),"0") -> 21 | AI110: =AH110*N110 -> 2100 | AK110: =AI110-AE110 -> 604 | AN110: =IFERROR(U110/2,"0") -> 13
A111: =A110+1 -> 110 | B111: 45768 | C111: s/Drona/04/25/36 | D111: 45768 | E111: triumph auto (cv) pvt ldt | F111: 0-100Km | G111: delhi | H111: HR38AC0599 | I111: 1109 | J111: Fixed | K111: 103 | L111: 20L Buckets | M111: =IFERROR(VLOOKUP(L111,'Material Master'!B:C,2,0),"") -> 20 | N111: 300 | O111: =IFERROR(M111*N111,"") -> 6000 | P111: Yes | R111: 45748 | U111: 63 | V111: 31 | W111: =IFERROR(U111*V111,"0") -> 1953 | Y111: =IFERROR((O111/1000)*Masters!$C$3,"0") -> 570 | AA111: =IFERROR(VLOOKUP(L111,Masters!G:H,2,0),"0") -> 5 | AB111: =IFERROR(AA111*N111,"0") -> 1500 | AE111: =W111+Y111+AB111+AD111 -> 4023 | AG111: =M111&"-"&F111 -> 20-0-100Km | AH111: =IFERROR(VLOOKUP(AG111,Masters!N:O,2,0),"0") -> 21 | AI111: =AH111*N111 -> 6300 | AK111: =AI111-AE111 -> 2277 | AN111: =IFERROR(U111/2,"0") -> 31.5
A112: =A111+1 -> 111 | B112: 45769 | C112: s/Drona/04/25/37 | D112: 45769 | E112: mangalam auto | F112: 101-250Km | G112: palwal | H112: HR38AC7854 | I112: 1109 | J112: Fixed | K112: 106 | L112: 20L Buckets | M112: =IFERROR(VLOOKUP(L112,'Material Master'!B:C,2,0),"") -> 20 | N112: 300 | O112: =IFERROR(M112*N112,"") -> 6000 | P112: Yes | R112: 45748 | U112: 344 | V112: 31 | W112: =IFERROR(U112*V112,"0") -> 10664 | Y112: =IFERROR((O112/1000)*Masters!$C$3,"0") -> 570 | AA112: =IFERROR(VLOOKUP(L112,Masters!G:H,2,0),"0") -> 5 | AB112: =IFERROR(AA112*N112,"0") -> 1500 | AE112: =W112+Y112+AB112+AD112 -> 12734 | AG112: =M112&"-"&F112 -> 20-101-250Km | AH112: =IFERROR(VLOOKUP(AG112,Masters!N:O,2,0),"0") -> 40 | AI112: =AH112*N112 -> 12000 | AK112: =AI112-AE112 -> -734 | AN112: =IFERROR(U112/2,"0") -> 172
A113: =A112+1 -> 112 | B113: 45769 | C113: s/Drona/04/25/38 | D113: 45769 | E113: gng auto aids pvt ltd | F113: 101-250Km | G113: bilaspur | H113: HR38AC0599 | I113: 909 | J113: Fixed | K113: 107 | L113: 20L Buckets | M113: =IFERROR(VLOOKUP(L113,'Material Master'!B:C,2,0),"") -> 20 | N113: 200 | O113: =IFERROR(M113*N113,"") -> 4000 | P113: Yes | R113: 45748 | U113: 230 | V113: 31 | W113: =IFERROR(U113*V113,"0") -> 7130 | Y113: =IFERROR((O113/1000)*Masters!$C$3,"0") -> 380 | AA113: =IFERROR(VLOOKUP(L113,Masters!G:H,2,0),"0") -> 5 | AB113: =IFERROR(AA113*N113,"0") -> 1000 | AE113: =W113+Y113+AB113+AD113 -> 8510 | AG113: =M113&"-"&F113 -> 20-101-250Km | AH113: =IFERROR(VLOOKUP(AG113,Masters!N:O,2,0),"0") -> 40 | AI113: =AH113*N113 -> 8000 | AK113: =AI113-AE113 -> -510 | AN113: =IFERROR(U113/2,"0") -> 115
... A127: =A126+1 -> 126 | B127: 45772 | C127: s/Drona/04/25/52 | D127: 45774 | E127: sahima motors | F127: 101-250Km | G127: bawal | H127: HR38AC0599 | I127: 1109 | J127: Fixed | K127: 120 | L127: 20L Buckets | M127: =IFERROR(VLOOKUP(L127,'Material Master'!B:C,2,0),"") -> 20 | N127: 300 | O127: =IFERROR(M127*N127,"") -> 6000 | P127: Yes | R127: 45748 | U127: 273 | V127: 31 | W127: =IFERROR(U127*V127,"0") -> 8463 | Y127: =IFERROR((O127/1000)*Masters!$C$3,"0") -> 570 | AA127: =IFERROR(VLOOKUP(L127,Masters!G:H,2,0),"0") -> 5 | AB127: =IFERROR(AA127*N127,"0") -> 1500 | AE127: =W127+Y127+AB127+AD127 -> 10533 | AG127: =M127&"-"&F127 -> 20-101-250Km | AH127: =IFERROR(VLOOKUP(AG127,Masters!N:O,2,0),"0") -> 40 | AI127: =AH127*N127 -> 12000 | AK127: =AI127-AE127 -> 1467 | AN127: =IFERROR(U127/2,"0") -> 136.5
A128: =A127+1 -> 127 | B128: 45772 | C128: s/Drona/04/25/53 | E128: jai goljeu motors | G128: tanakpur | I128: 709 | M128: =IFERROR(VLOOKUP(L128,'Material Master'!B:C,2,0),"") | O128: =IFERROR(M128*N128,"") | R128: 45748 | S128: CANCEL BY DRONA ( 20 L- 100 pcs) | V128: 31 | W128: =IFERROR(U128*V128,"0") -> 0 | Y128: =IFERROR((O128/1000)*Masters!$C$3,"0") -> 0 | AA128: =IFERROR(VLOOKUP(L128,Masters!G:H,2,0),"0") -> 0 | AB128: =IFERROR(AA128*N128,"0") -> 0 | AE128: =W128+Y128+AB128+AD128 -> 0 | AG128: =M128&"-"&F128 -> - | AH128: =IFERROR(VLOOKUP(AG128,Masters!N:O,2,0),"0") -> 0 | AI128: =AH128*N128 -> 0 | AK128: =AI128-AE128 -> 0 | AN128: =IFERROR(U128/2,"0") -> 0
A129: =A128+1 -> 128 | B129: 45773 | C129: s/Drona/04/25/54 | D129: 45774 | E129: amit auto wheels pvt ltd | F129: 251-400Km | G129: us nagar | H129: HR38AC7854 | I129: 709 | J129: Fixed | K129: 122 | L129: 20L Buckets | M129: =IFERROR(VLOOKUP(L129,'Material Master'!B:C,2,0),"") -> 20 | N129: 100 | O129: =IFERROR(M129*N129,"") -> 2000 | P129: Yes | R129: 45748 | U129: 543 | V129: 31 | W129: =IFERROR(U129*V129,"0") -> 16833 | Y129: =IFERROR((O129/1000)*Masters!$C$3,"0") -> 190 | AA129: =IFERROR(VLOOKUP(L129,Masters!G:H,2,0),"0") -> 5 | AB129: =IFERROR(AA129*N129,"0") -> 500 | AE129: =W129+Y129+AB129+AD129 -> 17523 | AG129: =M129&"-"&F129 -> 20-251-400Km | AH129: =IFERROR(VLOOKUP(AG129,Masters!N:O,2,0),"0") -> 68 | AI129: =AH129*N129 -> 6800 | AK129: =AI129-AE129 -> -10723 | AN129: =IFERROR(U129/2,"0") -> 271.5
A130: =A129+1 -> 129 | B130: 45775 | C130: s/Drona/04/25/55 | D130: 45775 | E130: ganganagar motros | F130: 0-100Km | G130: delhi | H130: HR38AC7243 | I130: 1109 | J130: Fixed | K130: 123 | L130: 20L Buckets | M130: =IFERROR(VLOOKUP(L130,'Material Master'!B:C,2,0),"") -> 20 | N130: 300 | O130: =IFERROR(M130*N130,"") -> 6000 | P130: Yes | R130: 45748 | U130: 74 | V130: 31 | W130: =IFERROR(U130*V130,"0") -> 2294 | Y130: =IFERROR((O130/1000)*Masters!$C$3,"0") -> 570 | AA130: =IFERROR(VLOOKUP(L130,Masters!G:H,2,0),"0") -> 5 | AB130: =IFERROR(AA130*N130,"0") -> 1500 | AE130: =W130+Y130+AB130+AD130 -> 4364 | AG130: =M130&"-"&F130 -> 20-0-100Km | AH130: =IFERROR(VLOOKUP(AG130,Masters!N:O,2,0),"0") -> 21 | AI130: =AH130*N130 -> 6300 | AK130: =AI130-AE130 -> 1936 | AN130: =IFERROR(U130/2,"0") -> 37
A131: =A130+1 -> 130 | B131: 45775 | C131: s/Drona/04/25/56 | D131: 45776 | E131: triumph auto parts distr pvt ltd | F131: 0-100Km | G131: bahadurgarh | H131: HR38AC0263 | I131: 909 | J131: Fixed | K131: 124 | L131: 20L Buckets | M131: =IFERROR(VLOOKUP(L131,'Material Master'!B:C,2,0),"") -> 20 | N131: 200 | O131: =IFERROR(M131*N131,"") -> 4000 | P131: Yes | R131: 45748 | U131: 134 | V131: 31 | W131: =IFERROR(U131*V131,"0") -> 4154 | Y131: =IFERROR((O131/1000)*Masters!$C$3,"0") -> 380 | AA131: =IFERROR(VLOOKUP(L131,Masters!G:H,2,0),"0") -> 5 | AB131: =IFERROR(AA131*N131,"0") -> 1000 | AE131: =W131+Y131+AB131+AD131 -> 5534 | AG131: =M131&"-"&F131 -> 20-0-100Km | AH131: =IFERROR(VLOOKUP(AG131,Masters!N:O,2,0),"0") -> 21 | AI131: =AH131*N131 -> 4200 | AK131: =AI131-AE131 -> -1334 | AN131: =IFERROR(U131/2,"0") -> 67
A132: =A131+1 -> 131 | B132: 45776 | C132: s/Drona/04/25/57 | D132: 45776 | E132: ashoka motors | F132: 101-250Km | G132: hisar | H132: HR38AC7243 | I132: 1109 | J132: Fixed | K132: 126 | L132: 20L Buckets | M132: =IFERROR(VLOOKUP(L132,'Material Master'!B:C,2,0),"") -> 20 | N132: 300 | O132: =IFERROR(M132*N132,"") -> 6000 | P132: Yes | R132: 45748 | U132: 347 | V132: 31 | W132: =IFERROR(U132*V132,"0") -> 10757 | Y132: =IFERROR((O132/1000)*Masters!$C$3,"0") -> 570 | AA132: =IFERROR(VLOOKUP(L132,Masters!G:H,2,0),"0") -> 5 | AB132: =IFERROR(AA132*N132,"0") -> 1500 | AE132: =W132+Y132+AB132+AD132 -> 12827 | AG132: =M132&"-"&F132 -> 20-101-250Km | AH132: =IFERROR(VLOOKUP(AG132,Masters!N:O,2,0),"0") -> 40 | AI132: =AH132*N132 -> 12000 | AK132: =AI132-AE132 -> -827 | AN132: =IFERROR(U132/2,"0") -> 173.5
A133: =A132+1 -> 132 | B133: 45776 | C133: s/Drona/04/25/58 | D133: 45776 | E133: triumph auto parts distr pvt ltd | F133: 101-250Km | G133: palwal | H133: HR38AC7854 | I133: 1109 | J133: Fixed | K133: 125 | L133: 20L Buckets | M133: =IFERROR(VLOOKUP(L133,'Material Master'!B:C,2,0),"") -> 20 | N133: 300 | O133: =IFERROR(M133*N133,"") -> 6000 | P133: Yes | R133: 45748 | U133: 317 | V133: 31 | W133: =IFERROR(U133*V133,"0") -> 9827 | Y133: =IFERROR((O133/1000)*Masters!$C$3,"0") -> 570 | AA133: =IFERROR(VLOOKUP(L133,Masters!G:H,2,0),"0") -> 5 | AB133: =IFERROR(AA133*N133,"0") -> 1500 | AE133: =W133+Y133+AB133+AD133 -> 11897 | AG133: =M133&"-"&F133 -> 20-101-250Km | AH133: =IFERROR(VLOOKUP(AG133,Masters!N:O,2,0),"0") -> 40 | AI133: =AH133*N133 -> 12000 | AK133: =AI133-AE133 -> 103 | AN133: =IFERROR(U133/2,"0") -> 158.5
...

Sheet Market Vehicle Data
A1: Date | B1: Vehicle No. | C1: Pickup Point | D1: Destination | E1: Driver Name | F1: Driver No. | G1: Fare
A2: 45742 | B2: HR69D3754 | C2: Sonipat | D2: Rewari | E2: SUERESH | F2: 9991915392 | G2: 4500
A3: 45742 | B3: HR39F5155 | C3: Sonipat | D3: Hisar | E3: AMIT | F3: 8930099027 | G3: 8500
A4: 45748 | B4: RJ32GB5198 | C4: Sonipat | D4: Shahpura | E4: SATPAL | F4: 9664161140 | G4: 15000
A5: 45748 | B5: RJ14GK8841 | C5: Sonipat | D5: Shahpura | E5: RAMBIR | F5: 7823062311 | G5: 15000
A6: 45750 | B6: Gj02xx9199 | C6: Sonipat | D6: Shahpura | E6: SONU | F6: 9358156970 | G6: 15000
A7: 45751 | B7: RJ14GQ2021 | C7: Sonipat | D7: Shahpura | E7: vikas | F7: 9991467044 | G7: 15000
A8: 45751 | B8: RJ32GC7626 | C8: Sonipat | D8: Shahpura | E8: anil | F8: 7568761465 | G8: 15000
A9: 45813 | B9: GJ02ZZ7600 | C9: Sonipat | D9: rewari | E9: sonu | F9: 9992503467 | G9: 13000
A10: 45822 | B10: RJ32GC3170 | C10: Sonipat | D10: Rewari | E10: anil | F10: 9812354689 | G10: 13000
A11: 45829 | B11: UP93AT8450 | C11: Sonipat | D11: Rewari | E11: SANJAY | F11: 9728516610 | G11: 13000
A12: 45855 | B12: HR69F2786 | C12: Sonipat | D12: Dharuhera | E12: amit | F12: 8528615343 | G12: 12000
A13: 45865 | B13: HR69F2786 | C13: Sonipat | D13: Dharuhera | E13: amit | F13: 8528615343 | G13: 12500
... A20: 45903 | B20: HR69D2623 | C20: Sonipat | D20: moradabad | E20: aslam | F20: 7015595178 | G20: 10000
A21: 45928 | B21: HR69F2786 | C21: Sonipat | D21: Dharuhera | E21: sahid | F21: 7015595178
A22: 45930 | B22: HR69F2786 | C22: Sonipat | D22: Dharuhera | E22: sahid | F22: 7015595178
A23: 45930 | B23: RJ02GC6043 | C23: Sonipat | D23: alwar | E23: nahim | F23: 9887891170
A24: 45936 | B24: RJ02GC6247 | C24: Sonipat | D24: alwar | E24: VIKAS | F24: 9812445367
A25: 45936 | B25: RJ02GC5261 | C25: Sonipat | D25: alwar | E25: SAHID | F25: 7014547833
A26: 45937 | B26: RJ02GB4919 | C26: Sonipat | D26: alwar | E26: JAHID | F26: 8053436689
A27: 45937 | B27: RJ02GC4928 | C27: Sonipat | D27: alwar | E27: VIKAS | F27: 7015544377
A28: 45938 | B28: RJ02GC4969 | C28: Sonipat | D28: alwar | E28: SUNIL | F28: 9991642276
A29: 45938 | B29: HR55AJ2829 | C29: Sonipat | D29: alwar | E29: NAHIM | F29: 7850091362
A30: 45938 | B30: RJ02GC5375 | C30: Sonipat | D30: alwar | E30: ARJUN | F30: 9812543300
A31: 45939 | B31: RJ02GC4847 | C31: Sonipat | D31: alwar | E31: RAMBIR | F31: 8053437891

Sheet Vehicle Readings
A1: Out Date | B1: In Date | C1: Vehicle No. | D1: Driver Name | E1: Out Reading | F1: In Reading | G1: Running | I1: Cost
A2: 45734 | B2: 45735 | C2: HR38AC7243 | D2: Saleem | E2: 91386 | F2: 91575 | G2: =IF((F2-E2)<0,0,(F2-E2)) -> 189 | I2: =IFERROR(SUMPRODUCT($G2*VLOOKUP($C2,'Vehicle Master'!$D:$F,3,0)),"") -> 5859
A3: 45734 | B3: 45735 | C3: HR38AC0263 | D3: Saikul | E3: 66666 | F3: 66805 | G3: =IF((F3-E3)<0,0,(F3-E3)) -> 139 | I3: =IFERROR(SUMPRODUCT($G3*VLOOKUP($C3,'Vehicle Master'!$D:$F,3,0)),"") -> 4309
A4: 45734 | B4: 45736 | C4: HR38AC0599 | D4: Akram | E4: 100949 | F4: 101270 | G4: =IF((F4-E4)<0,0,(F4-E4)) -> 321 | I4: =IFERROR(SUMPRODUCT($G4*VLOOKUP($C4,'Vehicle Master'!$D:$F,3,0)),"") -> 9951
A5: 45734 | B5: 45735 | C5: HR38AC7854 | D5: Jahid | E5: 88855 | F5: 88928 | G5: =IF((F5-E5)<0,0,(F5-E5)) -> 73 | I5: =IFERROR(SUMPRODUCT($G5*VLOOKUP($C5,'Vehicle Master'!$D:$F,3,0)),"") -> 2263
A6: 45735 | B6: 45736 | C6: HR38AC7854 | D6: Jahid | E6: 88928 | F6: 89111 | G6: =IF((F6-E6)<0,0,(F6-E6)) -> 183 | I6: =IFERROR(SUMPRODUCT($G6*VLOOKUP($C6,'Vehicle Master'!$D:$F,3,0)),"") -> 5673
A7: 45735 | B7: 45737 | C7: HR38AC0263 | D7: Saikul | E7: 66805 | F7: 67177 | G7: =IF((F7-E7)<0,0,(F7-E7)) -> 372 | I7: =IFERROR(SUMPRODUCT($G7*VLOOKUP($C7,'Vehicle Master'!$D:$F,3,0)),"") -> 11532
A8: 45735 | B8: 45736 | C8: HR38AC7243 | D8: Saleem | E8: 91575 | F8: 91741 | G8: =IF((F8-E8)<0,0,(F8-E8)) -> 166 | I8: =IFERROR(SUMPRODUCT($G8*VLOOKUP($C8,'Vehicle Master'!$D:$F,3,0)),"") -> 5146
A9: 45736 | B9: 45737 | C9: HR38AC0599 | D9: Yakil | E9: 101270 | F9: 101513 | G9: =IF((F9-E9)<0,0,(F9-E9)) -> 243 | I9: =IFERROR(SUMPRODUCT($G9*VLOOKUP($C9,'Vehicle Master'!$D:$F,3,0)),"") -> 7533
A10: 45736 | B10: 45737 | C10: HR38AC7243 | D10: Saleem | E10: 91741 | F10: 91887 | G10: =IF((F10-E10)<0,0,(F10-E10)) -> 146 | I10: =IFERROR(SUMPRODUCT($G10*VLOOKUP($C10,'Vehicle Master'!$D:$F,3,0)),"") -> 4526
A11: 45736 | B11: 45737 | C11: HR38AC7854 | D11: Jahid | E11: 89111 | F11: 89288 | G11: =IF((F11-E11)<0,0,(F11-E11)) -> 177 | I11: =IFERROR(SUMPRODUCT($G11*VLOOKUP($C11,'Vehicle Master'!$D:$F,3,0)),"") -> 5487
A12: 45737 | B12: 45738 | C12: HR38AC0263 | D12: Saikul | E12: 67177 | F12: 67548 | G12: =IF((F12-E12)<0,0,(F12-E12)) -> 371 | I12: =IFERROR(SUMPRODUCT($G12*VLOOKUP($C12,'Vehicle Master'!$D:$F,3,0)),"") -> 11501
A13: 45737 | B13: 45738 | C13: HR38AC0599 | D13: Yakil | E13: 101513 | F13: 101645 | G13: =IF((F13-E13)<0,0,(F13-E13)) -> 132 | I13: =IFERROR(SUMPRODUCT($G13*VLOOKUP($C13,'Vehicle Master'!$D:$F,3,0)),"") -> 4092
... A20: 45740 | B20: 45743 | C20: HR38AC0599 | D20: Yakil | E20: 101816 | F20: 102204 | G20: =IF((F20-E20)<0,0,(F20-E20)) -> 388 | I20: =IFERROR(SUMPRODUCT($G20*VLOOKUP($C20,'Vehicle Master'!$D:$F,3,0)),"") -> 12028
A21: 45741 | B21: 45742 | C21: HR38AC7854 | D21: Jahid | E21: 89813 | F21: 90037 | G21: 224 | I21: =IFERROR(SUMPRODUCT($G21*VLOOKUP($C21,'Vehicle Master'!$D:$F,3,0)),"") -> 6944
A22: 45741 | B22: 45742 | C22: HR38AC7243 | D22: Saleem | E22: 92248 | F22: 92391 | G22: 143 | I22: =IFERROR(SUMPRODUCT($G22*VLOOKUP($C22,'Vehicle Master'!$D:$F,3,0)),"") -> 4433
A23: 45741 | B23: 45742 | C23: HR38AC0263 | D23: Saikul | E23: 68068 | F23: 68208 | G23: 140 | I23: =IFERROR(SUMPRODUCT($G23*VLOOKUP($C23,'Vehicle Master'!$D:$F,3,0)),"") -> 4340
A24: 45742 | B24: 45743 | C24: HR38AC7243 | D24: Saleem | E24: 92391 | F24: 92563 | G24: 172 | I24: =IFERROR(SUMPRODUCT($G24*VLOOKUP($C24,'Vehicle Master'!$D:$F,3,0)),"") -> 5332
A25: 45742 | B25: 45743 | C25: HR38AC0263 | D25: Saikul | E25: 68208 | F25: 68387 | G25: 179 | I25: =IFERROR(SUMPRODUCT($G25*VLOOKUP($C25,'Vehicle Master'!$D:$F,3,0)),"") -> 5549
A26: 45742 | B26: 45743 | C26: HR38AC7854 | D26: Jahid | E26: 90037 | F26: 90160 | G26: 123 | I26: =IFERROR(SUMPRODUCT($G26*VLOOKUP($C26,'Vehicle Master'!$D:$F,3,0)),"") -> 3813
A27: 45743 | B27: 45743 | C27: HR38AC7854 | D27: Jahid | E27: 90161 | F27: 90340 | G27: 179 | I27: =IFERROR(SUMPRODUCT($G27*VLOOKUP($C27,'Vehicle Master'!$D:$F,3,0)),"") -> 5549
A28: 45743 | B28: 45743 | C28: HR38AC0599 | D28: Yakil | E28: 102204 | F28: 102240 | G28: 36 | I28: =IFERROR(SUMPRODUCT($G28*VLOOKUP($C28,'Vehicle Master'!$D:$F,3,0)),"") -> 1116
A29: 45743 | B29: 45744 | C29: HR38AC0263 | D29: Saikul | E29: 68387 | F29: 68567 | G29: 180 | I29: =IFERROR(SUMPRODUCT($G29*VLOOKUP($C29,'Vehicle Master'!$D:$F,3,0)),"") -> 5580
A30: 45744 | B30: 45745 | C30: HR38AC7854 | D30: Jahid | E30: 90340 | F30: 90515 | G30: 175 | I30: =IFERROR(SUMPRODUCT($G30*VLOOKUP($C30,'Vehicle Master'!$D:$F,3,0)),"") -> 5425
A31: 45744 | B31: 45746 | C31: HR38X6465 | D31: Saikul | E31: 282816 | F31: 283096 | G31: 280 | I31: =IFERROR(SUMPRODUCT($G31*VLOOKUP($C31,'Vehicle Master'!$D:$F,3,0)),"") -> 8400
A32: 45744 | B32: 45745 | C32: HR38AC7243 | D32: Saleem | E32: 92563 | F32: 92742 | G32: 179 | I32: =IFERROR(SUMPRODUCT($G32*VLOOKUP($C32,'Vehicle Master'!$D:$F,3,0)),"") -> 5549
... A36: 45745 | B36: 45746 | C36: HR38AC7854 | D36: Yakil | E36: 90515 | F36: 90696 | G36: 181 | I36: =IFERROR(SUMPRODUCT($G36*VLOOKUP($C36,'Vehicle Master'!$D:$F,3,0)),"") -> 5611
A37: 45745 | B37: 45746 | C37: HR38AC0599 | D37: Saleem | E37: 102636 | F37: 102770 | G37: =IF((F37-E37)<0,0,(F37-E37)) -> 134 | I37: =IFERROR(SUMPRODUCT($G37*VLOOKUP($C37,'Vehicle Master'!$D:$F,3,0)),"") -> 4154
A38: 45745 | B38: 45746 | C38: HR38AC7243 | D38: Jahid | E38: 92742 | F38: 93040 | G38: =IF((F38-E38)<0,0,(F38-E38)) -> 298 | I38: =IFERROR(SUMPRODUCT($G38*VLOOKUP($C38,'Vehicle Master'!$D:$F,3,0)),"") -> 9238
A39: 45746 | B39: 45747 | C39: HR38X6465 | D39: Saikul | E39: 283096 | F39: 283286 | G39: =IF((F39-E39)<0,0,(F39-E39)) -> 190 | I39: =IFERROR(SUMPRODUCT($G39*VLOOKUP($C39,'Vehicle Master'!$D:$F,3,0)),"") -> 5700
A40: 45746 | B40: 45747 | C40: HR38AC0263 | D40: Saleem | E40: 68819 | F40: 68970 | G40: =IF((F40-E40)<0,0,(F40-E40)) -> 151 | I40: =IFERROR(SUMPRODUCT($G40*VLOOKUP($C40,'Vehicle Master'!$D:$F,3,0)),"") -> 4681
A41: 45746 | B41: 45747 | C41: HR38AC0599 | D41: Jahid | E41: 102695 | F41: 102912 | G41: =IF((F41-E41)<0,0,(F41-E41)) -> 217 | I41: =IFERROR(SUMPRODUCT($G41*VLOOKUP($C41,'Vehicle Master'!$D:$F,3,0)),"") -> 6727
A42: 45746 | B42: 45747 | C42: HR38AC7854 | D42: Saleem | E42: 90696 | F42: 90808 | G42: =IF((F42-E42)<0,0,(F42-E42)) -> 112 | I42: =IFERROR(SUMPRODUCT($G42*VLOOKUP($C42,'Vehicle Master'!$D:$F,3,0)),"") -> 3472
A43: 45747 | B43: 45748 | C43: HR38X6465 | D43: Jahid | E43: 283286 | F43: 283533 | G43: =IF((F43-E43)<0,0,(F43-E43)) -> 247 | I43: =IFERROR(SUMPRODUCT($G43*VLOOKUP($C43,'Vehicle Master'!$D:$F,3,0)),"") -> 7410
A44: 45747 | B44: 45748 | C44: HR38AC0599 | D44: Saikul | E44: 102912 | F44: 103093 | G44: =IF((F44-E44)<0,0,(F44-E44)) -> 181 | I44: =IFERROR(SUMPRODUCT($G44*VLOOKUP($C44,'Vehicle Master'!$D:$F,3,0)),"") -> 5611
A45: 45747 | B45: 45748 | C45: HR38AC0263 | D45: Saleem | E45: 68970 | F45: 69144 | G45: =IF((F45-E45)<0,0,(F45-E45)) -> 174 | I45: =IFERROR(SUMPRODUCT($G45*VLOOKUP($C45,'Vehicle Master'!$D:$F,3,0)),"") -> 5394
A46: 45747 | B46: 45748 | C46: HR38AC7854 | D46: Jahid | E46: 90808 | F46: 90920 | G46: =IF((F46-E46)<0,0,(F46-E46)) -> 112 | I46: =IFERROR(SUMPRODUCT($G46*VLOOKUP($C46,'Vehicle Master'!$D:$F,3,0)),"") -> 3472
A47: 45748 | B47: 45749 | C47: HR38X6465 | D47: Saikul | E47: 283533 | F47: 284107 | G47: =IF((F47-E47)<0,0,(F47-E47)) -> 574 | I47: =IFERROR(SUMPRODUCT($G47*VLOOKUP($C47,'Vehicle Master'!$D:$F,3,0)),"") -> 17220
A48: 45748 | B48: 45749 | C48: HR38AC0263 | D48: Sarvesh | E48: 69144 | F48: 69320 | G48: =IF((F48-E48)<0,0,(F48-E48)) -> 176 | I48: =IFERROR(SUMPRODUCT($G48*VLOOKUP($C48,'Vehicle Master'!$D:$F,3,0)),"") -> 5456
... A146: 45785 | B146: 45786 | C146: HR38AC7243 | D146: Premsagar | E146: 99519 | F146: 99669 | G146: =IF((F146-E146)<0,0,(F146-E146)) -> 150 | I146: =IFERROR(SUMPRODUCT($G146*VLOOKUP($C146,'Vehicle Master'!$D:$F,3,0)),"") -> 4650
A147: 45786 | B147: 45787 | C147: HR38AC7854 | D147: Ravi | E147: 97199 | F147: 97382 | G147: 183 | I147: =IFERROR(SUMPRODUCT($G147*VLOOKUP($C147,'Vehicle Master'!$D:$F,3,0)),"") -> 5673
A148: 45786 | B148: 45786 | C148: HR38AC0263 | D148: Sarvesh | E148: 75615 | F148: 75770 | G148: =IF((F148-E148)<0,0,(F148-E148)) -> 155 | I148: =IFERROR(SUMPRODUCT($G148*VLOOKUP($C148,'Vehicle Master'!$D:$F,3,0)),"") -> 4805
A149: 45787 | B149: 45789 | C149: HR38AC0599 | D149: Javid | E149: 109613 | F149: 109993 | G149: =IF((F149-E149)<0,0,(F149-E149)) -> 380 | I149: =IFERROR(SUMPRODUCT($G149*VLOOKUP($C149,'Vehicle Master'!$D:$F,3,0)),"") -> 11780
A150: 45787 | B150: 45788 | C150: HR38AC7243 | D150: Premsagar | E150: 99669 | F150: 99967 | G150: =IF((F150-E150)<0,0,(F150-E150)) -> 298 | I150: =IFERROR(SUMPRODUCT($G150*VLOOKUP($C150,'Vehicle Master'!$D:$F,3,0)),"") -> 9238
A151: 45787 | B151: 45788 | C151: HR38AC0263 | D151: Sarvesh | E151: 75770 | F151: 76006 | G151: =IF((F151-E151)<0,0,(F151-E151)) -> 236 | I151: =IFERROR(SUMPRODUCT($G151*VLOOKUP($C151,'Vehicle Master'!$D:$F,3,0)),"") -> 7316
A152: 45789 | B152: 45789 | C152: HR38AC7854 | D152: Ravi | E152: 97382 | F152: 97485 | G152: =IF((F152-E152)<0,0,(F152-E152)) -> 103 | I152: =IFERROR(SUMPRODUCT($G152*VLOOKUP($C152,'Vehicle Master'!$D:$F,3,0)),"") -> 3193
A153: 45789 | B153: 45789 | C153: HR38AC0263 | D153: Sarvesh | E153: 76006 | F153: 76185 | G153: =IF((F153-E153)<0,0,(F153-E153)) -> 179 | I153: =IFERROR(SUMPRODUCT($G153*VLOOKUP($C153,'Vehicle Master'!$D:$F,3,0)),"") -> 5549
A154: 45790 | B154: 45790 | C154: HR38AC7243 | D154: Premsagar | E154: 99967 | F154: 100040 | G154: =IF((F154-E154)<0,0,(F154-E154)) -> 73 | I154: =IFERROR(SUMPRODUCT($G154*VLOOKUP($C154,'Vehicle Master'!$D:$F,3,0)),"") -> 2263
A155: 45790 | B155: 45791 | C155: HR38AC0599 | D155: Javid | E155: 109993 | F155: 110145 | G155: =IF((F155-E155)<0,0,(F155-E155)) -> 152 | I155: =IFERROR(SUMPRODUCT($G155*VLOOKUP($C155,'Vehicle Master'!$D:$F,3,0)),"") -> 4712
A156: 45790 | B156: 45791 | C156: HR38AC7854 | D156: Ravi | E156: 97485 | F156: 98123 | G156: =IF((F156-E156)<0,0,(F156-E156)) -> 638 | I156: =IFERROR(SUMPRODUCT($G156*VLOOKUP($C156,'Vehicle Master'!$D:$F,3,0)),"") -> 19778
A157: 45791 | B157: 45791 | C157: HR38AC0263 | D157: Sarvesh | E157: 76185 | F157: 76259 | G157: =IF((F157-E157)<0,0,(F157-E157)) -> 74 | I157: =IFERROR(SUMPRODUCT($G157*VLOOKUP($C157,'Vehicle Master'!$D:$F,3,0)),"") -> 2294
A158: 45791 | B158: 45791 | C158: HR38AC7243 | D158: Premsagar | E158: 100040 | F158: 100115 | G158: =IF((F158-E158)<0,0,(F158-E158)) -> 75 | I158: =IFERROR(SUMPRODUCT($G158*VLOOKUP($C158,'Vehicle Master'!$D:$F,3,0)),"") -> 2325
A159: 45791 | B159: 45792 | C159: HR38AC0599 | D159: Javid | E159: 110145 | F159: 110231 | G159: =IF((F159-E159)<0,0,(F159-E159)) -> 86 | I159: =IFERROR(SUMPRODUCT($G159*VLOOKUP($C159,'Vehicle Master'!$D:$F,3,0)),"") -> 2666
... A309: 45857 | B309: 45858 | C309: HR38AC0263 | D309: Sarvesh | E309: 86025 | F309: 86376 | G309: =IF((F309-E309)<0,0,(F309-E309)) -> 351 | I309: =IFERROR(SUMPRODUCT($G309*VLOOKUP($C309,'Vehicle Master'!$D:$F,3,0)),"") -> 10881
A310: 45857 | B310: 45858 | C310: HR38AC0599 | D310: Javid | E310: 120720 | F310: 120803 | G310: 83 | I310: =IFERROR(SUMPRODUCT($G310*VLOOKUP($C310,'Vehicle Master'!$D:$F,3,0)),"") -> 2573
A311: 45859 | B311: 45860 | C311: HR38AC0263 | D311: Sarvesh | E311: 86376 | F311: 86492 | G311: =IF((F311-E311)<0,0,(F311-E311)) -> 116 | I311: =IFERROR(SUMPRODUCT($G311*VLOOKUP($C311,'Vehicle Master'!$D:$F,3,0)),"") -> 3596
A312: 45859 | B312: 45860 | C312: HR38AC0599 | D312: Javid | E312: 120803 | F312: 121408 | G312: =IF((F312-E312)<0,0,(F312-E312)) -> 605 | I312: =IFERROR(SUMPRODUCT($G312*VLOOKUP($C312,'Vehicle Master'!$D:$F,3,0)),"") -> 18755
A313: 45860 | B313: 45861 | C313: HR38AC7854 | D313: Ravi | E313: 107232 | F313: 107601 | G313: =IF((F313-E313)<0,0,(F313-E313)) -> 369 | I313: =IFERROR(SUMPRODUCT($G313*VLOOKUP($C313,'Vehicle Master'!$D:$F,3,0)),"") -> 11439
A314: 45860 | B314: 45861 | C314: HR38AC7243 | D314: Premsagar | E314: 109405 | F314: 109289 | G314: 116 | I314: =IFERROR(SUMPRODUCT($G314*VLOOKUP($C314,'Vehicle Master'!$D:$F,3,0)),"") -> 3596
A315: 45860 | B315: 45860 | C315: HR38AC0263 | D315: Sarvesh | E315: 86492 | F315: 86554 | G315: =IF((F315-E315)<0,0,(F315-E315)) -> 62 | I315: =IFERROR(SUMPRODUCT($G315*VLOOKUP($C315,'Vehicle Master'!$D:$F,3,0)),"") -> 1922
A316: 45861 | B316: 45861 | C316: HR38AC0599 | D316: Javid | E316: 121408 | F316: 121465 | G316: =IF((F316-E316)<0,0,(F316-E316)) -> 57 | I316: =IFERROR(SUMPRODUCT($G316*VLOOKUP($C316,'Vehicle Master'!$D:$F,3,0)),"") -> 1767
A317: 45861 | B317: 45863 | C317: HR38AC0263 | D317: Sarvesh | E317: 86554 | F317: 86825 | G317: =IF((F317-E317)<0,0,(F317-E317)) -> 271 | I317: =IFERROR(SUMPRODUCT($G317*VLOOKUP($C317,'Vehicle Master'!$D:$F,3,0)),"") -> 8401
A318: 45861 | B318: 45862 | C318: HR38AC7243 | D318: Premsagar | E318: 109289 | F318: 109523 | G318: =IF((F318-E318)<0,0,(F318-E318)) -> 234 | I318: =IFERROR(SUMPRODUCT($G318*VLOOKUP($C318,'Vehicle Master'!$D:$F,3,0)),"") -> 7254
A319: 45861 | B319: 45862 | C319: HR38AC0599 | D319: Javid | E319: 121408 | F319: 121648 | G319: =IF((F319-E319)<0,0,(F319-E319)) -> 240 | I319: =IFERROR(SUMPRODUCT($G319*VLOOKUP($C319,'Vehicle Master'!$D:$F,3,0)),"") -> 7440 | J319: 2ND TRIP
A320: 45862 | B320: 45862 | C320: HR38AC7854 | D320: Ravi | E320: 107601 | F320: 107783 | G320: =IF((F320-E320)<0,0,(F320-E320)) -> 182 | I320: =IFERROR(SUMPRODUCT($G320*VLOOKUP($C320,'Vehicle Master'!$D:$F,3,0)),"") -> 5642
A321: 45862 | B321: 45863 | C321: HR38AC7243 | D321: Premsagar | E321: 109523 | F321: 109673 | G321: =IF((F321-E321)<0,0,(F321-E321)) -> 150 | I321: =IFERROR(SUMPRODUCT($G321*VLOOKUP($C321,'Vehicle Master'!$D:$F,3,0)),"") -> 4650 | J321: 109848
A322: 45862 | B322: 45863 | C322: HR38AC0599 | D322: Javid | E322: 121648 | F322: 122294 | G322: =IF((F322-E322)<0,0,(F322-E322)) -> 646 | I322: =IFERROR(SUMPRODUCT($G322*VLOOKUP($C322,'Vehicle Master'!$D:$F,3,0)),"") -> 20026
A323: 45863 | B323: 45867 | C323: HR38AC7854 | D323: Ravi | E323: 107783 | F323: 108407 | G323: =IF((F323-E323)<0,0,(F323-E323)) -> 624 | I323: =IFERROR(SUMPRODUCT($G323*VLOOKUP($C323,'Vehicle Master'!$D:$F,3,0)),"") -> 19344
A324: 45863 | B324: 45867 | C324: HR38AC7243 | D324: Premsagar | E324: 109848 | F324: 110260 | G324: =IF((F324-E324)<0,0,(F324-E324)) -> 412 | I324: =IFERROR(SUMPRODUCT($G324*VLOOKUP($C324,'Vehicle Master'!$D:$F,3,0)),"") -> 12772
A325: 45864 | B325: 45864 | C325: HR38AC0599 | D325: Javid | E325: 122294 | F325: 122524 | G325: =IF((F325-E325)<0,0,(F325-E325)) -> 230 | I325: =IFERROR(SUMPRODUCT($G325*VLOOKUP($C325,'Vehicle Master'!$D:$F,3,0)),"") -> 7130
A326: 45864 | B326: 45864 | C326: HR38AC0263 | D326: Ravi | E326: 86825 | F326: 87004 | G326: =IF((F326-E326)<0,0,(F326-E326)) -> 179 | I326: =IFERROR(SUMPRODUCT($G326*VLOOKUP($C326,'Vehicle Master'!$D:$F,3,0)),"") -> 5549
A327: 45865 | B327: 45866 | C327: HR38AC0599 | D327: Javid | E327: 122524 | F327: 122731 | G327: =IF((F327-E327)<0,0,(F327-E327)) -> 207 | I327: =IFERROR(SUMPRODUCT($G327*VLOOKUP($C327,'Vehicle Master'!$D:$F,3,0)),"") -> 6417
A328: 45865 | B328: 45866 | C328: HR38AC0263 | D328: Ravi | E328: 87004 | F328: 87234 | G328: =IF((F328-E328)<0,0,(F328-E328)) -> 230 | I328: =IFERROR(SUMPRODUCT($G328*VLOOKUP($C328,'Vehicle Master'!$D:$F,3,0)),"") -> 7130
A329: 45866 | B329: 45867 | C329: HR38AC0599 | D329: Javid | E329: 122731 | F329: 123157 | G329: =IF((F329-E329)<0,0,(F329-E329)) -> 426 | I329: =IFERROR(SUMPRODUCT($G329*VLOOKUP($C329,'Vehicle Master'!$D:$F,3,0)),"") -> 13206
A330: 45866 | B330: 45867 | C330: HR38AC0263 | D330: Ravi | E330: 87234 | F330: 87362 | G330: =IF((F330-E330)<0,0,(F330-E330)) -> 128 | I330: =IFERROR(SUMPRODUCT($G330*VLOOKUP($C330,'Vehicle Master'!$D:$F,3,0)),"") -> 3968
A331: 45867 | B331: 45868 | C331: HR38AC0263 | D331: Ravi | E331: 87362 | F331: 87575 | G331: =IF((F331-E331)<0,0,(F331-E331)) -> 213 | I331: =IFERROR(SUMPRODUCT($G331*VLOOKUP($C331,'Vehicle Master'!$D:$F,3,0)),"") -> 6603
A332: 45867 | B332: 45868 | C332: HR38AC7243 | D332: Premsagar | E332: 110260 | F332: 110475 | G332: =IF((F332-E332)<0,0,(F332-E332)) -> 215 | I332: =IFERROR(SUMPRODUCT($G332*VLOOKUP($C332,'Vehicle Master'!$D:$F,3,0)),"") -> 6665
A333: 45868 | B333: 45871 | C333: HR38AC0599 | D333: Javid | E333: 123157 | F333: 123236 | G333: =IF((F333-E333)<0,0,(F333-E333)) -> 79 | I333: =IFERROR(SUMPRODUCT($G333*VLOOKUP($C333,'Vehicle Master'!$D:$F,3,0)),"") -> 2449 | J333: 2 days hold from drona some issue
A334: 45868 | B334: 45871 | C334: HR38AC7854 | D334: Ravi | E334: 118407 | F334: 108771 | G334: 364 | I334: =IFERROR(SUMPRODUCT($G334*VLOOKUP($C334,'Vehicle Master'!$D:$F,3,0)),"") -> 11284 | J334: 2 days hold from drona some issue
A335: 45869 | B335: 45871 | C335: HR38AC0263 | D335: Sarvesh | E335: 87575 | F335: 87724 | G335: =IF((F335-E335)<0,0,(F335-E335)) -> 149 | I335: =IFERROR(SUMPRODUCT($G335*VLOOKUP($C335,'Vehicle Master'!$D:$F,3,0)),"") -> 4619 | J335: 2 days hold from drona some issue
A336: 45869 | B336: 45871 | C336: HR38AC7243 | D336: Premsagar | E336: 110475 | F336: 110626 | G336: =IF((F336-E336)<0,0,(F336-E336)) -> 151 | I336: =IFERROR(SUMPRODUCT($G336*VLOOKUP($C336,'Vehicle Master'!$D:$F,3,0)),"") -> 4681 | J336: 2 days hold from drona some issue
A337: 45873 | B337: 45874 | C337: HR38AC0263 | D337: Ravi | E337: 87724 | F337: 87980 | G337: =IF((F337-E337)<0,0,(F337-E337)) -> 256 | I337: =IFERROR(SUMPRODUCT($G337*VLOOKUP($C337,'Vehicle Master'!$D:$F,3,0)),"") -> 7936
A338: 45873 | B338: 45875 | C338: HR38AC0599 | D338: Javid | E338: 123236 | F338: 123723 | G338: =IF((F338-E338)<0,0,(F338-E338)) -> 487 | I338: =IFERROR(SUMPRODUCT($G338*VLOOKUP($C338,'Vehicle Master'!$D:$F,3,0)),"") -> 15097
A339: 45874 | B339: 45874 | C339: HR38AC7243 | D339: Premsagar | E339: 110626 | F339: 110682 | G339: =IF((F339-E339)<0,0,(F339-E339)) -> 56 | I339: =IFERROR(SUMPRODUCT($G339*VLOOKUP($C339,'Vehicle Master'!$D:$F,3,0)),"") -> 1736
A340: 45874 | B340: 45874 | C340: HR38AC7854 | D340: vipin | E340: 108771 | F340: 108881 | G340: =IF((F340-E340)<0,0,(F340-E340)) -> 110 | I340: =IFERROR(SUMPRODUCT($G340*VLOOKUP($C340,'Vehicle Master'!$D:$F,3,0)),"") -> 3410
A341: 45874 | B341: 45875 | C341: HR38AC0263 | D341: Ravi | E341: 87980 | F341: 88212 | G341: =IF((F341-E341)<0,0,(F341-E341)) -> 232 | I341: =IFERROR(SUMPRODUCT($G341*VLOOKUP($C341,'Vehicle Master'!$D:$F,3,0)),"") -> 7192
A342: 45875 | B342: 45875 | C342: HR38AC7243 | D342: Premsagar | E342: 110682 | F342: 110836 | G342: =IF((F342-E342)<0,0,(F342-E342)) -> 154 | I342: =IFERROR(SUMPRODUCT($G342*VLOOKUP($C342,'Vehicle Master'!$D:$F,3,0)),"") -> 4774
A343: 45876 | B343: 45876 | C343: HR38AC7854 | D343: vipin | E343: 108881 | F343: 108949 | G343: =IF((F343-E343)<0,0,(F343-E343)) -> 68 | I343: =IFERROR(SUMPRODUCT($G343*VLOOKUP($C343,'Vehicle Master'!$D:$F,3,0)),"") -> 2108
A344: 45877 | B344: 45880 | C344: HR38AC0263 | D344: Ravi | E344: 88212 | F344: 88300 | G344: =IF((F344-E344)<0,0,(F344-E344)) -> 88 | I344: =IFERROR(SUMPRODUCT($G344*VLOOKUP($C344,'Vehicle Master'!$D:$F,3,0)),"") -> 2728
A345: 45880 | B345: 45880 | C345: HR38AC0599 | D345: Javid | E345: 123723 | F345: 123799 | G345: =IF((F345-E345)<0,0,(F345-E345)) -> 76 | I345: =IFERROR(SUMPRODUCT($G345*VLOOKUP($C345,'Vehicle Master'!$D:$F,3,0)),"") -> 2356
A346: 45881 | B346: 45883 | C346: HR38AC0263 | D346: Ravi | E346: 88300 | F346: 88673 | G346: =IF((F346-E346)<0,0,(F346-E346)) -> 373 | I346: =IFERROR(SUMPRODUCT($G346*VLOOKUP($C346,'Vehicle Master'!$D:$F,3,0)),"") -> 11563
A347: 45881 | B347: 45883 | C347: HR38AC0599 | D347: Javid | E347: 123799 | F347: 124121 | G347: =IF((F347-E347)<0,0,(F347-E347)) -> 322 | I347: =IFERROR(SUMPRODUCT($G347*VLOOKUP($C347,'Vehicle Master'!$D:$F,3,0)),"") -> 9982
A348: 45882 | B348: 45884 | C348: HR38AC7854 | D348: vipin | E348: 108949 | F348: 109407 | G348: =IF((F348-E348)<0,0,(F348-E348)) -> 458 | I348: =IFERROR(SUMPRODUCT($G348*VLOOKUP($C348,'Vehicle Master'!$D:$F,3,0)),"") -> 14198
A349: 45882 | B349: 45885 | C349: HR38AC7243 | D349: Premsagar | E349: 110836 | F349: 111370 | G349: =IF((F349-E349)<0,0,(F349-E349)) -> 534 | I349: =IFERROR(SUMPRODUCT($G349*VLOOKUP($C349,'Vehicle Master'!$D:$F,3,0)),"") -> 16554
A350: 45882 | B350: 45885 | C350: HR38AC0263 | D350: Ravi | E350: 88673 | F350: 88976 | G350: =IF((F350-E350)<0,0,(F350-E350)) -> 303
A351: 45883 | B351: 45883 | C351: HR38AC0599 | D351: Javid | E351: 124121 | F351: 124289 | G351: =IF((F351-E351)<0,0,(F351-E351)) -> 168 | I351: =IFERROR(SUMPRODUCT($G351*VLOOKUP($C351,'Vehicle Master'!$D:$F,3,0)),"") -> 5208
A352: 45885 | B352: 45886 | C352: HR38AC7854 | D352: vipin | E352: 109407 | F352: 109667 | G352: =IF((F352-E352)<0,0,(F352-E352)) -> 260 | I352: =IFERROR(SUMPRODUCT($G352*VLOOKUP($C352,'Vehicle Master'!$D:$F,3,0)),"") -> 8060
A353: 45887 | B353: 45888 | C353: HR38AC0599 | D353: Javid | E353: 124289 | F353: 124688 | G353: =IF((F353-E353)<0,0,(F353-E353)) -> 399 | I353: =IFERROR(SUMPRODUCT($G353*VLOOKUP($C353,'Vehicle Master'!$D:$F,3,0)),"") -> 12369
A354: 45889 | B354: 45890 | C354: HR38AC0263 | D354: Ravi | E354: 88976 | F354: 89615 | G354: =IF((F354-E354)<0,0,(F354-E354)) -> 639 | I354: =IFERROR(SUMPRODUCT($G354*VLOOKUP($C354,'Vehicle Master'!$D:$F,3,0)),"") -> 19809
A355: 45890 | B355: 45891 | C355: HR38AC7243 | D355: Premsagar | E355: 111370 | F355: 112041 | G355: =IF((F355-E355)<0,0,(F355-E355)) -> 671 | I355: =IFERROR(SUMPRODUCT($G355*VLOOKUP($C355,'Vehicle Master'!$D:$F,3,0)),"") -> 20801
...

Sheet Vehicle Master
A1: S.No | B1: Vehicle Type | C1: Model | D1: Vehicle Number | E1: Total Running | F1: Total Cost (Rs./Kms) | G1: Monthly Rate
A2: 1 | B2: 1109 | C2: Fixed | D2: HR38AC0263 | E2: =SUMIF('Vehicle Readings'!C:C,'Vehicle Master'!D2,'Vehicle Readings'!G:G) -> 32204 | F2: =G2/5000 -> 31 | G2: 155000
A3: =A2+1 -> 2 | B3: 1109 | C3: Fixed | D3: HR38AC7854 | E3: =SUMIF('Vehicle Readings'!C:C,'Vehicle Master'!D3,'Vehicle Readings'!G:G) -> 32097 | F3: =G3/5000 -> 31 | G3: 155000
A4: =A3+1 -> 3 | B4: 1109 | C4: Fixed | D4: HR38AC0599 | E4: =SUMIF('Vehicle Readings'!C:C,'Vehicle Master'!D4,'Vehicle Readings'!G:G) -> 32495 | F4: =G4/5000 -> 31 | G4: 155000
A5: =A4+1 -> 4 | B5: 1109 | C5: Fixed | D5: HR38AC7243 | E5: =SUMIF('Vehicle Readings'!C:C,'Vehicle Master'!D5,'Vehicle Readings'!G:G) -> 29618 | F5: =G5/5000 -> 31 | G5: 155000
A6: 5 | B6: 709 | C6: Market | D6: HR69D3754
A7: 6 | B7: 1109 | C7: Market | D7: HR39F5155
A8: 7 | B8: 909 | C8: Fixed | D8: HR38X6465 | E8: =SUMIF('Vehicle Readings'!C:C,'Vehicle Master'!D8,'Vehicle Readings'!G:G) -> 1472 | F8: =G8/(5000/3) -> 30 | G8: 50000
A9: 8 | B9: 709 | C9: Fixed | D9: HR38X6465 | E9: =SUMIF('Vehicle Readings'!C:C,'Vehicle Master'!D9,'Vehicle Readings'!G:G) -> 1472 | F9: =G9/(5000/3) -> 30 | G9: 50000
A10: 9 | B10: 2515 | C10: market | D10: RJ32GB5198
A11: 10 | B11: 2515 | C11: market | D11: RJ14GK8841
A12: 11 | B12: 2515 | C12: Market | D12: Gj02xx9199
A13: 12 | B13: 2515 | C13: Market | D13: RJ14GQ2021
A14: 13 | B14: 2515 | C14: Market | D14: RJ32GC7626
A15: 14 | B15: 2515 | C15: Market | D15: GJ02ZZ7600
A16: 15 | B16: 2515 | C16: Market | D16: RJ32GC3170
A17: 16 | B17: 2515 | C17: Market | D17: UP93AT8450
A18: 17 | B18: 2515 | C18: Market | D18: HR69F2786
A19: 18 | B19: 2515 | C19: Market | D19: HR55AN6307
A20: 19 | B20: 1109 | C20: Market | D20: RJ02GC6249
A21: 20 | B21: 1109 | C21: Market | D21: HR55AK9163
... A34: 32 | B34: 2515 | C34: Market | D34: RJ02GC4847

Sheet Category & Range Wise Outward
D1: 0-100Km | G1: 101-250Km | J1: 251-400Km | M1: 401-600Km | P1: Total
A2: Date | B2: LR Count | C2: Load (Ton) | D2: {=TRANSPOSE('Material Master'!$B$2:$B$4)} -> 20L Buckets | E2: 20L Jerry Can | F2: 210L Barrels | G2: {=TRANSPOSE('Material Master'!$B$2:$B$4)} -> 20L Buckets | H2: 20L Jerry Can | I2: 210L Barrels | J2: {=TRANSPOSE('Material Master'!$B$2:$B$4)} -> 20L Buckets | K2: 20L Jerry Can | L2: 210L Barrels | M2: {=TRANSPOSE('Material Master'!$B$2:$B$4)} -> 20L Buckets | N2: 20L Jerry Can | O2: 210L Barrels | P2: {=TRANSPOSE('Material Master'!$B$2:$B$4)} -> 20L Buckets | Q2: 20L Jerry Can | R2: 210L Barrels
A3: 45734 | B3: {=IF(A3>TODAY(),"",COUNTA(_xlfn.UNIQUE(_xlfn._xlws.FILTER('OPs Data'!$K:$K,'OPs Data'!$D:$D='Category & Range Wise Outward'!A3))))} -> 4 | C3: =IF(A3>TODAY(),"",SUMIF('OPs Data'!$D:$D,'Category & Range Wise Outward'!$A3,'OPs Data'!O:O)/1000) -> 22.63 | D3: =IF(A3>TODAY(),"",SUMIFS('OPs Data'!$N:$N,'OPs Data'!$F:$F,'Category & Range Wise Outward'!D$1,'OPs Data'!$D:$D,'Category & Range Wise Outward'!$A3,'OPs Data'!$L:$L,'Category & Range Wise Outward'!D$2)) -> 800 | E3: =IF(A3>TODAY(),"",SUMIFS('OPs Data'!$N:$N,'OPs Data'!$F:$F,'Category & Range Wise Outward'!D$1,'OPs Data'!$D:$D,'Category & Range Wise Outward'!$A3,'OPs Data'!$L:$L,'Category & Range Wise Outward'!E$2)) -> 0 | F3: =IF(A3>TODAY(),"",SUMIFS('OPs Data'!$N:$N,'OPs Data'!$F:$F,'Category & Range Wise Outward'!D$1,'OPs Data'!$D:$D,'Category & Range Wise Outward'!$A3,'OPs Data'!$L:$L,'Category & Range Wise Outward'!F$2)) -> 3 | G3: =IF(E3>TODAY(),"",SUMIFS('OPs Data'!$N:$N,'OPs Data'!$F:$F,'Category & Range Wise Outward'!G$1,'OPs Data'!$D:$D,'Category & Range Wise Outward'!$A3,'OPs Data'!$L:$L,'Category & Range Wise Outward'!G$2)) -> 300 | H3: =IF(E3>TODAY(),"",SUMIFS('OPs Data'!$N:$N,'OPs Data'!$F:$F,'Category & Range Wise Outward'!G$1,'OPs Data'!$D:$D,'Category & Range Wise Outward'!$A3,'OPs Data'!$L:$L,'Category & Range Wise Outward'!H$2)) -> 0 | I3: =IF(E3>TODAY(),"",SUMIFS('OPs Data'!$N:$N,'OPs Data'!$F:$F,'Category & Range Wise Outward'!G$1,'OPs Data'!$D:$D,'Category & Range Wise Outward'!$A3,'OPs Data'!$L:$L,'Category & Range Wise Outward'!I$2)) -> 0 | J3: =IF(H3>TODAY(),"",SUMIFS('OPs Data'!$N:$N,'OPs Data'!$F:$F,'Category & Range Wise Outward'!J$1,'OPs Data'!$D:$D,'Category & Range Wise Outward'!$A3,'OPs Data'!$L:$L,'Category & Range Wise Outward'!J$2)) -> 0 | K3: =IF(H3>TODAY(),"",SUMIFS('OPs Data'!$N:$N,'OPs Data'!$F:$F,'Category & Range Wise Outward'!J$1,'OPs Data'!$D:$D,'Category & Range Wise Outward'!$A3,'OPs Data'!$L:$L,'Category & Range Wise Outward'!K$2)) -> 0 | L3: =IF(H3>TODAY(),"",SUMIFS('OPs Data'!$N:$N,'OPs Data'!$F:$F,'Category & Range Wise Outward'!J$1,'OPs Data'!$D:$D,'Category & Range Wise Outward'!$A3,'OPs Data'!$L:$L,'Category & Range Wise Outward'!L$2)) -> 0 | M3: =IF(K3>TODAY(),"",SUMIFS('OPs Data'!$N:$N,'OPs Data'!$F:$F,'Category & Range Wise Outward'!M$1,'OPs Data'!$D:$D,'Category & Range Wise Outward'!$A3,'OPs Data'!$L:$L,'Category & Range Wise Outward'!M$2)) -> 0 | N3: =IF(K3>TODAY(),"",SUMIFS('OPs Data'!$N:$N,'OPs Data'!$F:$F,'Category & Range Wise Outward'!M$1,'OPs Data'!$D:$D,'Category & Range Wise Outward'!$A3,'OPs Data'!$L:$L,'Category & Range Wise Outward'!N$2)) -> 0 | O3: =IF(K3>TODAY(),"",SUMIFS('OPs Data'!$N:$N,'OPs Data'!$F:$F,'Category & Range Wise Outward'!M$1,'OPs Data'!$D:$D,'Category & Range Wise Outward'!$A3,'OPs Data'!$L:$L,'Category & Range Wise Outward'!O$2)) -> 0 | P3: =IF($A3>TODAY(),"",SUM(D3,G3,J3,M3)) -> 1100 | Q3: =IF($A3>TODAY(),"",SUM(E3,H3,K3,N3)) -> 0 | R3: =IF($A3>TODAY(),"",SUM(F3,I3,L3,O3)) -> 3
A4: 45735 | B4: {=IF(A4>TODAY(),"",COUNTA(_xlfn.UNIQUE(_xlfn._xlws.FILTER('OPs Data'!$K:$K,'OPs Data'!$D:$D='Category & Range Wise Outward'!A4))))} -> 3 | C4: =IF(A4>TODAY(),"",SUMIF('OPs Data'!$D:$D,'Category & Range Wise Outward'!$A4,'OPs Data'!O:O)/1000) -> 18.6 | D4: =IF(A4>TODAY(),"",SUMIFS('OPs Data'!$N:$N,'OPs Data'!$F:$F,'Category & Range Wise Outward'!D$1,'OPs Data'!$D:$D,'Category & Range Wise Outward'!$A4,'OPs Data'!$L:$L,'Category & Range Wise Outward'!D$2)) -> 0 | E4: =IF(A4>TODAY(),"",SUMIFS('OPs Data'!$N:$N,'OPs Data'!$F:$F,'Category & Range Wise Outward'!D$1,'OPs Data'!$D:$D,'Category & Range Wise Outward'!$A4,'OPs Data'!$L:$L,'Category & Range Wise Outward'!E$2)) -> 0 | F4: =IF(A4>TODAY(),"",SUMIFS('OPs Data'!$N:$N,'OPs Data'!$F:$F,'Category & Range Wise Outward'!D$1,'OPs Data'!$D:$D,'Category & Range Wise Outward'!$A4,'OPs Data'!$L:$L,'Category & Range Wise Outward'!F$2)) -> 60 | G4: =IF(E4>TODAY(),"",SUMIFS('OPs Data'!$N:$N,'OPs Data'!$F:$F,'Category & Range Wise Outward'!G$1,'OPs Data'!$D:$D,'Category & Range Wise Outward'!$A4,'OPs Data'!$L:$L,'Category & Range Wise Outward'!G$2)) -> 300 | H4: =IF(E4>TODAY(),"",SUMIFS('OPs Data'!$N:$N,'OPs Data'!$F:$F,'Category & Range Wise Outward'!G$1,'OPs Data'!$D:$D,'Category & Range Wise Outward'!$A4,'OPs Data'!$L:$L,'Category & Range Wise Outward'!H$2)) -> 0 | I4: =IF(E4>TODAY(),"",SUMIFS('OPs Data'!$N:$N,'OPs Data'!$F:$F,'Category & Range Wise Outward'!G$1,'OPs Data'!$D:$D,'Category & Range Wise Outward'!$A4,'OPs Data'!$L:$L,'Category & Range Wise Outward'!I$2)) -> 0 | J4: =IF(H4>TODAY(),"",SUMIFS('OPs Data'!$N:$N,'OPs Data'!$F:$F,'Category & Range Wise Outward'!J$1,'OPs Data'!$D:$D,'Category & Range Wise Outward'!$A4,'OPs Data'!$L:$L,'Category & Range Wise Outward'!J$2)) -> 0 | K4: =IF(H4>TODAY(),"",SUMIFS('OPs Data'!$N:$N,'OPs Data'!$F:$F,'Category & Range Wise Outward'!J$1,'OPs Data'!$D:$D,'Category & Range Wise Outward'!$A4,'OPs Data'!$L:$L,'Category & Range Wise Outward'!K$2)) -> 0 | L4: =IF(H4>TODAY(),"",SUMIFS('OPs Data'!$N:$N,'OPs Data'!$F:$F,'Category & Range Wise Outward'!J$1,'OPs Data'!$D:$D,'Category & Range Wise Outward'!$A4,'OPs Data'!$L:$L,'Category & Range Wise Outward'!L$2)) -> 0 | M4: =IF(K4>TODAY(),"",SUMIFS('OPs Data'!$N:$N,'OPs Data'!$F:$F,'Category & Range Wise Outward'!M$1,'OPs Data'!$D:$D,'Category & Range Wise Outward'!$A4,'OPs Data'!$L:$L,'Category & Range Wise Outward'!M$2)) -> 0 | N4: =IF(K4>TODAY(),"",SUMIFS('OPs Data'!$N:$N,'OPs Data'!$F:$F,'Category & Range Wise Outward'!M$1,'OPs Data'!$D:$D,'Category & Range Wise Outward'!$A4,'OPs Data'!$L:$L,'Category & Range Wise Outward'!N$2)) -> 0 | O4: =IF(K4>TODAY(),"",SUMIFS('OPs Data'!$N:$N,'OPs Data'!$F:$F,'Category & Range Wise Outward'!M$1,'OPs Data'!$D:$D,'Category & Range Wise Outward'!$A4,'OPs Data'!$L:$L,'Category & Range Wise Outward'!O$2)) -> 0 | P4: =IF($A4>TODAY(),"",SUM(D4,G4,J4,M4)) -> 300 | Q4: =IF($A4>TODAY(),"",SUM(E4,H4,K4,N4)) -> 0 | R4: =IF($A4>TODAY(),"",SUM(F4,I4,L4,O4)) -> 60
A5: 45736 | B5: {=IF(A5>TODAY(),"",COUNTA(_xlfn.UNIQUE(_xlfn._xlws.FILTER('OPs Data'!$K:$K,'OPs Data'!$D:$D='Category & Range Wise Outward'!A5))))} -> 3 | C5: =IF(A5>TODAY(),"",SUMIF('OPs Data'!$D:$D,'Category & Range Wise Outward'!$A5,'OPs Data'!O:O)/1000) -> 10 | D5: =IF(A5>TODAY(),"",SUMIFS('OPs Data'!$N:$N,'OPs Data'!$F:$F,'Category & Range Wise Outward'!D$1,'OPs Data'!$D:$D,'Category & Range Wise Outward'!$A5,'OPs Data'!$L:$L,'Category & Range Wise Outward'!D$2)) -> 400 | E5: =IF(A5>TODAY(),"",SUMIFS('OPs Data'!$N:$N,'OPs Data'!$F:$F,'Category & Range Wise Outward'!D$1,'OPs Data'!$D:$D,'Category & Range Wise Outward'!$A5,'OPs Data'!$L:$L,'Category & Range Wise Outward'!E$2)) -> 0 | F5: =IF(A5>TODAY(),"",SUMIFS('OPs Data'!$N:$N,'OPs Data'!$F:$F,'Category & Range Wise Outward'!D$1,'OPs Data'!$D:$D,'Category & Range Wise Outward'!$A5,'OPs Data'!$L:$L,'Category & Range Wise Outward'!F$2)) -> 0 | G5: =IF(E5>TODAY(),"",SUMIFS('OPs Data'!$N:$N,'OPs Data'!$F:$F,'Category & Range Wise Outward'!G$1,'OPs Data'!$D:$D,'Category & Range Wise Outward'!$A5,'OPs Data'!$L:$L,'Category & Range Wise Outward'!G$2)) -> 100 | H5: =IF(E5>TODAY(),"",SUMIFS('OPs Data'!$N:$N,'OPs Data'!$F:$F,'Category & Range Wise Outward'!G$1,'OPs Data'!$D:$D,'Category & Range Wise Outward'!$A5,'OPs Data'!$L:$L,'Category & Range Wise Outward'!H$2)) -> 0 | I5: =IF(E5>TODAY(),"",SUMIFS('OPs Data'!$N:$N,'OPs Data'!$F:$F,'Category & Range Wise Outward'!G$1,'OPs Data'!$D:$D,'Category & Range Wise Outward'!$A5,'OPs Data'!$L:$L,'Category & Range Wise Outward'!I$2)) -> 0 | J5: =IF(H5>TODAY(),"",SUMIFS('OPs Data'!$N:$N,'OPs Data'!$F:$F,'Category & Range Wise Outward'!J$1,'OPs Data'!$D:$D,'Category & Range Wise Outward'!$A5,'OPs Data'!$L:$L,'Category & Range Wise Outward'!J$2)) -> 0 | K5: =IF(H5>TODAY(),"",SUMIFS('OPs Data'!$N:$N,'OPs Data'!$F:$F,'Category & Range Wise Outward'!J$1,'OPs Data'!$D:$D,'Category & Range Wise Outward'!$A5,'OPs Data'!$L:$L,'Category & Range Wise Outward'!K$2)) -> 0 | L5: =IF(H5>TODAY(),"",SUMIFS('OPs Data'!$N:$N,'OPs Data'!$F:$F,'Category & Range Wise Outward'!J$1,'OPs Data'!$D:$D,'Category & Range Wise Outward'!$A5,'OPs Data'!$L:$L,'Category & Range Wise Outward'!L$2)) -> 0 | M5: =IF(K5>TODAY(),"",SUMIFS('OPs Data'!$N:$N,'OPs Data'!$F:$F,'Category & Range Wise Outward'!M$1,'OPs Data'!$D:$D,'Category & Range Wise Outward'!$A5,'OPs Data'!$L:$L,'Category & Range Wise Outward'!M$2)) -> 0 | N5: =IF(K5>TODAY(),"",SUMIFS('OPs Data'!$N:$N,'OPs Data'!$F:$F,'Category & Range Wise Outward'!M$1,'OPs Data'!$D:$D,'Category & Range Wise Outward'!$A5,'OPs Data'!$L:$L,'Category & Range Wise Outward'!N$2)) -> 0 | O5: =IF(K5>TODAY(),"",SUMIFS('OPs Data'!$N:$N,'OPs Data'!$F:$F,'Category & Range Wise Outward'!M$1,'OPs Data'!$D:$D,'Category & Range Wise Outward'!$A5,'OPs Data'!$L:$L,'Category & Range Wise Outward'!O$2)) -> 0 | P5: =IF($A5>TODAY(),"",SUM(D5,G5,J5,M5)) -> 500 | Q5: =IF($A5>TODAY(),"",SUM(E5,H5,K5,N5)) -> 0 | R5: =IF($A5>TODAY(),"",SUM(F5,I5,L5,O5)) -> 0
A6: 45737 | B6: {=IF(A6>TODAY(),"",COUNTA(_xlfn.UNIQUE(_xlfn._xlws.FILTER('OPs Data'!$K:$K,'OPs Data'!$D:$D='Category & Range Wise Outward'!A6))))} -> 4 | C6: =IF(A6>TODAY(),"",SUMIF('OPs Data'!$D:$D,'Category & Range Wise Outward'!$A6,'OPs Data'!O:O)/1000) -> 24.3 | D6: =IF(A6>TODAY(),"",SUMIFS('OPs Data'!$N:$N,'OPs Data'!$F:$F,'Category & Range Wise Outward'!D$1,'OPs Data'!$D:$D,'Category & Range Wise Outward'!$A6,'OPs Data'!$L:$L,'Category & Range Wise Outward'!D$2)) -> 300 | E6: =IF(A6>TODAY(),"",SUMIFS('OPs Data'!$N:$N,'OPs Data'!$F:$F,'Category & Range Wise Outward'!D$1,'OPs Data'!$D:$D,'Category & Range Wise Outward'!$A6,'OPs Data'!$L:$L,'Category & Range Wise Outward'!E$2)) -> 0 | F6: =IF(A6>TODAY(),"",SUMIFS('OPs Data'!$N:$N,'OPs Data'!$F:$F,'Category & Range Wise Outward'!D$1,'OPs Data'!$D:$D,'Category & Range Wise Outward'!$A6,'OPs Data'!$L:$L,'Category & Range Wise Outward'!F$2)) -> 30 | G6: =IF(E6>TODAY(),"",SUMIFS('OPs Data'!$N:$N,'OPs Data'!$F:$F,'Category & Range Wise Outward'!G$1,'OPs Data'!$D:$D,'Category & Range Wise Outward'!$A6,'OPs Data'!$L:$L,'Category & Range Wise Outward'!G$2)) -> 300 | H6: =IF(E6>TODAY(),"",SUMIFS('OPs Data'!$N:$N,'OPs Data'!$F:$F,'Category & Range Wise Outward'!G$1,'OPs Data'!$D:$D,'Category & Range Wise Outward'!$A6,'OPs Data'!$L:$L,'Category & Range Wise Outward'!H$2)) -> 0 | I6: =IF(E6>TODAY(),"",SUMIFS('OPs Data'!$N:$N,'OPs Data'!$F:$F,'Category & Range Wise Outward'!G$1,'OPs Data'!$D:$D,'Category & Range Wise Outward'!$A6,'OPs Data'!$L:$L,'Category & Range Wise Outward'!I$2)) -> 0 | J6: =IF(H6>TODAY(),"",SUMIFS('OPs Data'!$N:$N,'OPs Data'!$F:$F,'Category & Range Wise Outward'!J$1,'OPs Data'!$D:$D,'Category & Range Wise Outward'!$A6,'OPs Data'!$L:$L,'Category & Range Wise Outward'!J$2)) -> 300 | K6: =IF(H6>TODAY(),"",SUMIFS('OPs Data'!$N:$N,'OPs Data'!$F:$F,'Category & Range Wise Outward'!J$1,'OPs Data'!$D:$D,'Category & Range Wise Outward'!$A6,'OPs Data'!$L:$L,'Category & Range Wise Outward'!K$2)) -> 0 | L6: =IF(H6>TODAY(),"",SUMIFS('OPs Data'!$N:$N,'OPs Data'!$F:$F,'Category & Range Wise Outward'!J$1,'OPs Data'!$D:$D,'Category & Range Wise Outward'!$A6,'OPs Data'!$L:$L,'Category & Range Wise Outward'!L$2)) -> 0 | M6: =IF(K6>TODAY(),"",SUMIFS('OPs Data'!$N:$N,'OPs Data'!$F:$F,'Category & Range Wise Outward'!M$1,'OPs Data'!$D:$D,'Category & Range Wise Outward'!$A6,'OPs Data'!$L:$L,'Category & Range Wise Outward'!M$2)) -> 0 | N6: =IF(K6>TODAY(),"",SUMIFS('OPs Data'!$N:$N,'OPs Data'!$F:$F,'Category & Range Wise Outward'!M$1,'OPs Data'!$D:$D,'Category & Range Wise Outward'!$A6,'OPs Data'!$L:$L,'Category & Range Wise Outward'!N$2)) -> 0 | O6: =IF(K6>TODAY(),"",SUMIFS('OPs Data'!$N:$N,'OPs Data'!$F:$F,'Category & Range Wise Outward'!M$1,'OPs Data'!$D:$D,'Category & Range Wise Outward'!$A6,'OPs Data'!$L:$L,'Category & Range Wise Outward'!O$2)) -> 0 | P6: =IF($A6>TODAY(),"",SUM(D6,G6,J6,M6)) -> 900 | Q6: =IF($A6>TODAY(),"",SUM(E6,H6,K6,N6)) -> 0 | R6: =IF($A6>TODAY(),"",SUM(F6,I6,L6,O6)) -> 30
A7: 45738 | B7: {=IF(A7>TODAY(),"",COUNTA(_xlfn.UNIQUE(_xlfn._xlws.FILTER('OPs Data'!$K:$K,'OPs Data'!$D:$D='Category & Range Wise Outward'!A7))))} -> 2 | C7: =IF(A7>TODAY(),"",SUMIF('OPs Data'!$D:$D,'Category & Range Wise Outward'!$A7,'OPs Data'!O:O)/1000) -> 10 | D7: =IF(A7>TODAY(),"",SUMIFS('OPs Data'!$N:$N,'OPs Data'!$F:$F,'Category & Range Wise Outward'!D$1,'OPs Data'!$D:$D,'Category & Range Wise Outward'!$A7,'OPs Data'!$L:$L,'Category & Range Wise Outward'!D$2)) -> 500 | E7: =IF(A7>TODAY(),"",SUMIFS('OPs Data'!$N:$N,'OPs Data'!$F:$F,'Category & Range Wise Outward'!D$1,'OPs Data'!$D:$D,'Category & Range Wise Outward'!$A7,'OPs Data'!$L:$L,'Category & Range Wise Outward'!E$2)) -> 0 | F7: =IF(A7>TODAY(),"",SUMIFS('OPs Data'!$N:$N,'OPs Data'!$F:$F,'Category & Range Wise Outward'!D$1,'OPs Data'!$D:$D,'Category & Range Wise Outward'!$A7,'OPs Data'!$L:$L,'Category & Range Wise Outward'!F$2)) -> 0 | G7: =IF(E7>TODAY(),"",SUMIFS('OPs Data'!$N:$N,'OPs Data'!$F:$F,'Category & Range Wise Outward'!G$1,'OPs Data'!$D:$D,'Category & Range Wise Outward'!$A7,'OPs Data'!$L:$L,'Category & Range Wise Outward'!G$2)) -> 0 | H7: =IF(E7>TODAY(),"",SUMIFS('OPs Data'!$N:$N,'OPs Data'!$F:$F,'Category & Range Wise Outward'!G$1,'OPs Data'!$D:$D,'Category & Range Wise Outward'!$A7,'OPs Data'!$L:$L,'Category & Range Wise Outward'!H$2)) -> 0 | I7: =IF(E7>TODAY(),"",SUMIFS('OPs Data'!$N:$N,'OPs Data'!$F:$F,'Category & Range Wise Outward'!G$1,'OPs Data'!$D:$D,'Category & Range Wise Outward'!$A7,'OPs Data'!$L:$L,'Category & Range Wise Outward'!I$2)) -> 0 | J7: =IF(H7>TODAY(),"",SUMIFS('OPs Data'!$N:$N,'OPs Data'!$F:$F,'Category & Range Wise Outward'!J$1,'OPs Data'!$D:$D,'Category & Range Wise Outward'!$A7,'OPs Data'!$L:$L,'Category & Range Wise Outward'!J$2)) -> 0 | K7: =IF(H7>TODAY(),"",SUMIFS('OPs Data'!$N:$N,'OPs Data'!$F:$F,'Category & Range Wise Outward'!J$1,'OPs Data'!$D:$D,'Category & Range Wise Outward'!$A7,'OPs Data'!$L:$L,'Category & Range Wise Outward'!K$2)) -> 0 | L7: =IF(H7>TODAY(),"",SUMIFS('OPs Data'!$N:$N,'OPs Data'!$F:$F,'Category & Range Wise Outward'!J$1,'OPs Data'!$D:$D,'Category & Range Wise Outward'!$A7,'OPs Data'!$L:$L,'Category & Range Wise Outward'!L$2)) -> 0 | M7: =IF(K7>TODAY(),"",SUMIFS('OPs Data'!$N:$N,'OPs Data'!$F:$F,'Category & Range Wise Outward'!M$1,'OPs Data'!$D:$D,'Category & Range Wise Outward'!$A7,'OPs Data'!$L:$L,'Category & Range Wise Outward'!M$2)) -> 0 | N7: =IF(K7>TODAY(),"",SUMIFS('OPs Data'!$N:$N,'OPs Data'!$F:$F,'Category & Range Wise Outward'!M$1,'OPs Data'!$D:$D,'Category & Range Wise Outward'!$A7,'OPs Data'!$L:$L,'Category & Range Wise Outward'!N$2)) -> 0 | O7: =IF(K7>TODAY(),"",SUMIFS('OPs Data'!$N:$N,'OPs Data'!$F:$F,'Category & Range Wise Outward'!M$1,'OPs Data'!$D:$D,'Category & Range Wise Outward'!$A7,'OPs Data'!$L:$L,'Category & Range Wise Outward'!O$2)) -> 0 | P7: =IF($A7>TODAY(),"",SUM(D7,G7,J7,M7)) -> 500 | Q7: =IF($A7>TODAY(),"",SUM(E7,H7,K7,N7)) -> 0 | R7: =IF($A7>TODAY(),"",SUM(F7,I7,L7,O7)) -> 0
A8: 45739 | B8: {=IF(A8>TODAY(),"",COUNTA(_xlfn.UNIQUE(_xlfn._xlws.FILTER('OPs Data'!$K:$K,'OPs Data'!$D:$D='Category & Range Wise Outward'!A8))))} -> 1 | C8: =IF(A8>TODAY(),"",SUMIF('OPs Data'!$D:$D,'Category & Range Wise Outward'!$A8,'OPs Data'!O:O)/1000) -> 0 | D8: =IF(A8>TODAY(),"",SUMIFS('OPs Data'!$N:$N,'OPs Data'!$F:$F,'Category & Range Wise Outward'!D$1,'OPs Data'!$D:$D,'Category & Range Wise Outward'!$A8,'OPs Data'!$L:$L,'Category & Range Wise Outward'!D$2)) -> 0 | E8: =IF(A8>TODAY(),"",SUMIFS('OPs Data'!$N:$N,'OPs Data'!$F:$F,'Category & Range Wise Outward'!D$1,'OPs Data'!$D:$D,'Category & Range Wise Outward'!$A8,'OPs Data'!$L:$L,'Category & Range Wise Outward'!E$2)) -> 0 | F8: =IF(A8>TODAY(),"",SUMIFS('OPs Data'!$N:$N,'OPs Data'!$F:$F,'Category & Range Wise Outward'!D$1,'OPs Data'!$D:$D,'Category & Range Wise Outward'!$A8,'OPs Data'!$L:$L,'Category & Range Wise Outward'!F$2)) -> 0 | G8: =IF(E8>TODAY(),"",SUMIFS('OPs Data'!$N:$N,'OPs Data'!$F:$F,'Category & Range Wise Outward'!G$1,'OPs Data'!$D:$D,'Category & Range Wise Outward'!$A8,'OPs Data'!$L:$L,'Category & Range Wise Outward'!G$2)) -> 0 | H8: =IF(E8>TODAY(),"",SUMIFS('OPs Data'!$N:$N,'OPs Data'!$F:$F,'Category & Range Wise Outward'!G$1,'OPs Data'!$D:$D,'Category & Range Wise Outward'!$A8,'OPs Data'!$L:$L,'Category & Range Wise Outward'!H$2)) -> 0 | I8: =IF(E8>TODAY(),"",SUMIFS('OPs Data'!$N:$N,'OPs Data'!$F:$F,'Category & Range Wise Outward'!G$1,'OPs Data'!$D:$D,'Category & Range Wise Outward'!$A8,'OPs Data'!$L:$L,'Category & Range Wise Outward'!I$2)) -> 0 | J8: =IF(H8>TODAY(),"",SUMIFS('OPs Data'!$N:$N,'OPs Data'!$F:$F,'Category & Range Wise Outward'!J$1,'OPs Data'!$D:$D,'Category & Range Wise Outward'!$A8,'OPs Data'!$L:$L,'Category & Range Wise Outward'!J$2)) -> 0 | K8: =IF(H8>TODAY(),"",SUMIFS('OPs Data'!$N:$N,'OPs Data'!$F:$F,'Category & Range Wise Outward'!J$1,'OPs Data'!$D:$D,'Category & Range Wise Outward'!$A8,'OPs Data'!$L:$L,'Category & Range Wise Outward'!K$2)) -> 0 | L8: =IF(H8>TODAY(),"",SUMIFS('OPs Data'!$N:$N,'OPs Data'!$F:$F,'Category & Range Wise Outward'!J$1,'OPs Data'!$D:$D,'Category & Range Wise Outward'!$A8,'OPs Data'!$L:$L,'Category & Range Wise Outward'!L$2)) -> 0 | M8: =IF(K8>TODAY(),"",SUMIFS('OPs Data'!$N:$N,'OPs Data'!$F:$F,'Category & Range Wise Outward'!M$1,'OPs Data'!$D:$D,'Category & Range Wise Outward'!$A8,'OPs Data'!$L:$L,'Category & Range Wise Outward'!M$2)) -> 0 | N8: =IF(K8>TODAY(),"",SUMIFS('OPs Data'!$N:$N,'OPs Data'!$F:$F,'Category & Range Wise Outward'!M$1,'OPs Data'!$D:$D,'Category & Range Wise Outward'!$A8,'OPs Data'!$L:$L,'Category & Range Wise Outward'!N$2)) -> 0 | O8: =IF(K8>TODAY(),"",SUMIFS('OPs Data'!$N:$N,'OPs Data'!$F:$F,'Category & Range Wise Outward'!M$1,'OPs Data'!$D:$D,'Category & Range Wise Outward'!$A8,'OPs Data'!$L:$L,'Category & Range Wise Outward'!O$2)) -> 0 | P8: =IF($A8>TODAY(),"",SUM(D8,G8,J8,M8)) -> 0 | Q8: =IF($A8>TODAY(),"",SUM(E8,H8,K8,N8)) -> 0 | R8: =IF($A8>TODAY(),"",SUM(F8,I8,L8,O8)) -> 0
A9: 45740 | B9: {=IF(A9>TODAY(),"",COUNTA(_xlfn.UNIQUE(_xlfn._xlws.FILTER('OPs Data'!$K:$K,'OPs Data'!$D:$D='Category & Range Wise Outward'!A9))))} -> 3 | C9: =IF(A9>TODAY(),"",SUMIF('OPs Data'!$D:$D,'Category & Range Wise Outward'!$A9,'OPs Data'!O:O)/1000) -> 18.3 | D9: =IF(A9>TODAY(),"",SUMIFS('OPs Data'!$N:$N,'OPs Data'!$F:$F,'Category & Range Wise Outward'!D$1,'OPs Data'!$D:$D,'Category & Range Wise Outward'!$A9,'OPs Data'!$L:$L,'Category & Range Wise Outward'!D$2)) -> 300 | E9: =IF(A9>TODAY(),"",SUMIFS('OPs Data'!$N:$N,'OPs Data'!$F:$F,'Category & Range Wise Outward'!D$1,'OPs Data'!$D:$D,'Category & Range Wise Outward'!$A9,'OPs Data'!$L:$L,'Category & Range Wise Outward'!E$2)) -> 0 | F9: =IF(A9>TODAY(),"",SUMIFS('OPs Data'!$N:$N,'OPs Data'!$F:$F,'Category & Range Wise Outward'!D$1,'OPs Data'!$D:$D,'Category & Range Wise Outward'!$A9,'OPs Data'!$L:$L,'Category & Range Wise Outward'!F$2)) -> 0 | G9: =IF(E9>TODAY(),"",SUMIFS('OPs Data'!$N:$N,'OPs Data'!$F:$F,'Category & Range Wise Outward'!G$1,'OPs Data'!$D:$D,'Category & Range Wise Outward'!$A9,'OPs Data'!$L:$L,'Category & Range Wise Outward'!G$2)) -> 300 | H9: =IF(E9>TODAY(),"",SUMIFS('OPs Data'!$N:$N,'OPs Data'!$F:$F,'Category & Range Wise Outward'!G$1,'OPs Data'!$D:$D,'Category & Range Wise Outward'!$A9,'OPs Data'!$L:$L,'Category & Range Wise Outward'!H$2)) -> 0 | I9: =IF(E9>TODAY(),"",SUMIFS('OPs Data'!$N:$N,'OPs Data'!$F:$F,'Category & Range Wise Outward'!G$1,'OPs Data'!$D:$D,'Category & Range Wise Outward'!$A9,'OPs Data'!$L:$L,'Category & Range Wise Outward'!I$2)) -> 30 | J9: =IF(H9>TODAY(),"",SUMIFS('OPs Data'!$N:$N,'OPs Data'!$F:$F,'Category & Range Wise Outward'!J$1,'OPs Data'!$D:$D,'Category & Range Wise Outward'!$A9,'OPs Data'!$L:$L,'Category & Range Wise Outward'!J$2)) -> 0 | K9: =IF(H9>TODAY(),"",SUMIFS('OPs Data'!$N:$N,'OPs Data'!$F:$F,'Category & Range Wise Outward'!J$1,'OPs Data'!$D:$D,'Category & Range Wise Outward'!$A9,'OPs Data'!$L:$L,'Category & Range Wise Outward'!K$2)) -> 0 | L9: =IF(H9>TODAY(),"",SUMIFS('OPs Data'!$N:$N,'OPs Data'!$F:$F,'Category & Range Wise Outward'!J$1,'OPs Data'!$D:$D,'Category & Range Wise Outward'!$A9,'OPs Data'!$L:$L,'Category & Range Wise Outward'!L$2)) -> 0 | M9: =IF(K9>TODAY(),"",SUMIFS('OPs Data'!$N:$N,'OPs Data'!$F:$F,'Category & Range Wise Outward'!M$1,'OPs Data'!$D:$D,'Category & Range Wise Outward'!$A9,'OPs Data'!$L:$L,'Category & Range Wise Outward'!M$2)) -> 0 | N9: =IF(K9>TODAY(),"",SUMIFS('OPs Data'!$N:$N,'OPs Data'!$F:$F,'Category & Range Wise Outward'!M$1,'OPs Data'!$D:$D,'Category & Range Wise Outward'!$A9,'OPs Data'!$L:$L,'Category & Range Wise Outward'!N$2)) -> 0 | O9: =IF(K9>TODAY(),"",SUMIFS('OPs Data'!$N:$N,'OPs Data'!$F:$F,'Category & Range Wise Outward'!M$1,'OPs Data'!$D:$D,'Category & Range Wise Outward'!$A9,'OPs Data'!$L:$L,'Category & Range Wise Outward'!O$2)) -> 0 | P9: =IF($A9>TODAY(),"",SUM(D9,G9,J9,M9)) -> 600 | Q9: =IF($A9>TODAY(),"",SUM(E9,H9,K9,N9)) -> 0 | R9: =IF($A9>TODAY(),"",SUM(F9,I9,L9,O9)) -> 30
A10: 45741 | B10: {=IF(A10>TODAY(),"",COUNTA(_xlfn.UNIQUE(_xlfn._xlws.FILTER('OPs Data'!$K:$K,'OPs Data'!$D:$D='Category & Range Wise Outward'!A10))))} -> 4 | C10: =IF(A10>TODAY(),"",SUMIF('OPs Data'!$D:$D,'Category & Range Wise Outward'!$A10,'OPs Data'!O:O)/1000) -> 14 | D10: =IF(A10>TODAY(),"",SUMIFS('OPs Data'!$N:$N,'OPs Data'!$F:$F,'Category & Range Wise Outward'!D$1,'OPs Data'!$D:$D,'Category & Range Wise Outward'!$A10,'OPs Data'!$L:$L,'Category & Range Wise Outward'!D$2)) -> 500 | E10: =IF(A10>TODAY(),"",SUMIFS('OPs Data'!$N:$N,'OPs Data'!$F:$F,'Category & Range Wise Outward'!D$1,'OPs Data'!$D:$D,'Category & Range Wise Outward'!$A10,'OPs Data'!$L:$L,'Category & Range Wise Outward'!E$2)) -> 0 | F10: =IF(A10>TODAY(),"",SUMIFS('OPs Data'!$N:$N,'OPs Data'!$F:$F,'Category & Range Wise Outward'!D$1,'OPs Data'!$D:$D,'Category & Range Wise Outward'!$A10,'OPs Data'!$L:$L,'Category & Range Wise Outward'!F$2)) -> 0 | G10: =IF(E10>TODAY(),"",SUMIFS('OPs Data'!$N:$N,'OPs Data'!$F:$F,'Category & Range Wise Outward'!G$1,'OPs Data'!$D:$D,'Category & Range Wise Outward'!$A10,'OPs Data'!$L:$L,'Category & Range Wise Outward'!G$2)) -> 200 | H10: =IF(E10>TODAY(),"",SUMIFS('OPs Data'!$N:$N,'OPs Data'!$F:$F,'Category & Range Wise Outward'!G$1,'OPs Data'!$D:$D,'Category & Range Wise Outward'!$A10,'OPs Data'!$L:$L,'Category & Range Wise Outward'!H$2)) -> 0 | I10: =IF(E10>TODAY(),"",SUMIFS('OPs Data'!$N:$N,'OPs Data'!$F:$F,'Category & Range Wise Outward'!G$1,'OPs Data'!$D:$D,'Category & Range Wise Outward'!$A10,'OPs Data'!$L:$L,'Category & Range Wise Outward'!I$2)) -> 0 | J10: =IF(H10>TODAY(),"",SUMIFS('OPs Data'!$N:$N,'OPs Data'!$F:$F,'Category & Range Wise Outward'!J$1,'OPs Data'!$D:$D,'Category & Range Wise Outward'!$A10,'OPs Data'!$L:$L,'Category & Range Wise Outward'!J$2)) -> 0 | K10: =IF(H10>TODAY(),"",SUMIFS('OPs Data'!$N:$N,'OPs Data'!$F:$F,'Category & Range Wise Outward'!J$1,'OPs Data'!$D:$D,'Category & Range Wise Outward'!$A10,'OPs Data'!$L:$L,'Category & Range Wise Outward'!K$2)) -> 0 | L10: =IF(H10>TODAY(),"",SUMIFS('OPs Data'!$N:$N,'OPs Data'!$F:$F,'Category & Range Wise Outward'!J$1,'OPs Data'!$D:$D,'Category & Range Wise Outward'!$A10,'OPs Data'!$L:$L,'Category & Range Wise Outward'!L$2)) -> 0 | M10: =IF(K10>TODAY(),"",SUMIFS('OPs Data'!$N:$N,'OPs Data'!$F:$F,'Category & Range Wise Outward'!M$1,'OPs Data'!$D:$D,'Category & Range Wise Outward'!$A10,'OPs Data'!$L:$L,'Category & Range Wise Outward'!M$2)) -> 0 | N10: =IF(K10>TODAY(),"",SUMIFS('OPs Data'!$N:$N,'OPs Data'!$F:$F,'Category & Range Wise Outward'!M$1,'OPs Data'!$D:$D,'Category & Range Wise Outward'!$A10,'OPs Data'!$L:$L,'Category & Range Wise Outward'!N$2)) -> 0 | O10: =IF(K10>TODAY(),"",SUMIFS('OPs Data'!$N:$N,'OPs Data'!$F:$F,'Category & Range Wise Outward'!M$1,'OPs Data'!$D:$D,'Category & Range Wise Outward'!$A10,'OPs Data'!$L:$L,'Category & Range Wise Outward'!O$2)) -> 0 | P10: =IF($A10>TODAY(),"",SUM(D10,G10,J10,M10)) -> 700 | Q10: =IF($A10>TODAY(),"",SUM(E10,H10,K10,N10)) -> 0 | R10: =IF($A10>TODAY(),"",SUM(F10,I10,L10,O10)) -> 0
A11: 45742 | B11: {=IF(A11>TODAY(),"",COUNTA(_xlfn.UNIQUE(_xlfn._xlws.FILTER('OPs Data'!$K:$K,'OPs Data'!$D:$D='Category & Range Wise Outward'!A11))))} -> 5 | C11: =IF(A11>TODAY(),"",SUMIF('OPs Data'!$D:$D,'Category & Range Wise Outward'!$A11,'OPs Data'!O:O)/1000) -> 26 | D11: =IF(A11>TODAY(),"",SUMIFS('OPs Data'!$N:$N,'OPs Data'!$F:$F,'Category & Range Wise Outward'!D$1,'OPs Data'!$D:$D,'Category & Range Wise Outward'!$A11,'OPs Data'!$L:$L,'Category & Range Wise Outward'!D$2)) -> 900 | E11: =IF(A11>TODAY(),"",SUMIFS('OPs Data'!$N:$N,'OPs Data'!$F:$F,'Category & Range Wise Outward'!D$1,'OPs Data'!$D:$D,'Category & Range Wise Outward'!$A11,'OPs Data'!$L:$L,'Category & Range Wise Outward'!E$2)) -> 0 | F11: =IF(A11>TODAY(),"",SUMIFS('OPs Data'!$N:$N,'OPs Data'!$F:$F,'Category & Range Wise Outward'!D$1,'OPs Data'!$D:$D,'Category & Range Wise Outward'!$A11,'OPs Data'!$L:$L,'Category & Range Wise Outward'!F$2)) -> 0 | G11: =IF(E11>TODAY(),"",SUMIFS('OPs Data'!$N:$N,'OPs Data'!$F:$F,'Category & Range Wise Outward'!G$1,'OPs Data'!$D:$D,'Category & Range Wise Outward'!$A11,'OPs Data'!$L:$L,'Category & Range Wise Outward'!G$2)) -> 400 | H11: =IF(E11>TODAY(),"",SUMIFS('OPs Data'!$N:$N,'OPs Data'!$F:$F,'Category & Range Wise Outward'!G$1,'OPs Data'!$D:$D,'Category & Range Wise Outward'!$A11,'OPs Data'!$L:$L,'Category & Range Wise Outward'!H$2)) -> 0 | I11: =IF(E11>TODAY(),"",SUMIFS('OPs Data'!$N:$N,'OPs Data'!$F:$F,'Category & Range Wise Outward'!G$1,'OPs Data'!$D:$D,'Category & Range Wise Outward'!$A11,'OPs Data'!$L:$L,'Category & Range Wise Outward'!I$2)) -> 0 | J11: =IF(H11>TODAY(),"",SUMIFS('OPs Data'!$N:$N,'OPs Data'!$F:$F,'Category & Range Wise Outward'!J$1,'OPs Data'!$D:$D,'Category & Range Wise Outward'!$A11,'OPs Data'!$L:$L,'Category & Range Wise Outward'!J$2)) -> 0 | K11: =IF(H11>TODAY(),"",SUMIFS('OPs Data'!$N:$N,'OPs Data'!$F:$F,'Category & Range Wise Outward'!J$1,'OPs Data'!$D:$D,'Category & Range Wise Outward'!$A11,'OPs Data'!$L:$L,'Category & Range Wise Outward'!K$2)) -> 0 | L11: =IF(H11>TODAY(),"",SUMIFS('OPs Data'!$N:$N,'OPs Data'!$F:$F,'Category & Range Wise Outward'!J$1,'OPs Data'!$D:$D,'Category & Range Wise Outward'!$A11,'OPs Data'!$L:$L,'Category & Range Wise Outward'!L$2)) -> 0 | M11: =IF(K11>TODAY(),"",SUMIFS('OPs Data'!$N:$N,'OPs Data'!$F:$F,'Category & Range Wise Outward'!M$1,'OPs Data'!$D:$D,'Category & Range Wise Outward'!$A11,'OPs Data'!$L:$L,'Category & Range Wise Outward'!M$2)) -> 0 | N11: =IF(K11>TODAY(),"",SUMIFS('OPs Data'!$N:$N,'OPs Data'!$F:$F,'Category & Range Wise Outward'!M$1,'OPs Data'!$D:$D,'Category & Range Wise Outward'!$A11,'OPs Data'!$L:$L,'Category & Range Wise Outward'!N$2)) -> 0 | O11: =IF(K11>TODAY(),"",SUMIFS('OPs Data'!$N:$N,'OPs Data'!$F:$F,'Category & Range Wise Outward'!M$1,'OPs Data'!$D:$D,'Category & Range Wise Outward'!$A11,'OPs Data'!$L:$L,'Category & Range Wise Outward'!O$2)) -> 0 | P11: =IF($A11>TODAY(),"",SUM(D11,G11,J11,M11)) -> 1300 | Q11: =IF($A11>TODAY(),"",SUM(E11,H11,K11,N11)) -> 0 | R11: =IF($A11>TODAY(),"",SUM(F11,I11,L11,O11)) -> 0
A12: 45743 | B12: {=IF(A12>TODAY(),"",COUNTA(_xlfn.UNIQUE(_xlfn._xlws.FILTER('OPs Data'!$K:$K,'OPs Data'!$D:$D='Category & Range Wise Outward'!A12))))} -> 3 | C12: =IF(A12>TODAY(),"",SUMIF('OPs Data'!$D:$D,'Category & Range Wise Outward'!$A12,'OPs Data'!O:O)/1000) -> 18.3 | D12: =IF(A12>TODAY(),"",SUMIFS('OPs Data'!$N:$N,'OPs Data'!$F:$F,'Category & Range Wise Outward'!D$1,'OPs Data'!$D:$D,'Category & Range Wise Outward'!$A12,'OPs Data'!$L:$L,'Category & Range Wise Outward'!D$2)) -> 600 | E12: =IF(A12>TODAY(),"",SUMIFS('OPs Data'!$N:$N,'OPs Data'!$F:$F,'Category & Range Wise Outward'!D$1,'OPs Data'!$D:$D,'Category & Range Wise Outward'!$A12,'OPs Data'!$L:$L,'Category & Range Wise Outward'!E$2)) -> 0 | F12: =IF(A12>TODAY(),"",SUMIFS('OPs Data'!$N:$N,'OPs Data'!$F:$F,'Category & Range Wise Outward'!D$1,'OPs Data'!$D:$D,'Category & Range Wise Outward'!$A12,'OPs Data'!$L:$L,'Category & Range Wise Outward'!F$2)) -> 30 | G12: =IF(E12>TODAY(),"",SUMIFS('OPs Data'!$N:$N,'OPs Data'!$F:$F,'Category & Range Wise Outward'!G$1,'OPs Data'!$D:$D,'Category & Range Wise Outward'!$A12,'OPs Data'!$L:$L,'Category & Range Wise Outward'!G$2)) -> 0 | H12: =IF(E12>TODAY(),"",SUMIFS('OPs Data'!$N:$N,'OPs Data'!$F:$F,'Category & Range Wise Outward'!G$1,'OPs Data'!$D:$D,'Category & Range Wise Outward'!$A12,'OPs Data'!$L:$L,'Category & Range Wise Outward'!H$2)) -> 0 | I12: =IF(E12>TODAY(),"",SUMIFS('OPs Data'!$N:$N,'OPs Data'!$F:$F,'Category & Range Wise Outward'!G$1,'OPs Data'!$D:$D,'Category & Range Wise Outward'!$A12,'OPs Data'!$L:$L,'Category & Range Wise Outward'!I$2)) -> 0 | J12: =IF(H12>TODAY(),"",SUMIFS('OPs Data'!$N:$N,'OPs Data'!$F:$F,'Category & Range Wise Outward'!J$1,'OPs Data'!$D:$D,'Category & Range Wise Outward'!$A12,'OPs Data'!$L:$L,'Category & Range Wise Outward'!J$2)) -> 0 | K12: =IF(H12>TODAY(),"",SUMIFS('OPs Data'!$N:$N,'OPs Data'!$F:$F,'Category & Range Wise Outward'!J$1,'OPs Data'!$D:$D,'Category & Range Wise Outward'!$A12,'OPs Data'!$L:$L,'Category & Range Wise Outward'!K$2)) -> 0 | L12: =IF(H12>TODAY(),"",SUMIFS('OPs Data'!$N:$N,'OPs Data'!$F:$F,'Category & Range Wise Outward'!J$1,'OPs Data'!$D:$D,'Category & Range Wise Outward'!$A12,'OPs Data'!$L:$L,'Category & Range Wise Outward'!L$2)) -> 0 | M12: =IF(K12>TODAY(),"",SUMIFS('OPs Data'!$N:$N,'OPs Data'!$F:$F,'Category & Range Wise Outward'!M$1,'OPs Data'!$D:$D,'Category & Range Wise Outward'!$A12,'OPs Data'!$L:$L,'Category & Range Wise Outward'!M$2)) -> 0 | N12: =IF(K12>TODAY(),"",SUMIFS('OPs Data'!$N:$N,'OPs Data'!$F:$F,'Category & Range Wise Outward'!M$1,'OPs Data'!$D:$D,'Category & Range Wise Outward'!$A12,'OPs Data'!$L:$L,'Category & Range Wise Outward'!N$2)) -> 0 | O12: =IF(K12>TODAY(),"",SUMIFS('OPs Data'!$N:$N,'OPs Data'!$F:$F,'Category & Range Wise Outward'!M$1,'OPs Data'!$D:$D,'Category & Range Wise Outward'!$A12,'OPs Data'!$L:$L,'Category & Range Wise Outward'!O$2)) -> 0 | P12: =IF($A12>TODAY(),"",SUM(D12,G12,J12,M12)) -> 600 | Q12: =IF($A12>TODAY(),"",SUM(E12,H12,K12,N12)) -> 0 | R12: =IF($A12>TODAY(),"",SUM(F12,I12,L12,O12)) -> 30
A13: 45744 | B13: {=IF(A13>TODAY(),"",COUNTA(_xlfn.UNIQUE(_xlfn._xlws.FILTER('OPs Data'!$K:$K,'OPs Data'!$D:$D='Category & Range Wise Outward'!A13))))} -> 5 | C13: =IF(A13>TODAY(),"",SUMIF('OPs Data'!$D:$D,'Category & Range Wise Outward'!$A13,'OPs Data'!O:O)/1000) -> 24 | D13: =IF(A13>TODAY(),"",SUMIFS('OPs Data'!$N:$N,'OPs Data'!$F:$F,'Category & Range Wise Outward'!D$1,'OPs Data'!$D:$D,'Category & Range Wise Outward'!$A13,'OPs Data'!$L:$L,'Category & Range Wise Outward'!D$2)) -> 800 | E13: =IF(A13>TODAY(),"",SUMIFS('OPs Data'!$N:$N,'OPs Data'!$F:$F,'Category & Range Wise Outward'!D$1,'OPs Data'!$D:$D,'Category & Range Wise Outward'!$A13,'OPs Data'!$L:$L,'Category & Range Wise Outward'!E$2)) -> 0 | F13: =IF(A13>TODAY(),"",SUMIFS('OPs Data'!$N:$N,'OPs Data'!$F:$F,'Category & Range Wise Outward'!D$1,'OPs Data'!$D:$D,'Category & Range Wise Outward'!$A13,'OPs Data'!$L:$L,'Category & Range Wise Outward'!F$2)) -> 0 | G13: =IF(E13>TODAY(),"",SUMIFS('OPs Data'!$N:$N,'OPs Data'!$F:$F,'Category & Range Wise Outward'!G$1,'OPs Data'!$D:$D,'Category & Range Wise Outward'!$A13,'OPs Data'!$L:$L,'Category & Range Wise Outward'!G$2)) -> 400 | H13: =IF(E13>TODAY(),"",SUMIFS('OPs Data'!$N:$N,'OPs Data'!$F:$F,'Category & Range Wise Outward'!G$1,'OPs Data'!$D:$D,'Category & Range Wise Outward'!$A13,'OPs Data'!$L:$L,'Category & Range Wise Outward'!H$2)) -> 0 | I13: =IF(E13>TODAY(),"",SUMIFS('OPs Data'!$N:$N,'OPs Data'!$F:$F,'Category & Range Wise Outward'!G$1,'OPs Data'!$D:$D,'Category & Range Wise Outward'!$A13,'OPs Data'!$L:$L,'Category & Range Wise Outward'!I$2)) -> 0 | J13: =IF(H13>TODAY(),"",SUMIFS('OPs Data'!$N:$N,'OPs Data'!$F:$F,'Category & Range Wise Outward'!J$1,'OPs Data'!$D:$D,'Category & Range Wise Outward'!$A13,'OPs Data'!$L:$L,'Category & Range Wise Outward'!J$2)) -> 0 | K13: =IF(H13>TODAY(),"",SUMIFS('OPs Data'!$N:$N,'OPs Data'!$F:$F,'Category & Range Wise Outward'!J$1,'OPs Data'!$D:$D,'Category & Range Wise Outward'!$A13,'OPs Data'!$L:$L,'Category & Range Wise Outward'!K$2)) -> 0 | L13: =IF(H13>TODAY(),"",SUMIFS('OPs Data'!$N:$N,'OPs Data'!$F:$F,'Category & Range Wise Outward'!J$1,'OPs Data'!$D:$D,'Category & Range Wise Outward'!$A13,'OPs Data'!$L:$L,'Category & Range Wise Outward'!L$2)) -> 0 | M13: =IF(K13>TODAY(),"",SUMIFS('OPs Data'!$N:$N,'OPs Data'!$F:$F,'Category & Range Wise Outward'!M$1,'OPs Data'!$D:$D,'Category & Range Wise Outward'!$A13,'OPs Data'!$L:$L,'Category & Range Wise Outward'!M$2)) -> 0 | N13: =IF(K13>TODAY(),"",SUMIFS('OPs Data'!$N:$N,'OPs Data'!$F:$F,'Category & Range Wise Outward'!M$1,'OPs Data'!$D:$D,'Category & Range Wise Outward'!$A13,'OPs Data'!$L:$L,'Category & Range Wise Outward'!N$2)) -> 0 | O13: =IF(K13>TODAY(),"",SUMIFS('OPs Data'!$N:$N,'OPs Data'!$F:$F,'Category & Range Wise Outward'!M$1,'OPs Data'!$D:$D,'Category & Range Wise Outward'!$A13,'OPs Data'!$L:$L,'Category & Range Wise Outward'!O$2)) -> 0 | P13: =IF($A13>TODAY(),"",SUM(D13,G13,J13,M13)) -> 1200 | Q13: =IF($A13>TODAY(),"",SUM(E13,H13,K13,N13)) -> 0 | R13: =IF($A13>TODAY(),"",SUM(F13,I13,L13,O13)) -> 0
A14: 45745 | B14: {=IF(A14>TODAY(),"",COUNTA(_xlfn.UNIQUE(_xlfn._xlws.FILTER('OPs Data'!$K:$K,'OPs Data'!$D:$D='Category & Range Wise Outward'!A14))))} -> 4 | C14: =IF(A14>TODAY(),"",SUMIF('OPs Data'!$D:$D,'Category & Range Wise Outward'!$A14,'OPs Data'!O:O)/1000) -> 24 | D14: =IF(A14>TODAY(),"",SUMIFS('OPs Data'!$N:$N,'OPs Data'!$F:$F,'Category & Range Wise Outward'!D$1,'OPs Data'!$D:$D,'Category & Range Wise Outward'!$A14,'OPs Data'!$L:$L,'Category & Range Wise Outward'!D$2)) -> 900 | E14: =IF(A14>TODAY(),"",SUMIFS('OPs Data'!$N:$N,'OPs Data'!$F:$F,'Category & Range Wise Outward'!D$1,'OPs Data'!$D:$D,'Category & Range Wise Outward'!$A14,'OPs Data'!$L:$L,'Category & Range Wise Outward'!E$2)) -> 0 | F14: =IF(A14>TODAY(),"",SUMIFS('OPs Data'!$N:$N,'OPs Data'!$F:$F,'Category & Range Wise Outward'!D$1,'OPs Data'!$D:$D,'Category & Range Wise Outward'!$A14,'OPs Data'!$L:$L,'Category & Range Wise Outward'!F$2)) -> 0 | G14: =IF(E14>TODAY(),"",SUMIFS('OPs Data'!$N:$N,'OPs Data'!$F:$F,'Category & Range Wise Outward'!G$1,'OPs Data'!$D:$D,'Category & Range Wise Outward'!$A14,'OPs Data'!$L:$L,'Category & Range Wise Outward'!G$2)) -> 300 | H14: =IF(E14>TODAY(),"",SUMIFS('OPs Data'!$N:$N,'OPs Data'!$F:$F,'Category & Range Wise Outward'!G$1,'OPs Data'!$D:$D,'Category & Range Wise Outward'!$A14,'OPs Data'!$L:$L,'Category & Range Wise Outward'!H$2)) -> 0 | I14: =IF(E14>TODAY(),"",SUMIFS('OPs Data'!$N:$N,'OPs Data'!$F:$F,'Category & Range Wise Outward'!G$1,'OPs Data'!$D:$D,'Category & Range Wise Outward'!$A14,'OPs Data'!$L:$L,'Category & Range Wise Outward'!I$2)) -> 0 | J14: =IF(H14>TODAY(),"",SUMIFS('OPs Data'!$N:$N,'OPs Data'!$F:$F,'Category & Range Wise Outward'!J$1,'OPs Data'!$D:$D,'Category & Range Wise Outward'!$A14,'OPs Data'!$L:$L,'Category & Range Wise Outward'!J$2)) -> 0 | K14: =IF(H14>TODAY(),"",SUMIFS('OPs Data'!$N:$N,'OPs Data'!$F:$F,'Category & Range Wise Outward'!J$1,'OPs Data'!$D:$D,'Category & Range Wise Outward'!$A14,'OPs Data'!$L:$L,'Category & Range Wise Outward'!K$2)) -> 0 | L14: =IF(H14>TODAY(),"",SUMIFS('OPs Data'!$N:$N,'OPs Data'!$F:$F,'Category & Range Wise Outward'!J$1,'OPs Data'!$D:$D,'Category & Range Wise Outward'!$A14,'OPs Data'!$L:$L,'Category & Range Wise Outward'!L$2)) -> 0 | M14: =IF(K14>TODAY(),"",SUMIFS('OPs Data'!$N:$N,'OPs Data'!$F:$F,'Category & Range Wise Outward'!M$1,'OPs Data'!$D:$D,'Category & Range Wise Outward'!$A14,'OPs Data'!$L:$L,'Category & Range Wise Outward'!M$2)) -> 0 | N14: =IF(K14>TODAY(),"",SUMIFS('OPs Data'!$N:$N,'OPs Data'!$F:$F,'Category & Range Wise Outward'!M$1,'OPs Data'!$D:$D,'Category & Range Wise Outward'!$A14,'OPs Data'!$L:$L,'Category & Range Wise Outward'!N$2)) -> 0 | O14: =IF(K14>TODAY(),"",SUMIFS('OPs Data'!$N:$N,'OPs Data'!$F:$F,'Category & Range Wise Outward'!M$1,'OPs Data'!$D:$D,'Category & Range Wise Outward'!$A14,'OPs Data'!$L:$L,'Category & Range Wise Outward'!O$2)) -> 0 | P14: =IF($A14>TODAY(),"",SUM(D14,G14,J14,M14)) -> 1200 | Q14: =IF($A14>TODAY(),"",SUM(E14,H14,K14,N14)) -> 0 | R14: =IF($A14>TODAY(),"",SUM(F14,I14,L14,O14)) -> 0
... A77: 45808 | B77: {=IF(A77>TODAY(),"",COUNTA(_xlfn.UNIQUE(_xlfn._xlws.FILTER('OPs Data'!$K:$K,'OPs Data'!$D:$D='Category & Range Wise Outward'!A77))))} -> 7 | C77: =IF(A77>TODAY(),"",SUMIF('OPs Data'!$D:$D,'Category & Range Wise Outward'!$A77,'OPs Data'!O:O)/1000) -> 30.6 | D77: =IF(A77>TODAY(),"",SUMIFS('OPs Data'!$N:$N,'OPs Data'!$F:$F,'Category & Range Wise Outward'!D$1,'OPs Data'!$D:$D,'Category & Range Wise Outward'!$A77,'OPs Data'!$L:$L,'Category & Range Wise Outward'!D$2)) -> 0 | E77: =IF(A77>TODAY(),"",SUMIFS('OPs Data'!$N:$N,'OPs Data'!$F:$F,'Category & Range Wise Outward'!D$1,'OPs Data'!$D:$D,'Category & Range Wise Outward'!$A77,'OPs Data'!$L:$L,'Category & Range Wise Outward'!E$2)) -> 0 | F77: =IF(A77>TODAY(),"",SUMIFS('OPs Data'!$N:$N,'OPs Data'!$F:$F,'Category & Range Wise Outward'!D$1,'OPs Data'!$D:$D,'Category & Range Wise Outward'!$A77,'OPs Data'!$L:$L,'Category & Range Wise Outward'!F$2)) -> 60 | G77: =IF(E77>TODAY(),"",SUMIFS('OPs Data'!$N:$N,'OPs Data'!$F:$F,'Category & Range Wise Outward'!G$1,'OPs Data'!$D:$D,'Category & Range Wise Outward'!$A77,'OPs Data'!$L:$L,'Category & Range Wise Outward'!G$2)) -> 800 | H77: =IF(E77>TODAY(),"",SUMIFS('OPs Data'!$N:$N,'OPs Data'!$F:$F,'Category & Range Wise Outward'!G$1,'OPs Data'!$D:$D,'Category & Range Wise Outward'!$A77,'OPs Data'!$L:$L,'Category & Range Wise Outward'!H$2)) -> 0 | I77: =IF(E77>TODAY(),"",SUMIFS('OPs Data'!$N:$N,'OPs Data'!$F:$F,'Category & Range Wise Outward'!G$1,'OPs Data'!$D:$D,'Category & Range Wise Outward'!$A77,'OPs Data'!$L:$L,'Category & Range Wise Outward'!I$2)) -> 0 | J77: =IF(H77>TODAY(),"",SUMIFS('OPs Data'!$N:$N,'OPs Data'!$F:$F,'Category & Range Wise Outward'!J$1,'OPs Data'!$D:$D,'Category & Range Wise Outward'!$A77,'OPs Data'!$L:$L,'Category & Range Wise Outward'!J$2)) -> 100 | K77: =IF(H77>TODAY(),"",SUMIFS('OPs Data'!$N:$N,'OPs Data'!$F:$F,'Category & Range Wise Outward'!J$1,'OPs Data'!$D:$D,'Category & Range Wise Outward'!$A77,'OPs Data'!$L:$L,'Category & Range Wise Outward'!K$2)) -> 0 | L77: =IF(H77>TODAY(),"",SUMIFS('OPs Data'!$N:$N,'OPs Data'!$F:$F,'Category & Range Wise Outward'!J$1,'OPs Data'!$D:$D,'Category & Range Wise Outward'!$A77,'OPs Data'!$L:$L,'Category & Range Wise Outward'!L$2)) -> 0 | M77: =IF(K77>TODAY(),"",SUMIFS('OPs Data'!$N:$N,'OPs Data'!$F:$F,'Category & Range Wise Outward'!M$1,'OPs Data'!$D:$D,'Category & Range Wise Outward'!$A77,'OPs Data'!$L:$L,'Category & Range Wise Outward'!M$2)) -> 0 | N77: =IF(K77>TODAY(),"",SUMIFS('OPs Data'!$N:$N,'OPs Data'!$F:$F,'Category & Range Wise Outward'!M$1,'OPs Data'!$D:$D,'Category & Range Wise Outward'!$A77,'OPs Data'!$L:$L,'Category & Range Wise Outward'!N$2)) -> 0 | O77: =IF(K77>TODAY(),"",SUMIFS('OPs Data'!$N:$N,'OPs Data'!$F:$F,'Category & Range Wise Outward'!M$1,'OPs Data'!$D:$D,'Category & Range Wise Outward'!$A77,'OPs Data'!$L:$L,'Category & Range Wise Outward'!O$2)) -> 0 | P77: =IF($A77>TODAY(),"",SUM(D77,G77,J77,M77)) -> 900 | Q77: =IF($A77>TODAY(),"",SUM(E77,H77,K77,N77)) -> 0 | R77: =IF($A77>TODAY(),"",SUM(F77,I77,L77,O77)) -> 60

Sheet P&L
A1: Date | B1: Month | C1: Revenue | D1: Expense | E1: Cummlative Revenue | F1: Cummlative Expense | G1: Daily P&L | H1: P&L Till Date | K1: Expense | L1: Revenue | M1: P&L | N1: P&L %
A2: 45734 | B2: =TEXT(A2,"mmm-yy") -> Mar-25 | C2: =VLOOKUP(A2,'Revenue Sheet'!A:R,18,0) -> 29461.5 | D2: =VLOOKUP(A2,'Expense Sheet'!A:F,6,0) -> 30508.947 | E2: =C2 -> 29461.5 | F2: =D2 -> 30508.947 | G2: =IFERROR(C2-D2,"") -> -1047.4468 | H2: =IFERROR(E2-F2,"") -> -1047.4468 | J2: Yesterday's | K2: =VLOOKUP(TODAY()-1,A:D,4,0) -> #N/A | L2: =VLOOKUP(TODAY()-1,A:D,3,0) -> #N/A | M2: =L2-K2 -> #N/A | N2: =IFERROR(M2/L2,0) -> 0
A3: 45735 | B3: =TEXT(A3,"mmm-yy") -> Mar-25 | C3: =VLOOKUP(A3,'Revenue Sheet'!A:R,18,0) -> 25230 | D3: =VLOOKUP(A3,'Expense Sheet'!A:F,6,0) -> 27805.097 | E3: =IFERROR(C3+E2,"") -> 54691.5 | F3: =IFERROR(D3+F2,"") -> 58314.044 | G3: =IFERROR(C3-D3,"") -> -2575.0968 | H3: =IFERROR(E3-F3,"") -> -3622.5435 | J3: MTD | K3: =SUMIF(B:B,TEXT(TODAY(),"mmm-yy"),D:D) -> 0 | L3: =SUMIF(B:B,TEXT(TODAY(),"mmm-yy"),C:C) -> 0 | M3: =L3-K3 -> 0 | N3: =IFERROR(M3/L3,0) -> 0
A4: 45736 | B4: =TEXT(A4,"mmm-yy") -> Mar-25 | C4: =VLOOKUP(A4,'Revenue Sheet'!A:R,18,0) -> 12400 | D4: =VLOOKUP(A4,'Expense Sheet'!A:F,6,0) -> 21383.097 | E4: =IFERROR(C4+E3,"") -> 67091.5 | F4: =IFERROR(D4+F3,"") -> 79697.14 | G4: =IFERROR(C4-D4,"") -> -8983.0968 | H4: =IFERROR(E4-F4,"") -> -12605.64 | J4: Last Month | K4: =SUMIF(B:B,TEXT(EOMONTH(EDATE(TODAY(),-1),0),"mmm-yy"),D:D) -> 0 | L4: =SUMIF(B:B,TEXT(EOMONTH(EDATE(TODAY(),-1),0),"mmm-yy"),C:C) -> 0 | M4: =L4-K4 -> 0 | N4: =IFERROR(M4/L4,0) -> 0
A5: 45737 | B5: =TEXT(A5,"mmm-yy") -> Mar-25 | C5: =VLOOKUP(A5,'Revenue Sheet'!A:R,18,0) -> 45315 | D5: =VLOOKUP(A5,'Expense Sheet'!A:F,6,0) -> 44179.597 | E5: =IFERROR(C5+E4,"") -> 112406.5 | F5: =IFERROR(D5+F4,"") -> 123876.74 | G5: =IFERROR(C5-D5,"") -> 1135.4032 | H5: =IFERROR(E5-F5,"") -> -11470.237 | J5: YTD | K5: =SUM(D:D) -> 2110079.5 | L5: =SUM(C:C) -> 1917866.5 | M5: =L5-K5 -> -192212.95 | N5: =IFERROR(M5/L5,0) -> -0.10022228
A6: 45738 | B6: =TEXT(A6,"mmm-yy") -> Mar-25 | C6: =VLOOKUP(A6,'Revenue Sheet'!A:R,18,0) -> 10500 | D6: =VLOOKUP(A6,'Expense Sheet'!A:F,6,0) -> 15338.097 | E6: =IFERROR(C6+E5,"") -> 122906.5 | F6: =IFERROR(D6+F5,"") -> 139214.83 | G6: =IFERROR(C6-D6,"") -> -4838.0968 | H6: =IFERROR(E6-F6,"") -> -16308.334
A7: 45739 | B7: =TEXT(A7,"mmm-yy") -> Mar-25 | C7: =VLOOKUP(A7,'Revenue Sheet'!A:R,18,0) -> 0 | D7: =VLOOKUP(A7,'Expense Sheet'!A:F,6,0) -> 387.09677 | E7: =IFERROR(C7+E6,"") -> 122906.5 | F7: =IFERROR(D7+F6,"") -> 139601.93 | G7: =IFERROR(C7-D7,"") -> -387.09677 | H7: =IFERROR(E7-F7,"") -> -16695.431
A8: 45740 | B8: =TEXT(A8,"mmm-yy") -> Mar-25 | C8: =VLOOKUP(A8,'Revenue Sheet'!A:R,18,0) -> 30900 | D8: =VLOOKUP(A8,'Expense Sheet'!A:F,6,0) -> 33522.597 | E8: =IFERROR(C8+E7,"") -> 153806.5 | F8: =IFERROR(D8+F7,"") -> 173124.53 | G8: =IFERROR(C8-D8,"") -> -2622.5968 | H8: =IFERROR(E8-F8,"") -> -19318.027
A9: 45741 | B9: =TEXT(A9,"mmm-yy") -> Mar-25 | C9: =VLOOKUP(A9,'Revenue Sheet'!A:R,18,0) -> 18500 | D9: =VLOOKUP(A9,'Expense Sheet'!A:F,6,0) -> 20934.097 | E9: =IFERROR(C9+E8,"") -> 172306.5 | F9: =IFERROR(D9+F8,"") -> 194058.62 | G9: =IFERROR(C9-D9,"") -> -2434.0968 | H9: =IFERROR(E9-F9,"") -> -21752.124
A10: 45742 | B10: =TEXT(A10,"mmm-yy") -> Mar-25 | C10: =VLOOKUP(A10,'Revenue Sheet'!A:R,18,0) -> 34900 | D10: =VLOOKUP(A10,'Expense Sheet'!A:F,6,0) -> 37051.097 | E10: =IFERROR(C10+E9,"") -> 207206.5 | F10: =IFERROR(D10+F9,"") -> 231109.72 | G10: =IFERROR(C10-D10,"") -> -2151.0968 | H10: =IFERROR(E10-F10,"") -> -23903.221
A11: 45743 | B11: =TEXT(A11,"mmm-yy") -> Mar-25 | C11: =VLOOKUP(A11,'Revenue Sheet'!A:R,18,0) -> 19215 | D11: =VLOOKUP(A11,'Expense Sheet'!A:F,6,0) -> 18270.597 | E11: =IFERROR(C11+E10,"") -> 226421.5 | F11: =IFERROR(D11+F10,"") -> 249380.32 | G11: =IFERROR(C11-D11,"") -> 944.40323 | H11: =IFERROR(E11-F11,"") -> -22958.818
A12: 45744 | B12: =TEXT(A12,"mmm-yy") -> Mar-25 | C12: =VLOOKUP(A12,'Revenue Sheet'!A:R,18,0) -> 32800 | D12: =VLOOKUP(A12,'Expense Sheet'!A:F,6,0) -> 44130.097 | E12: =IFERROR(C12+E11,"") -> 259221.5 | F12: =IFERROR(D12+F11,"") -> 293510.41 | G12: =IFERROR(C12-D12,"") -> -11330.097 | H12: =IFERROR(E12-F12,"") -> -34288.915
A13: 45745 | B13: =TEXT(A13,"mmm-yy") -> Mar-25 | C13: =VLOOKUP(A13,'Revenue Sheet'!A:R,18,0) -> 30900 | D13: =VLOOKUP(A13,'Expense Sheet'!A:F,6,0) -> 34025.097 | E13: =IFERROR(C13+E12,"") -> 290121.5 | F13: =IFERROR(D13+F12,"") -> 327535.51 | G13: =IFERROR(C13-D13,"") -> -3125.0968 | H13: =IFERROR(E13-F13,"") -> -37414.011
A14: 45746 | B14: =TEXT(A14,"mmm-yy") -> Mar-25 | C14: =VLOOKUP(A14,'Revenue Sheet'!A:R,18,0) -> 23700 | D14: =VLOOKUP(A14,'Expense Sheet'!A:F,6,0) -> 27349.597 | E14: =IFERROR(C14+E13,"") -> 313821.5 | F14: =IFERROR(D14+F13,"") -> 354885.11 | G14: =IFERROR(C14-D14,"") -> -3649.5968 | H14: =IFERROR(E14-F14,"") -> -41063.608
A15: 45747 | B15: =TEXT(A15,"mmm-yy") -> Mar-25 | C15: =VLOOKUP(A15,'Revenue Sheet'!A:R,18,0) -> 20800 | D15: =VLOOKUP(A15,'Expense Sheet'!A:F,6,0) -> 28484.097 | E15: =IFERROR(C15+E14,"") -> 334621.5 | F15: =IFERROR(D15+F14,"") -> 383369.2 | G15: =IFERROR(C15-D15,"") -> -7684.0968 | H15: =IFERROR(E15-F15,"") -> -48747.705
A16: 45748 | B16: =TEXT(A16,"mmm-yy") -> Apr-25 | C16: =VLOOKUP(A16,'Revenue Sheet'!A:R,18,0) -> 85700 | D16: =VLOOKUP(A16,'Expense Sheet'!A:F,6,0) -> 86291 | E16: =IFERROR(C16+E15,"") -> 420321.5 | F16: =IFERROR(D16+F15,"") -> 469660.2 | G16: =IFERROR(C16-D16,"") -> -591 | H16: =IFERROR(E16-F16,"") -> -49338.705
A17: 45749 | B17: =TEXT(A17,"mmm-yy") -> Apr-25 | C17: =VLOOKUP(A17,'Revenue Sheet'!A:R,18,0) -> 30900 | D17: =VLOOKUP(A17,'Expense Sheet'!A:F,6,0) -> 31582.5 | E17: =IFERROR(C17+E16,"") -> 451221.5 | F17: =IFERROR(D17+F16,"") -> 501242.7 | G17: =IFERROR(C17-D17,"") -> -682.5 | H17: =IFERROR(E17-F17,"") -> -50021.205
... A76: 45808 | B76: =TEXT(A76,"mmm-yy") -> May-25 | C76: =VLOOKUP(A76,'Revenue Sheet'!A:R,18,0) -> 52030 | D76: =VLOOKUP(A76,'Expense Sheet'!A:F,6,0) -> 52498.097 | E76: =IFERROR(C76+E75,"") -> 1917866.5 | F76: =IFERROR(D76+F75,"") -> 2110079.5 | G76: =IFERROR(C76-D76,"") -> -468.09677 | H76: =IFERROR(E76-F76,"") -> -192212.95

Sheet Customer Master
A1: S.No | B1: Customer Name | C1: Location | D1: Address | E1: Distance | F1: Range
A2: 1 | B2: Cargo Motors | C2: Delhi | E2: 37 | F2: {=_xlfn.IFNA(_xlfn.IFS(AND(E2>0,E2<101),"0-100Km",AND(E2>100,E2<251),"101-250Km",AND(E2>250,E2<401),"251-400Km",AND(E2>400,E2<601),"401-600Km",E2>600,"Above 600Km"),0)} -> 0-100Km
A3: 2 | B3: VLH Marketing | C3: Karnal | E3: 95 | F3: {=_xlfn.IFNA(_xlfn.IFS(AND(E3>0,E3<101),"0-100Km",AND(E3>100,E3<251),"101-250Km",AND(E3>250,E3<401),"251-400Km",AND(E3>400,E3<601),"401-600Km",E3>600,"Above 600Km"),0)} -> 0-100Km
A4: 3 | B4: Johar Automobiles | C4: Faridabad | E4: 161 | F4: {=_xlfn.IFNA(_xlfn.IFS(AND(E4>0,E4<101),"0-100Km",AND(E4>100,E4<251),"101-250Km",AND(E4>250,E4<401),"251-400Km",AND(E4>400,E4<601),"401-600Km",E4>600,"Above 600Km"),0)} -> 101-250Km
A5: 4 | B5: Pasco Motors LLP | C5: New Delhi | E5: 70 | F5: {=_xlfn.IFNA(_xlfn.IFS(AND(E5>0,E5<101),"0-100Km",AND(E5>100,E5<251),"101-250Km",AND(E5>250,E5<401),"251-400Km",AND(E5>400,E5<601),"401-600Km",E5>600,"Above 600Km"),0)} -> 0-100Km
A6: 5 | B6: Yuvraj Motors | C6: Aligarh | E6: 186 | F6: {=_xlfn.IFNA(_xlfn.IFS(AND(E6>0,E6<101),"0-100Km",AND(E6>100,E6<251),"101-250Km",AND(E6>250,E6<401),"251-400Km",AND(E6>400,E6<601),"401-600Km",E6>600,"Above 600Km"),0)} -> 101-250Km
A7: 6 | B7: UP State Road Transport Corporation | C7: ghaziabad | E7: 91 | F7: {=_xlfn.IFNA(_xlfn.IFS(AND(E7>0,E7<101),"0-100Km",AND(E7>100,E7<251),"101-250Km",AND(E7>250,E7<401),"251-400Km",AND(E7>400,E7<601),"401-600Km",E7>600,"Above 600Km"),0)} -> 0-100Km
A8: 7 | B8: Sisothiya Automobile | C8: Dharuhera | E8: 121 | F8: {=_xlfn.IFNA(_xlfn.IFS(AND(E8>0,E8<101),"0-100Km",AND(E8>100,E8<251),"101-250Km",AND(E8>250,E8<401),"251-400Km",AND(E8>400,E8<601),"401-600Km",E8>600,"Above 600Km"),0)} -> 101-250Km
A9: 8 | B9: Sahni Motors | C9: Karnal | E9: 88 | F9: {=_xlfn.IFNA(_xlfn.IFS(AND(E9>0,E9<101),"0-100Km",AND(E9>100,E9<251),"101-250Km",AND(E9>250,E9<401),"251-400Km",AND(E9>400,E9<601),"401-600Km",E9>600,"Above 600Km"),0)} -> 0-100Km
A10: 9 | B10: Metro Motors Pvt Ltd. | C10: Karnal | E10: 100 | F10: {=_xlfn.IFNA(_xlfn.IFS(AND(E10>0,E10<101),"0-100Km",AND(E10>100,E10<251),"101-250Km",AND(E10>250,E10<401),"251-400Km",AND(E10>400,E10<601),"401-600Km",E10>600,"Above 600Km"),0)} -> 0-100Km
A11: 10 | B11: AA Automobiles Pvt. Ltd. | C11: Gaziabad | E11: 66 | F11: {=_xlfn.IFNA(_xlfn.IFS(AND(E11>0,E11<101),"0-100Km",AND(E11>100,E11<251),"101-250Km",AND(E11>250,E11<401),"251-400Km",AND(E11>400,E11<601),"401-600Km",E11>600,"Above 600Km"),0)} -> 0-100Km
A12: 11 | B12: Jain Motors Srore | C12: Tohana | E12: 186 | F12: {=_xlfn.IFNA(_xlfn.IFS(AND(E12>0,E12<101),"0-100Km",AND(E12>100,E12<251),"101-250Km",AND(E12>250,E12<401),"251-400Km",AND(E12>400,E12<601),"401-600Km",E12>600,"Above 600Km"),0)} -> 101-250Km
A13: 12 | B13: Shree Shyam Automobiles | C13: Ferozpur | E13: 251 | F13: {=_xlfn.IFNA(_xlfn.IFS(AND(E13>0,E13<101),"0-100Km",AND(E13>100,E13<251),"101-250Km",AND(E13>250,E13<401),"251-400Km",AND(E13>400,E13<601),"401-600Km",E13>600,"Above 600Km"),0)} -> 251-400Km
... A16: 15 | B16: RK Automobiles Private Limited | C16: Sahibabad | E16: 80 | F16: {=_xlfn.IFNA(_xlfn.IFS(AND(E16>0,E16<101),"0-100Km",AND(E16>100,E16<251),"101-250Km",AND(E16>250,E16<401),"251-400Km",AND(E16>400,E16<601),"401-600Km",E16>600,"Above 600Km"),0)} -> 0-100Km
A17: 16 | B17: mangalam auto | C17: Palwal | E17: =320/2 -> 160 | F17: {=_xlfn.IFNA(_xlfn.IFS(AND(E17>0,E17<101),"0-100Km",AND(E17>100,E17<251),"101-250Km",AND(E17>250,E17<401),"251-400Km",AND(E17>400,E17<601),"401-600Km",E17>600,"Above 600Km"),0)} -> 101-250Km
A18: 17 | B18: UP State Road Transport Corporation | C18: Saharanpur | E18: 194 | F18: {=_xlfn.IFNA(_xlfn.IFS(AND(E18>0,E18<101),"0-100Km",AND(E18>100,E18<251),"101-250Km",AND(E18>250,E18<401),"251-400Km",AND(E18>400,E18<601),"401-600Km",E18>600,"Above 600Km"),0)} -> 101-250Km
A19: 18 | B19: Anand motors | C19: gohana | E19: 86 | F19: {=_xlfn.IFNA(_xlfn.IFS(AND(E19>0,E19<101),"0-100Km",AND(E19>100,E19<251),"101-250Km",AND(E19>250,E19<401),"251-400Km",AND(E19>400,E19<601),"401-600Km",E19>600,"Above 600Km"),0)} -> 0-100Km
A20: 19 | B20: mg motors | C20: rohtak | E20: 90 | F20: {=_xlfn.IFNA(_xlfn.IFS(AND(E20>0,E20<101),"0-100Km",AND(E20>100,E20<251),"101-250Km",AND(E20>250,E20<401),"251-400Km",AND(E20>400,E20<601),"401-600Km",E20>600,"Above 600Km"),0)} -> 0-100Km
A21: 20 | B21: Sanghi Automobiles | C21: Rewari | E21: 122 | F21: {=_xlfn.IFNA(_xlfn.IFS(AND(E21>0,E21<101),"0-100Km",AND(E21>100,E21<251),"101-250Km",AND(E21>250,E21<401),"251-400Km",AND(E21>400,E21<601),"401-600Km",E21>600,"Above 600Km"),0)} -> 101-250Km
A22: 21 | B22: Hind Motor | C22: Hisar | E22: 197 | F22: {=_xlfn.IFNA(_xlfn.IFS(AND(E22>0,E22<101),"0-100Km",AND(E22>100,E22<251),"101-250Km",AND(E22>250,E22<401),"251-400Km",AND(E22>400,E22<601),"401-600Km",E22>600,"Above 600Km"),0)} -> 101-250Km
A23: 22 | B23: ganganagar vehicles pvt ltd | C23: Karnal | E23: 90 | F23: {=_xlfn.IFNA(_xlfn.IFS(AND(E23>0,E23<101),"0-100Km",AND(E23>100,E23<251),"101-250Km",AND(E23>250,E23<401),"251-400Km",AND(E23>400,E23<601),"401-600Km",E23>600,"Above 600Km"),0)} -> 0-100Km
A24: 23 | B24: sumit auto store | C24: rohtak | E24: 90 | F24: {=_xlfn.IFNA(_xlfn.IFS(AND(E24>0,E24<101),"0-100Km",AND(E24>100,E24<251),"101-250Km",AND(E24>250,E24<401),"251-400Km",AND(E24>400,E24<601),"401-600Km",E24>600,"Above 600Km"),0)} -> 0-100Km
A25: 24 | B25: raju motor store | C25: sonipat | D25: 131001 | E25: 21 | F25: {=_xlfn.IFNA(_xlfn.IFS(AND(E25>0,E25<101),"0-100Km",AND(E25>100,E25<251),"101-250Km",AND(E25>250,E25<401),"251-400Km",AND(E25>400,E25<601),"401-600Km",E25>600,"Above 600Km"),0)} -> 0-100Km
A26: 25 | B26: laxmi agencies | C26: pilkhuwa | E26: 88 | F26: {=_xlfn.IFNA(_xlfn.IFS(AND(E26>0,E26<101),"0-100Km",AND(E26>100,E26<251),"101-250Km",AND(E26>250,E26<401),"251-400Km",AND(E26>400,E26<601),"401-600Km",E26>600,"Above 600Km"),0)} -> 0-100Km
A27: 26 | B27: pcj motors | C27: muzaffarnagar | E27: 140 | F27: {=_xlfn.IFNA(_xlfn.IFS(AND(E27>0,E27<101),"0-100Km",AND(E27>100,E27<251),"101-250Km",AND(E27>250,E27<401),"251-400Km",AND(E27>400,E27<601),"401-600Km",E27>600,"Above 600Km"),0)} -> 101-250Km
A28: 27 | B28: ashoka motors | C28: hisar | E28: 186 | F28: {=_xlfn.IFNA(_xlfn.IFS(AND(E28>0,E28<101),"0-100Km",AND(E28>100,E28<251),"101-250Km",AND(E28>250,E28<401),"251-400Km",AND(E28>400,E28<601),"401-600Km",E28>600,"Above 600Km"),0)} -> 101-250Km
A29: 28 | B29: shivam motor | C29: rohtak | E29: 74 | F29: {=_xlfn.IFNA(_xlfn.IFS(AND(E29>0,E29<101),"0-100Km",AND(E29>100,E29<251),"101-250Km",AND(E29>250,E29<401),"251-400Km",AND(E29>400,E29<601),"401-600Km",E29>600,"Above 600Km"),0)} -> 0-100Km
A30: 29 | B30: hloc auto parts pvt.ltd. | C30: New Delhi | E30: 35 | F30: {=_xlfn.IFNA(_xlfn.IFS(AND(E30>0,E30<101),"0-100Km",AND(E30>100,E30<251),"101-250Km",AND(E30>250,E30<401),"251-400Km",AND(E30>400,E30<601),"401-600Km",E30>600,"Above 600Km"),0)} -> 0-100Km
A31: 30 | B31: sjs motors | C31: shamli | E31: 95 | F31: {=_xlfn.IFNA(_xlfn.IFS(AND(E31>0,E31<101),"0-100Km",AND(E31>100,E31<251),"101-250Km",AND(E31>250,E31<401),"251-400Km",AND(E31>400,E31<601),"401-600Km",E31>600,"Above 600Km"),0)} -> 0-100Km
A32: 31 | B32: garg logistics | C32: panipat | E32: 67 | F32: {=_xlfn.IFNA(_xlfn.IFS(AND(E32>0,E32<101),"0-100Km",AND(E32>100,E32<251),"101-250Km",AND(E32>250,E32<401),"251-400Km",AND(E32>400,E32<601),"401-600Km",E32>600,"Above 600Km"),0)} -> 0-100Km
A33: 32 | B33: shiva motors | C33: narwana | E33: 149 | F33: {=_xlfn.IFNA(_xlfn.IFS(AND(E33>0,E33<101),"0-100Km",AND(E33>100,E33<251),"101-250Km",AND(E33>250,E33<401),"251-400Km",AND(E33>400,E33<601),"401-600Km",E33>600,"Above 600Km"),0)} -> 101-250Km
A34: 33 | B34: gng auto aids pvt ltd | C34: bilaspur gurgaon | E34: 109 | F34: {=_xlfn.IFNA(_xlfn.IFS(AND(E34>0,E34<101),"0-100Km",AND(E34>100,E34<251),"101-250Km",AND(E34>250,E34<401),"251-400Km",AND(E34>400,E34<601),"401-600Km",E34>600,"Above 600Km"),0)} -> 101-250Km
A35: 34 | B35: patricia holdings pvt ltd | C35: udham singh nagar | E35: 287 | F35: {=_xlfn.IFNA(_xlfn.IFS(AND(E35>0,E35<101),"0-100Km",AND(E35>100,E35<251),"101-250Km",AND(E35>250,E35<401),"251-400Km",AND(E35>400,E35<601),"401-600Km",E35>600,"Above 600Km"),0)} -> 251-400Km
A36: 35 | B36: pasco | C36: Delhi | E36: 56 | F36: {=_xlfn.IFNA(_xlfn.IFS(AND(E36>0,E36<101),"0-100Km",AND(E36>100,E36<251),"101-250Km",AND(E36>250,E36<401),"251-400Km",AND(E36>400,E36<601),"401-600Km",E36>600,"Above 600Km"),0)} -> 0-100Km
A37: 36 | B37: Metro Motors Pvt Ltd. | C37: panipat | E37: 56 | F37: {=_xlfn.IFNA(_xlfn.IFS(AND(E37>0,E37<101),"0-100Km",AND(E37>100,E37<251),"101-250Km",AND(E37>250,E37<401),"251-400Km",AND(E37>400,E37<601),"401-600Km",E37>600,"Above 600Km"),0)} -> 0-100Km
... A39: 38 | B39: shanti autosales pvt ltd | C39: Gautam Budhh Nagar | E39: 97 | F39: {=_xlfn.IFNA(_xlfn.IFS(AND(E39>0,E39<101),"0-100Km",AND(E39>100,E39<251),"101-250Km",AND(E39>250,E39<401),"251-400Km",AND(E39>400,E39<601),"401-600Km",E39>600,"Above 600Km"),0)} -> 0-100Km
A40: 39 | B40: meerut automobile pvt ltd | C40: muzaffarnagar | D40: 251002 | E40: 95 | F40: {=_xlfn.IFNA(_xlfn.IFS(AND(E40>0,E40<101),"0-100Km",AND(E40>100,E40<251),"101-250Km",AND(E40>250,E40<401),"251-400Km",AND(E40>400,E40<601),"401-600Km",E40>600,"Above 600Km"),0)} -> 0-100Km
A41: 40 | B41: tkj automobiles jv | C41: chhutmalpur | E41: 169 | F41: {=_xlfn.IFNA(_xlfn.IFS(AND(E41>0,E41<101),"0-100Km",AND(E41>100,E41<251),"101-250Km",AND(E41>250,E41<401),"251-400Km",AND(E41>400,E41<601),"401-600Km",E41>600,"Above 600Km"),0)} -> 101-250Km
A42: 41 | B42: abc motors | C42: fatehabad | E42: 117 | F42: {=_xlfn.IFNA(_xlfn.IFS(AND(E42>0,E42<101),"0-100Km",AND(E42>100,E42<251),"101-250Km",AND(E42>250,E42<401),"251-400Km",AND(E42>400,E42<601),"401-600Km",E42>600,"Above 600Km"),0)} -> 101-250Km
A43: 42 | B43: cns motors pvt ltd | C43: bijnor | D43: 246701 | E43: 142 | F43: {=_xlfn.IFNA(_xlfn.IFS(AND(E43>0,E43<101),"0-100Km",AND(E43>100,E43<251),"101-250Km",AND(E43>250,E43<401),"251-400Km",AND(E43>400,E43<601),"401-600Km",E43>600,"Above 600Km"),0)} -> 101-250Km
A44: 43 | B44: Ashok Ventures LLP | C44: Gautam Buddha Nagar | E44: 90 | F44: {=_xlfn.IFNA(_xlfn.IFS(AND(E44>0,E44<101),"0-100Km",AND(E44>100,E44<251),"101-250Km",AND(E44>250,E44<401),"251-400Km",AND(E44>400,E44<601),"401-600Km",E44>600,"Above 600Km"),0)} -> 0-100Km
A45: 44 | B45: vijay automobile | C45: bharatpur | E45: 329 | F45: {=_xlfn.IFNA(_xlfn.IFS(AND(E45>0,E45<101),"0-100Km",AND(E45>100,E45<251),"101-250Km",AND(E45>250,E45<401),"251-400Km",AND(E45>400,E45<601),"401-600Km",E45>600,"Above 600Km"),0)} -> 251-400Km
A46: 45 | B46: ashok auto sales ltd | C46: mathura | E46: 265 | F46: {=_xlfn.IFNA(_xlfn.IFS(AND(E46>0,E46<101),"0-100Km",AND(E46>100,E46<251),"101-250Km",AND(E46>250,E46<401),"251-400Km",AND(E46>400,E46<601),"401-600Km",E46>600,"Above 600Km"),0)} -> 251-400Km
A47: 46 | B47: pasco motors LLP | C47: faridabad | E47: 148 | F47: {=_xlfn.IFNA(_xlfn.IFS(AND(E47>0,E47<101),"0-100Km",AND(E47>100,E47<251),"101-250Km",AND(E47>250,E47<401),"251-400Km",AND(E47>400,E47<601),"401-600Km",E47>600,"Above 600Km"),0)} -> 101-250Km
A48: 47 | B48: triumph auto parts distr pvt ltd | C48: palwal | E48: 158 | F48: {=_xlfn.IFNA(_xlfn.IFS(AND(E48>0,E48<101),"0-100Km",AND(E48>100,E48<251),"101-250Km",AND(E48>250,E48<401),"251-400Km",AND(E48>400,E48<601),"401-600Km",E48>600,"Above 600Km"),0)} -> 101-250Km
A49: 48 | B49: pasco Motors LLP | C49: gurgaon | E49: 107 | F49: {=_xlfn.IFNA(_xlfn.IFS(AND(E49>0,E49<101),"0-100Km",AND(E49>100,E49<251),"101-250Km",AND(E49>250,E49<401),"251-400Km",AND(E49>400,E49<601),"401-600Km",E49>600,"Above 600Km"),0)} -> 101-250Km
A50: 49 | B50: oberai motors ltd | C50: kotdwara | E50: 218 | F50: {=_xlfn.IFNA(_xlfn.IFS(AND(E50>0,E50<101),"0-100Km",AND(E50>100,E50<251),"101-250Km",AND(E50>250,E50<401),"251-400Km",AND(E50>400,E50<601),"401-600Km",E50>600,"Above 600Km"),0)} -> 101-250Km
A51: 50 | B51: mona generator services pvt ltd | C51: New Delhi | E51: 71 | F51: {=_xlfn.IFNA(_xlfn.IFS(AND(E51>0,E51<101),"0-100Km",AND(E51>100,E51<251),"101-250Km",AND(E51>250,E51<401),"251-400Km",AND(E51>400,E51<601),"401-600Km",E51>600,"Above 600Km"),0)} -> 0-100Km
A52: 51 | B52: sjs motors | C52: saharanpur | E52: 147 | F52: {=_xlfn.IFNA(_xlfn.IFS(AND(E52>0,E52<101),"0-100Km",AND(E52>100,E52<251),"101-250Km",AND(E52>250,E52<401),"251-400Km",AND(E52>400,E52<601),"401-600Km",E52>600,"Above 600Km"),0)} -> 101-250Km
A53: 52 | B53: sjs motors | C53: tatarpur | D53: 245201 | E53: 98 | F53: {=_xlfn.IFNA(_xlfn.IFS(AND(E53>0,E53<101),"0-100Km",AND(E53>100,E53<251),"101-250Km",AND(E53>250,E53<401),"251-400Km",AND(E53>400,E53<601),"401-600Km",E53>600,"Above 600Km"),0)} -> 0-100Km
A54: 53 | B54: ra motors pvt ltd | C54: moradabad | E54: 208 | F54: {=_xlfn.IFNA(_xlfn.IFS(AND(E54>0,E54<101),"0-100Km",AND(E54>100,E54<251),"101-250Km",AND(E54>250,E54<401),"251-400Km",AND(E54>400,E54<601),"401-600Km",E54>600,"Above 600Km"),0)} -> 101-250Km
A55: 54 | B55: abhishek automobiles | C55: Rewari | E55: 113 | F55: {=_xlfn.IFNA(_xlfn.IFS(AND(E55>0,E55<101),"0-100Km",AND(E55>100,E55<251),"101-250Km",AND(E55>250,E55<401),"251-400Km",AND(E55>400,E55<601),"401-600Km",E55>600,"Above 600Km"),0)} -> 101-250Km
A56: 55 | B56: shri shyam automobiles | C56: ferozpur jhirka | E56: 167 | F56: {=_xlfn.IFNA(_xlfn.IFS(AND(E56>0,E56<101),"0-100Km",AND(E56>100,E56<251),"101-250Km",AND(E56>250,E56<401),"251-400Km",AND(E56>400,E56<601),"401-600Km",E56>600,"Above 600Km"),0)} -> 101-250Km
A57: 56 | B57: a&a automobiles pvt ltd | C57: ghaziabad | E57: 62 | F57: {=_xlfn.IFNA(_xlfn.IFS(AND(E57>0,E57<101),"0-100Km",AND(E57>100,E57<251),"101-250Km",AND(E57>250,E57<401),"251-400Km",AND(E57>400,E57<601),"401-600Km",E57>600,"Above 600Km"),0)} -> 0-100Km
A58: 57 | B58: patricia holdings pvt ltd | C58: roorkee | E58: 171 | F58: {=_xlfn.IFNA(_xlfn.IFS(AND(E58>0,E58<101),"0-100Km",AND(E58>100,E58<251),"101-250Km",AND(E58>250,E58<401),"251-400Km",AND(E58>400,E58<601),"401-600Km",E58>600,"Above 600Km"),0)} -> 101-250Km
A59: 58 | B59: haryana motor | C59: jhajjar | E59: 80 | F59: {=_xlfn.IFNA(_xlfn.IFS(AND(E59>0,E59<101),"0-100Km",AND(E59>100,E59<251),"101-250Km",AND(E59>250,E59<401),"251-400Km",AND(E59>400,E59<601),"401-600Km",E59>600,"Above 600Km"),0)} -> 0-100Km
A60: 59 | B60: yuvraj motors | C60: aligarh | E60: 185 | F60: {=_xlfn.IFNA(_xlfn.IFS(AND(E60>0,E60<101),"0-100Km",AND(E60>100,E60<251),"101-250Km",AND(E60>250,E60<401),"251-400Km",AND(E60>400,E60<601),"401-600Km",E60>600,"Above 600Km"),0)} -> 101-250Km
A61: 60 | B61: amit auto wheels pvt ltd | C61: rudrapur | E61: 287 | F61: {=_xlfn.IFNA(_xlfn.IFS(AND(E61>0,E61<101),"0-100Km",AND(E61>100,E61<251),"101-250Km",AND(E61>250,E61<401),"251-400Km",AND(E61>400,E61<601),"401-600Km",E61>600,"Above 600Km"),0)} -> 251-400Km
A62: 61 | B62: amit auto wheels pvt ltd | C62: haldwani | E62: 312 | F62: {=_xlfn.IFNA(_xlfn.IFS(AND(E62>0,E62<101),"0-100Km",AND(E62>100,E62<251),"101-250Km",AND(E62>250,E62<401),"251-400Km",AND(E62>400,E62<601),"401-600Km",E62>600,"Above 600Km"),0)} -> 251-400Km
A63: 62 | B63: singhal enterprises | C63: manglaur | E63: 154 | F63: {=_xlfn.IFNA(_xlfn.IFS(AND(E63>0,E63<101),"0-100Km",AND(E63>100,E63<251),"101-250Km",AND(E63>250,E63<401),"251-400Km",AND(E63>400,E63<601),"401-600Km",E63>600,"Above 600Km"),0)} -> 101-250Km
A64: 63 | B64: triumph auto (cv) pvt ldt | C64: Delhi | E64: 32 | F64: {=_xlfn.IFNA(_xlfn.IFS(AND(E64>0,E64<101),"0-100Km",AND(E64>100,E64<251),"101-250Km",AND(E64>250,E64<401),"251-400Km",AND(E64>400,E64<601),"401-600Km",E64>600,"Above 600Km"),0)} -> 0-100Km
A65: 64 | B65: saawariya automobiles | C65: sohna | E65: 125 | F65: {=_xlfn.IFNA(_xlfn.IFS(AND(E65>0,E65<101),"0-100Km",AND(E65>100,E65<251),"101-250Km",AND(E65>250,E65<401),"251-400Km",AND(E65>400,E65<601),"401-600Km",E65>600,"Above 600Km"),0)} -> 101-250Km
... A82: 81 | B82: nvdeep autocops pvt ltd. | C82: tauru | E82: 116 | F82: {=_xlfn.IFNA(_xlfn.IFS(AND(E82>0,E82<101),"0-100Km",AND(E82>100,E82<251),"101-250Km",AND(E82>250,E82<401),"251-400Km",AND(E82>400,E82<601),"401-600Km",E82>600,"Above 600Km"),0)} -> 101-250Km
A83: 82 | B83: triumph auto parts distr pvt ltd | C83: bahadurgarh | D83: 124507 | E83: 62 | F83: {=_xlfn.IFNA(_xlfn.IFS(AND(E83>0,E83<101),"0-100Km",AND(E83>100,E83<251),"101-250Km",AND(E83>250,E83<401),"251-400Km",AND(E83>400,E83<601),"401-600Km",E83>600,"Above 600Km"),0)} -> 0-100Km
A84: 83 | B84: ganganagar motros | C84: Delhi | E84: 37 | F84: {=_xlfn.IFNA(_xlfn.IFS(AND(E84>0,E84<101),"0-100Km",AND(E84>100,E84<251),"101-250Km",AND(E84>250,E84<401),"251-400Km",AND(E84>400,E84<601),"401-600Km",E84>600,"Above 600Km"),0)} -> 0-100Km
A85: 84 | B85: mlk autos | C85: haldwani | E85: 319 | F85: {=_xlfn.IFNA(_xlfn.IFS(AND(E85>0,E85<101),"0-100Km",AND(E85>100,E85<251),"101-250Km",AND(E85>250,E85<401),"251-400Km",AND(E85>400,E85<601),"401-600Km",E85>600,"Above 600Km"),0)} -> 251-400Km
A86: 85 | B86: arihant motors | C86: rohtak | E86: 75 | F86: {=_xlfn.IFNA(_xlfn.IFS(AND(E86>0,E86<101),"0-100Km",AND(E86>100,E86<251),"101-250Km",AND(E86>250,E86<401),"251-400Km",AND(E86>400,E86<601),"401-600Km",E86>600,"Above 600Km"),0)} -> 0-100Km
A87: 86 | B87: hindustan motors | C87: rohtak | E87: 81 | F87: {=_xlfn.IFNA(_xlfn.IFS(AND(E87>0,E87<101),"0-100Km",AND(E87>100,E87<251),"101-250Km",AND(E87>250,E87<401),"251-400Km",AND(E87>400,E87<601),"401-600Km",E87>600,"Above 600Km"),0)} -> 0-100Km
A88: 87 | B88: cns motors pvt ltd | C88: joya | D88: 244222 | E88: 164 | F88: {=_xlfn.IFNA(_xlfn.IFS(AND(E88>0,E88<101),"0-100Km",AND(E88>100,E88<251),"101-250Km",AND(E88>250,E88<401),"251-400Km",AND(E88>400,E88<601),"401-600Km",E88>600,"Above 600Km"),0)} -> 101-250Km
A89: 88 | B89: vipin motors pvt ltd | C89: hisar | E89: 185 | F89: 101-250km
A90: 89 | B90: meerut automobile pvt ltd | C90: Delhi | E90: 62 | F90: {=_xlfn.IFNA(_xlfn.IFS(AND(E90>0,E90<101),"0-100Km",AND(E90>100,E90<251),"101-250Km",AND(E90>250,E90<401),"251-400Km",AND(E90>400,E90<601),"401-600Km",E90>600,"Above 600Km"),0)} -> 0-100Km
A91: 90 | B91: up state road transport | C91: ghaziabad | E91: 76 | F91: {=_xlfn.IFNA(_xlfn.IFS(AND(E91>0,E91<101),"0-100Km",AND(E91>100,E91<251),"101-250Km",AND(E91>250,E91<401),"251-400Km",AND(E91>400,E91<601),"401-600Km",E91>600,"Above 600Km"),0)} -> 0-100Km
A92: 91 | B92: up state road transport | C92: aligarh | E92: 190 | F92: {=_xlfn.IFNA(_xlfn.IFS(AND(E92>0,E92<101),"0-100Km",AND(E92>100,E92<251),"101-250Km",AND(E92>250,E92<401),"251-400Km",AND(E92>400,E92<601),"401-600Km",E92>600,"Above 600Km"),0)} -> 101-250Km
A93: 92 | B93: ashirvad motors | C93: agra | E93: 318 | F93: {=_xlfn.IFNA(_xlfn.IFS(AND(E93>0,E93<101),"0-100Km",AND(E93>100,E93<251),"101-250Km",AND(E93>250,E93<401),"251-400Km",AND(E93>400,E93<601),"401-600Km",E93>600,"Above 600Km"),0)} -> 251-400Km
A94: 93 | B94: standard motors stores | C94: dehradun | E94: 204 | F94: {=_xlfn.IFNA(_xlfn.IFS(AND(E94>0,E94<101),"0-100Km",AND(E94>100,E94<251),"101-250Km",AND(E94>250,E94<401),"251-400Km",AND(E94>400,E94<601),"401-600Km",E94>600,"Above 600Km"),0)} -> 101-250Km
A95: 94 | B95: lube solution | C95: noida | E95: 124 | F95: {=_xlfn.IFNA(_xlfn.IFS(AND(E95>0,E95<101),"0-100Km",AND(E95>100,E95<251),"101-250Km",AND(E95>250,E95<401),"251-400Km",AND(E95>400,E95<601),"401-600Km",E95>600,"Above 600Km"),0)} -> 101-250Km
A96: 95 | B96: bharat steel & auto spares | C96: ghaziabad | E96: 124 | F96: {=_xlfn.IFNA(_xlfn.IFS(AND(E96>0,E96<101),"0-100Km",AND(E96>100,E96<251),"101-250Km",AND(E96>250,E96<401),"251-400Km",AND(E96>400,E96<601),"401-600Km",E96>600,"Above 600Km"),0)} -> 101-250Km
A97: 96 | B97: v 8 autos | C97: tehri garhwal | E97: 226 | F97: {=_xlfn.IFNA(_xlfn.IFS(AND(E97>0,E97<101),"0-100Km",AND(E97>100,E97<251),"101-250Km",AND(E97>250,E97<401),"251-400Km",AND(E97>400,E97<601),"401-600Km",E97>600,"Above 600Km"),0)} -> 101-250Km
A98: 97 | B98: r k automobile pvt ltd (up state ) | C98: Sahibabad | E98: 75 | F98: {=_xlfn.IFNA(_xlfn.IFS(AND(E98>0,E98<101),"0-100Km",AND(E98>100,E98<251),"101-250Km",AND(E98>250,E98<401),"251-400Km",AND(E98>400,E98<601),"401-600Km",E98>600,"Above 600Km"),0)} -> 0-100Km
A99: 98 | B99: cas motors | C99: bagwali | E99: 194 | F99: {=_xlfn.IFNA(_xlfn.IFS(AND(E99>0,E99<101),"0-100Km",AND(E99>100,E99<251),"101-250Km",AND(E99>250,E99<401),"251-400Km",AND(E99>400,E99<601),"401-600Km",E99>600,"Above 600Km"),0)} -> 101-250Km
A100: 99 | B100: ganganagar motros | C100: jhalawar | E100: 610 | F100: {=_xlfn.IFNA(_xlfn.IFS(AND(E100>0,E100<101),"0-100Km",AND(E100>100,E100<251),"101-250Km",AND(E100>250,E100<401),"251-400Km",AND(E100>400,E100<601),"401-600Km",E100>600,"Above 600Km"),0)} -> Above 600Km
A101: 100 | B101: mangalam auto | C101: hodel | E101: 177 | F101: {=_xlfn.IFNA(_xlfn.IFS(AND(E101>0,E101<101),"0-100Km",AND(E101>100,E101<251),"101-250Km",AND(E101>250,E101<401),"251-400Km",AND(E101>400,E101<601),"401-600Km",E101>600,"Above 600Km"),0)} -> 101-250Km
A102: 101 | B102: jain transport corporation | C102: lalkuan | E102: 305 | F102: {=_xlfn.IFNA(_xlfn.IFS(AND(E102>0,E102<101),"0-100Km",AND(E102>100,E102<251),"101-250Km",AND(E102>250,E102<401),"251-400Km",AND(E102>400,E102<601),"401-600Km",E102>600,"Above 600Km"),0)} -> 251-400Km
A103: 102 | B103: lotus motors | C103: rajasamand
A104: 103 | B104: pascos | C104: delhi | E104: 31 | F104: 0-100km
A105: 104 | B105: rennita motors | C105: herbertpur | E105: 206 | F105: 101-250km
A106: 105 | B106: bee gee automobiles | C106: shimla | E106: 304 | F106: 251-400km
A107: 106 | B107: pinder motors | C107: simli
A108: 107 | B108: sarthi construction pvt ltd | C108: tanakpur | E108: 372 | F108: 251-400km
A109: 108 | B109: taksh motors | C109: ghaziabad | E109: 70 | F109: 0-100km
A110: 109 | B110: pasco motors LLP | C110: pataudi | E110: 90 | F110: 0-100km
A111: 110 | B111: H S MOTOR | C111: panipat | E111: 65 | F111: 0-100km
A112: 111 | B112: raghunath prasad brijnandan prasad | C112: bijnor | E112: 234 | F112: 101-250km
A113: 112 | B113: aayush motors | C113: haridwar | E113: 186 | F113: 101-250km
A114: 113 | B114: vijay shree automobile | C114: rishikesh | D114: 249201 | E114: 202 | F114: 101-250km
A115: 114 | B115: s r trading | C115: pargana dasna | D115: 201001 | E115: 66 | F115: 0-100km
A116: 115 | B116: aayush motors | C116: bhagwanpur | D116: 247661 | E116: 181 | F116: 101-250km
A117: 116 | B117: shree ram motors | C117: mathura | D117: 281005 | E117: 239 | F117: 101-250km
A118: 117 | B118: gaba traders | C118: rudrapur | D118: 263153 | E118: 269 | F118: 251-400km
A119: 118 | B119: pradeep kumar contarctor | C119: pauri garhwal | D119: 246174 | E119: 329 | F119: 251-400km
...

Sheet Revenue Sheet
C1: 0-100Km | F1: 101-250Km | I1: 251-400Km | L1: 401-600Km | O1: Total
A2: Date | B2: LR Count | C2: {=TRANSPOSE('Material Master'!$B$2:$B$4)} -> 20L Buckets | D2: 20L Jerry Can | E2: 210L Barrels | F2: {=TRANSPOSE('Material Master'!$B$2:$B$4)} -> 20L Buckets | G2: 20L Jerry Can | H2: 210L Barrels | I2: {=TRANSPOSE('Material Master'!$B$2:$B$4)} -> 20L Buckets | J2: 20L Jerry Can | K2: 210L Barrels | L2: {=TRANSPOSE('Material Master'!$B$2:$B$4)} -> 20L Buckets | M2: 20L Jerry Can | N2: 210L Barrels | O2: {=TRANSPOSE('Material Master'!$B$2:$B$4)} -> 20L Buckets | P2: 20L Jerry Can | Q2: 210L Barrels | R2: Total Revenue
A3: 45734 | B3: {=IF(A3>TODAY(),"",COUNTA(_xlfn.UNIQUE(_xlfn._xlws.FILTER('OPs Data'!$K:$K,'OPs Data'!$D:$D='Revenue Sheet'!A3))))} -> 4 | C3: =IF(A3>TODAY(),"",SUMIFS('OPs Data'!$N:$N,'OPs Data'!$F:$F,'Revenue Sheet'!C$1,'OPs Data'!$D:$D,'Revenue Sheet'!$A3,'OPs Data'!$L:$L,'Revenue Sheet'!C$2)*VLOOKUP($C$1,'Rate Card'!$B:$E,MATCH('Revenue Sheet'!C$2,'Rate Card'!$B$2:$E$2,0),0)) -> 16800 | D3: =IF(A3>TODAY(),"",SUMIFS('OPs Data'!$N:$N,'OPs Data'!$F:$F,'Revenue Sheet'!C$1,'OPs Data'!$D:$D,'Revenue Sheet'!$A3,'OPs Data'!$L:$L,'Revenue Sheet'!D$2)*VLOOKUP($C$1,'Rate Card'!$B:$E,MATCH('Revenue Sheet'!D$2,'Rate Card'!$B$2:$E$2,0),0)) -> 0 | E3: =IF(A3>TODAY(),"",SUMIFS('OPs Data'!$N:$N,'OPs Data'!$F:$F,'Revenue Sheet'!C$1,'OPs Data'!$D:$D,'Revenue Sheet'!$A3,'OPs Data'!$L:$L,'Revenue Sheet'!E$2)*VLOOKUP($C$1,'Rate Card'!$B:$E,MATCH('Revenue Sheet'!E$2,'Rate Card'!$B$2:$E$2,0),0)) -> 661.5 | F3: =IF(A3>TODAY(),"",SUMIFS('OPs Data'!$N:$N,'OPs Data'!$F:$F,'Revenue Sheet'!F$1,'OPs Data'!$D:$D,'Revenue Sheet'!$A3,'OPs Data'!$L:$L,'Revenue Sheet'!F$2)*VLOOKUP($F$1,'Rate Card'!$B:$E,MATCH('Revenue Sheet'!F$2,'Rate Card'!$B$2:$E$2,0),0)) -> 12000 | G3: =IF(A3>TODAY(),"",SUMIFS('OPs Data'!$N:$N,'OPs Data'!$F:$F,'Revenue Sheet'!F$1,'OPs Data'!$D:$D,'Revenue Sheet'!$A3,'OPs Data'!$L:$L,'Revenue Sheet'!G$2)*VLOOKUP($F$1,'Rate Card'!$B:$E,MATCH('Revenue Sheet'!G$2,'Rate Card'!$B$2:$E$2,0),0)) -> 0 | H3: =IF(A3>TODAY(),"",SUMIFS('OPs Data'!$N:$N,'OPs Data'!$F:$F,'Revenue Sheet'!F$1,'OPs Data'!$D:$D,'Revenue Sheet'!$A3,'OPs Data'!$L:$L,'Revenue Sheet'!H$2)*VLOOKUP($F$1,'Rate Card'!$B:$E,MATCH('Revenue Sheet'!H$2,'Rate Card'!$B$2:$E$2,0),0)) -> 0 | I3: =IF(A3>TODAY(),"",SUMIFS('OPs Data'!$N:$N,'OPs Data'!$F:$F,'Revenue Sheet'!I$1,'OPs Data'!$D:$D,'Revenue Sheet'!$A3,'OPs Data'!$L:$L,'Revenue Sheet'!I$2)*VLOOKUP($I$1,'Rate Card'!$B:$E,MATCH('Revenue Sheet'!I$2,'Rate Card'!$B$2:$E$2,0),0)) -> 0 | J3: =IF(A3>TODAY(),"",SUMIFS('OPs Data'!$N:$N,'OPs Data'!$F:$F,'Revenue Sheet'!I$1,'OPs Data'!$D:$D,'Revenue Sheet'!$A3,'OPs Data'!$L:$L,'Revenue Sheet'!J$2)*VLOOKUP($I$1,'Rate Card'!$B:$E,MATCH('Revenue Sheet'!J$2,'Rate Card'!$B$2:$E$2,0),0)) -> 0 | K3: =IF(A3>TODAY(),"",SUMIFS('OPs Data'!$N:$N,'OPs Data'!$F:$F,'Revenue Sheet'!I$1,'OPs Data'!$D:$D,'Revenue Sheet'!$A3,'OPs Data'!$L:$L,'Revenue Sheet'!K$2)*VLOOKUP($I$1,'Rate Card'!$B:$E,MATCH('Revenue Sheet'!K$2,'Rate Card'!$B$2:$E$2,0),0)) -> 0 | L3: =IF(A3>TODAY(),"",SUMIFS('OPs Data'!$N:$N,'OPs Data'!$F:$F,'Revenue Sheet'!L$1,'OPs Data'!$D:$D,'Revenue Sheet'!$A3,'OPs Data'!$L:$L,'Revenue Sheet'!L$2)*VLOOKUP($L$1,'Rate Card'!$B:$E,MATCH('Revenue Sheet'!L$2,'Rate Card'!$B$2:$E$2,0),0)) -> 0 | M3: =IF(A3>TODAY(),"",SUMIFS('OPs Data'!$N:$N,'OPs Data'!$F:$F,'Revenue Sheet'!L$1,'OPs Data'!$D:$D,'Revenue Sheet'!$A3,'OPs Data'!$L:$L,'Revenue Sheet'!M$2)*VLOOKUP($L$1,'Rate Card'!$B:$E,MATCH('Revenue Sheet'!M$2,'Rate Card'!$B$2:$E$2,0),0)) -> 0 | N3: =IF(A3>TODAY(),"",SUMIFS('OPs Data'!$N:$N,'OPs Data'!$F:$F,'Revenue Sheet'!L$1,'OPs Data'!$D:$D,'Revenue Sheet'!$A3,'OPs Data'!$L:$L,'Revenue Sheet'!N$2)*VLOOKUP($L$1,'Rate Card'!$B:$E,MATCH('Revenue Sheet'!N$2,'Rate Card'!$B$2:$E$2,0),0)) -> 0 | O3: =IF($A3>TODAY(),"",SUM(C3,F3,I3,L3)) -> 28800 | P3: =IF($A3>TODAY(),"",SUM(D3,G3,J3,M3)) -> 0 | Q3: =IF($A3>TODAY(),"",SUM(E3,H3,K3,N3)) -> 661.5 | R3: =IF($A3>TODAY(),"",SUM(O3:Q3)) -> 29461.5
A4: 45735 | B4: {=IF(A4>TODAY(),"",COUNTA(_xlfn.UNIQUE(_xlfn._xlws.FILTER('OPs Data'!$K:$K,'OPs Data'!$D:$D='Revenue Sheet'!A4))))} -> 3 | C4: =IF(A4>TODAY(),"",SUMIFS('OPs Data'!$N:$N,'OPs Data'!$F:$F,'Revenue Sheet'!C$1,'OPs Data'!$D:$D,'Revenue Sheet'!$A4,'OPs Data'!$L:$L,'Revenue Sheet'!C$2)*VLOOKUP($C$1,'Rate Card'!$B:$E,MATCH('Revenue Sheet'!C$2,'Rate Card'!$B$2:$E$2,0),0)) -> 0 | D4: =IF(A4>TODAY(),"",SUMIFS('OPs Data'!$N:$N,'OPs Data'!$F:$F,'Revenue Sheet'!C$1,'OPs Data'!$D:$D,'Revenue Sheet'!$A4,'OPs Data'!$L:$L,'Revenue Sheet'!D$2)*VLOOKUP($C$1,'Rate Card'!$B:$E,MATCH('Revenue Sheet'!D$2,'Rate Card'!$B$2:$E$2,0),0)) -> 0 | E4: =IF(A4>TODAY(),"",SUMIFS('OPs Data'!$N:$N,'OPs Data'!$F:$F,'Revenue Sheet'!C$1,'OPs Data'!$D:$D,'Revenue Sheet'!$A4,'OPs Data'!$L:$L,'Revenue Sheet'!E$2)*VLOOKUP($C$1,'Rate Card'!$B:$E,MATCH('Revenue Sheet'!E$2,'Rate Card'!$B$2:$E$2,0),0)) -> 13230 | F4: =IF(A4>TODAY(),"",SUMIFS('OPs Data'!$N:$N,'OPs Data'!$F:$F,'Revenue Sheet'!F$1,'OPs Data'!$D:$D,'Revenue Sheet'!$A4,'OPs Data'!$L:$L,'Revenue Sheet'!F$2)*VLOOKUP($F$1,'Rate Card'!$B:$E,MATCH('Revenue Sheet'!F$2,'Rate Card'!$B$2:$E$2,0),0)) -> 12000 | G4: =IF(A4>TODAY(),"",SUMIFS('OPs Data'!$N:$N,'OPs Data'!$F:$F,'Revenue Sheet'!F$1,'OPs Data'!$D:$D,'Revenue Sheet'!$A4,'OPs Data'!$L:$L,'Revenue Sheet'!G$2)*VLOOKUP($F$1,'Rate Card'!$B:$E,MATCH('Revenue Sheet'!G$2,'Rate Card'!$B$2:$E$2,0),0)) -> 0 | H4: =IF(A4>TODAY(),"",SUMIFS('OPs Data'!$N:$N,'OPs Data'!$F:$F,'Revenue Sheet'!F$1,'OPs Data'!$D:$D,'Revenue Sheet'!$A4,'OPs Data'!$L:$L,'Revenue Sheet'!H$2)*VLOOKUP($F$1,'Rate Card'!$B:$E,MATCH('Revenue Sheet'!H$2,'Rate Card'!$B$2:$E$2,0),0)) -> 0 | I4: =IF(A4>TODAY(),"",SUMIFS('OPs Data'!$N:$N,'OPs Data'!$F:$F,'Revenue Sheet'!I$1,'OPs Data'!$D:$D,'Revenue Sheet'!$A4,'OPs Data'!$L:$L,'Revenue Sheet'!I$2)*VLOOKUP($I$1,'Rate Card'!$B:$E,MATCH('Revenue Sheet'!I$2,'Rate Card'!$B$2:$E$2,0),0)) -> 0 | J4: =IF(A4>TODAY(),"",SUMIFS('OPs Data'!$N:$N,'OPs Data'!$F:$F,'Revenue Sheet'!I$1,'OPs Data'!$D:$D,'Revenue Sheet'!$A4,'OPs Data'!$L:$L,'Revenue Sheet'!J$2)*VLOOKUP($I$1,'Rate Card'!$B:$E,MATCH('Revenue Sheet'!J$2,'Rate Card'!$B$2:$E$2,0),0)) -> 0 | K4: =IF(A4>TODAY(),"",SUMIFS('OPs Data'!$N:$N,'OPs Data'!$F:$F,'Revenue Sheet'!I$1,'OPs Data'!$D:$D,'Revenue Sheet'!$A4,'OPs Data'!$L:$L,'Revenue Sheet'!K$2)*VLOOKUP($I$1,'Rate Card'!$B:$E,MATCH('Revenue Sheet'!K$2,'Rate Card'!$B$2:$E$2,0),0)) -> 0 | L4: =IF(A4>TODAY(),"",SUMIFS('OPs Data'!$N:$N,'OPs Data'!$F:$F,'Revenue Sheet'!L$1,'OPs Data'!$D:$D,'Revenue Sheet'!$A4,'OPs Data'!$L:$L,'Revenue Sheet'!L$2)*VLOOKUP($L$1,'Rate Card'!$B:$E,MATCH('Revenue Sheet'!L$2,'Rate Card'!$B$2:$E$2,0),0)) -> 0 | M4: =IF(A4>TODAY(),"",SUMIFS('OPs Data'!$N:$N,'OPs Data'!$F:$F,'Revenue Sheet'!L$1,'OPs Data'!$D:$D,'Revenue Sheet'!$A4,'OPs Data'!$L:$L,'Revenue Sheet'!M$2)*VLOOKUP($L$1,'Rate Card'!$B:$E,MATCH('Revenue Sheet'!M$2,'Rate Card'!$B$2:$E$2,0),0)) -> 0 | N4: =IF(A4>TODAY(),"",SUMIFS('OPs Data'!$N:$N,'OPs Data'!$F:$F,'Revenue Sheet'!L$1,'OPs Data'!$D:$D,'Revenue Sheet'!$A4,'OPs Data'!$L:$L,'Revenue Sheet'!N$2)*VLOOKUP($L$1,'Rate Card'!$B:$E,MATCH('Revenue Sheet'!N$2,'Rate Card'!$B$2:$E$2,0),0)) -> 0 | O4: =IF($A4>TODAY(),"",SUM(C4,F4,I4,L4)) -> 12000 | P4: =IF($A4>TODAY(),"",SUM(D4,G4,J4,M4)) -> 0 | Q4: =IF($A4>TODAY(),"",SUM(E4,H4,K4,N4)) -> 13230 | R4: =IF($A4>TODAY(),"",SUM(O4:Q4)) -> 25230
A5: 45736 | B5: {=IF(A5>TODAY(),"",COUNTA(_xlfn.UNIQUE(_xlfn._xlws.FILTER('OPs Data'!$K:$K,'OPs Data'!$D:$D='Revenue Sheet'!A5))))} -> 3 | C5: =IF(A5>TODAY(),"",SUMIFS('OPs Data'!$N:$N,'OPs Data'!$F:$F,'Revenue Sheet'!C$1,'OPs Data'!$D:$D,'Revenue Sheet'!$A5,'OPs Data'!$L:$L,'Revenue Sheet'!C$2)*VLOOKUP($C$1,'Rate Card'!$B:$E,MATCH('Revenue Sheet'!C$2,'Rate Card'!$B$2:$E$2,0),0)) -> 8400 | D5: =IF(A5>TODAY(),"",SUMIFS('OPs Data'!$N:$N,'OPs Data'!$F:$F,'Revenue Sheet'!C$1,'OPs Data'!$D:$D,'Revenue Sheet'!$A5,'OPs Data'!$L:$L,'Revenue Sheet'!D$2)*VLOOKUP($C$1,'Rate Card'!$B:$E,MATCH('Revenue Sheet'!D$2,'Rate Card'!$B$2:$E$2,0),0)) -> 0 | E5: =IF(A5>TODAY(),"",SUMIFS('OPs Data'!$N:$N,'OPs Data'!$F:$F,'Revenue Sheet'!C$1,'OPs Data'!$D:$D,'Revenue Sheet'!$A5,'OPs Data'!$L:$L,'Revenue Sheet'!E$2)*VLOOKUP($C$1,'Rate Card'!$B:$E,MATCH('Revenue Sheet'!E$2,'Rate Card'!$B$2:$E$2,0),0)) -> 0 | F5: =IF(A5>TODAY(),"",SUMIFS('OPs Data'!$N:$N,'OPs Data'!$F:$F,'Revenue Sheet'!F$1,'OPs Data'!$D:$D,'Revenue Sheet'!$A5,'OPs Data'!$L:$L,'Revenue Sheet'!F$2)*VLOOKUP($F$1,'Rate Card'!$B:$E,MATCH('Revenue Sheet'!F$2,'Rate Card'!$B$2:$E$2,0),0)) -> 4000 | G5: =IF(A5>TODAY(),"",SUMIFS('OPs Data'!$N:$N,'OPs Data'!$F:$F,'Revenue Sheet'!F$1,'OPs Data'!$D:$D,'Revenue Sheet'!$A5,'OPs Data'!$L:$L,'Revenue Sheet'!G$2)*VLOOKUP($F$1,'Rate Card'!$B:$E,MATCH('Revenue Sheet'!G$2,'Rate Card'!$B$2:$E$2,0),0)) -> 0 | H5: =IF(A5>TODAY(),"",SUMIFS('OPs Data'!$N:$N,'OPs Data'!$F:$F,'Revenue Sheet'!F$1,'OPs Data'!$D:$D,'Revenue Sheet'!$A5,'OPs Data'!$L:$L,'Revenue Sheet'!H$2)*VLOOKUP($F$1,'Rate Card'!$B:$E,MATCH('Revenue Sheet'!H$2,'Rate Card'!$B$2:$E$2,0),0)) -> 0 | I5: =IF(A5>TODAY(),"",SUMIFS('OPs Data'!$N:$N,'OPs Data'!$F:$F,'Revenue Sheet'!I$1,'OPs Data'!$D:$D,'Revenue Sheet'!$A5,'OPs Data'!$L:$L,'Revenue Sheet'!I$2)*VLOOKUP($I$1,'Rate Card'!$B:$E,MATCH('Revenue Sheet'!I$2,'Rate Card'!$B$2:$E$2,0),0)) -> 0 | J5: =IF(A5>TODAY(),"",SUMIFS('OPs Data'!$N:$N,'OPs Data'!$F:$F,'Revenue Sheet'!I$1,'OPs Data'!$D:$D,'Revenue Sheet'!$A5,'OPs Data'!$L:$L,'Revenue Sheet'!J$2)*VLOOKUP($I$1,'Rate Card'!$B:$E,MATCH('Revenue Sheet'!J$2,'Rate Card'!$B$2:$E$2,0),0)) -> 0 | K5: =IF(A5>TODAY(),"",SUMIFS('OPs Data'!$N:$N,'OPs Data'!$F:$F,'Revenue Sheet'!I$1,'OPs Data'!$D:$D,'Revenue Sheet'!$A5,'OPs Data'!$L:$L,'Revenue Sheet'!K$2)*VLOOKUP($I$1,'Rate Card'!$B:$E,MATCH('Revenue Sheet'!K$2,'Rate Card'!$B$2:$E$2,0),0)) -> 0 | L5: =IF(A5>TODAY(),"",SUMIFS('OPs Data'!$N:$N,'OPs Data'!$F:$F,'Revenue Sheet'!L$1,'OPs Data'!$D:$D,'Revenue Sheet'!$A5,'OPs Data'!$L:$L,'Revenue Sheet'!L$2)*VLOOKUP($L$1,'Rate Card'!$B:$E,MATCH('Revenue Sheet'!L$2,'Rate Card'!$B$2:$E$2,0),0)) -> 0 | M5: =IF(A5>TODAY(),"",SUMIFS('OPs Data'!$N:$N,'OPs Data'!$F:$F,'Revenue Sheet'!L$1,'OPs Data'!$D:$D,'Revenue Sheet'!$A5,'OPs Data'!$L:$L,'Revenue Sheet'!M$2)*VLOOKUP($L$1,'Rate Card'!$B:$E,MATCH('Revenue Sheet'!M$2,'Rate Card'!$B$2:$E$2,0),0)) -> 0 | N5: =IF(A5>TODAY(),"",SUMIFS('OPs Data'!$N:$N,'OPs Data'!$F:$F,'Revenue Sheet'!L$1,'OPs Data'!$D:$D,'Revenue Sheet'!$A5,'OPs Data'!$L:$L,'Revenue Sheet'!N$2)*VLOOKUP($L$1,'Rate Card'!$B:$E,MATCH('Revenue Sheet'!N$2,'Rate Card'!$B$2:$E$2,0),0)) -> 0 | O5: =IF($A5>TODAY(),"",SUM(C5,F5,I5,L5)) -> 12400 | P5: =IF($A5>TODAY(),"",SUM(D5,G5,J5,M5)) -> 0 | Q5: =IF($A5>TODAY(),"",SUM(E5,H5,K5,N5)) -> 0 | R5: =IF($A5>TODAY(),"",SUM(O5:Q5)) -> 12400
A6: 45737 | B6: {=IF(A6>TODAY(),"",COUNTA(_xlfn.UNIQUE(_xlfn._xlws.FILTER('OPs Data'!$K:$K,'OPs Data'!$D:$D='Revenue Sheet'!A6))))} -> 4 | C6: =IF(A6>TODAY(),"",SUMIFS('OPs Data'!$N:$N,'OPs Data'!$F:$F,'Revenue Sheet'!C$1,'OPs Data'!$D:$D,'Revenue Sheet'!$A6,'OPs Data'!$L:$L,'Revenue Sheet'!C$2)*VLOOKUP($C$1,'Rate Card'!$B:$E,MATCH('Revenue Sheet'!C$2,'Rate Card'!$B$2:$E$2,0),0)) -> 6300 | D6: =IF(A6>TODAY(),"",SUMIFS('OPs Data'!$N:$N,'OPs Data'!$F:$F,'Revenue Sheet'!C$1,'OPs Data'!$D:$D,'Revenue Sheet'!$A6,'OPs Data'!$L:$L,'Revenue Sheet'!D$2)*VLOOKUP($C$1,'Rate Card'!$B:$E,MATCH('Revenue Sheet'!D$2,'Rate Card'!$B$2:$E$2,0),0)) -> 0 | E6: =IF(A6>TODAY(),"",SUMIFS('OPs Data'!$N:$N,'OPs Data'!$F:$F,'Revenue Sheet'!C$1,'OPs Data'!$D:$D,'Revenue Sheet'!$A6,'OPs Data'!$L:$L,'Revenue Sheet'!E$2)*VLOOKUP($C$1,'Rate Card'!$B:$E,MATCH('Revenue Sheet'!E$2,'Rate Card'!$B$2:$E$2,0),0)) -> 6615 | F6: =IF(A6>TODAY(),"",SUMIFS('OPs Data'!$N:$N,'OPs Data'!$F:$F,'Revenue Sheet'!F$1,'OPs Data'!$D:$D,'Revenue Sheet'!$A6,'OPs Data'!$L:$L,'Revenue Sheet'!F$2)*VLOOKUP($F$1,'Rate Card'!$B:$E,MATCH('Revenue Sheet'!F$2,'Rate Card'!$B$2:$E$2,0),0)) -> 12000 | G6: =IF(A6>TODAY(),"",SUMIFS('OPs Data'!$N:$N,'OPs Data'!$F:$F,'Revenue Sheet'!F$1,'OPs Data'!$D:$D,'Revenue Sheet'!$A6,'OPs Data'!$L:$L,'Revenue Sheet'!G$2)*VLOOKUP($F$1,'Rate Card'!$B:$E,MATCH('Revenue Sheet'!G$2,'Rate Card'!$B$2:$E$2,0),0)) -> 0 | H6: =IF(A6>TODAY(),"",SUMIFS('OPs Data'!$N:$N,'OPs Data'!$F:$F,'Revenue Sheet'!F$1,'OPs Data'!$D:$D,'Revenue Sheet'!$A6,'OPs Data'!$L:$L,'Revenue Sheet'!H$2)*VLOOKUP($F$1,'Rate Card'!$B:$E,MATCH('Revenue Sheet'!H$2,'Rate Card'!$B$2:$E$2,0),0)) -> 0 | I6: =IF(A6>TODAY(),"",SUMIFS('OPs Data'!$N:$N,'OPs Data'!$F:$F,'Revenue Sheet'!I$1,'OPs Data'!$D:$D,'Revenue Sheet'!$A6,'OPs Data'!$L:$L,'Revenue Sheet'!I$2)*VLOOKUP($I$1,'Rate Card'!$B:$E,MATCH('Revenue Sheet'!I$2,'Rate Card'!$B$2:$E$2,0),0)) -> 20400 | J6: =IF(A6>TODAY(),"",SUMIFS('OPs Data'!$N:$N,'OPs Data'!$F:$F,'Revenue Sheet'!I$1,'OPs Data'!$D:$D,'Revenue Sheet'!$A6,'OPs Data'!$L:$L,'Revenue Sheet'!J$2)*VLOOKUP($I$1,'Rate Card'!$B:$E,MATCH('Revenue Sheet'!J$2,'Rate Card'!$B$2:$E$2,0),0)) -> 0 | K6: =IF(A6>TODAY(),"",SUMIFS('OPs Data'!$N:$N,'OPs Data'!$F:$F,'Revenue Sheet'!I$1,'OPs Data'!$D:$D,'Revenue Sheet'!$A6,'OPs Data'!$L:$L,'Revenue Sheet'!K$2)*VLOOKUP($I$1,'Rate Card'!$B:$E,MATCH('Revenue Sheet'!K$2,'Rate Card'!$B$2:$E$2,0),0)) -> 0 | L6: =IF(A6>TODAY(),"",SUMIFS('OPs Data'!$N:$N,'OPs Data'!$F:$F,'Revenue Sheet'!L$1,'OPs Data'!$D:$D,'Revenue Sheet'!$A6,'OPs Data'!$L:$L,'Revenue Sheet'!L$2)*VLOOKUP($L$1,'Rate Card'!$B:$E,MATCH('Revenue Sheet'!L$2,'Rate Card'!$B$2:$E$2,0),0)) -> 0 | M6: =IF(A6>TODAY(),"",SUMIFS('OPs Data'!$N:$N,'OPs Data'!$F:$F,'Revenue Sheet'!L$1,'OPs Data'!$D:$D,'Revenue Sheet'!$A6,'OPs Data'!$L:$L,'Revenue Sheet'!M$2)*VLOOKUP($L$1,'Rate Card'!$B:$E,MATCH('Revenue Sheet'!M$2,'Rate Card'!$B$2:$E$2,0),0)) -> 0 | N6: =IF(A6>TODAY(),"",SUMIFS('OPs Data'!$N:$N,'OPs Data'!$F:$F,'Revenue Sheet'!L$1,'OPs Data'!$D:$D,'Revenue Sheet'!$A6,'OPs Data'!$L:$L,'Revenue Sheet'!N$2)*VLOOKUP($L$1,'Rate Card'!$B:$E,MATCH('Revenue Sheet'!N$2,'Rate Card'!$B$2:$E$2,0),0)) -> 0 | O6: =IF($A6>TODAY(),"",SUM(C6,F6,I6,L6)) -> 38700 | P6: =IF($A6>TODAY(),"",SUM(D6,G6,J6,M6)) -> 0 | Q6: =IF($A6>TODAY(),"",SUM(E6,H6,K6,N6)) -> 6615 | R6: =IF($A6>TODAY(),"",SUM(O6:Q6)) -> 45315
A7: 45738 | B7: {=IF(A7>TODAY(),"",COUNTA(_xlfn.UNIQUE(_xlfn._xlws.FILTER('OPs Data'!$K:$K,'OPs Data'!$D:$D='Revenue Sheet'!A7))))} -> 2 | C7: =IF(A7>TODAY(),"",SUMIFS('OPs Data'!$N:$N,'OPs Data'!$F:$F,'Revenue Sheet'!C$1,'OPs Data'!$D:$D,'Revenue Sheet'!$A7,'OPs Data'!$L:$L,'Revenue Sheet'!C$2)*VLOOKUP($C$1,'Rate Card'!$B:$E,MATCH('Revenue Sheet'!C$2,'Rate Card'!$B$2:$E$2,0),0)) -> 10500 | D7: =IF(A7>TODAY(),"",SUMIFS('OPs Data'!$N:$N,'OPs Data'!$F:$F,'Revenue Sheet'!C$1,'OPs Data'!$D:$D,'Revenue Sheet'!$A7,'OPs Data'!$L:$L,'Revenue Sheet'!D$2)*VLOOKUP($C$1,'Rate Card'!$B:$E,MATCH('Revenue Sheet'!D$2,'Rate Card'!$B$2:$E$2,0),0)) -> 0 | E7: =IF(A7>TODAY(),"",SUMIFS('OPs Data'!$N:$N,'OPs Data'!$F:$F,'Revenue Sheet'!C$1,'OPs Data'!$D:$D,'Revenue Sheet'!$A7,'OPs Data'!$L:$L,'Revenue Sheet'!E$2)*VLOOKUP($C$1,'Rate Card'!$B:$E,MATCH('Revenue Sheet'!E$2,'Rate Card'!$B$2:$E$2,0),0)) -> 0 | F7: =IF(A7>TODAY(),"",SUMIFS('OPs Data'!$N:$N,'OPs Data'!$F:$F,'Revenue Sheet'!F$1,'OPs Data'!$D:$D,'Revenue Sheet'!$A7,'OPs Data'!$L:$L,'Revenue Sheet'!F$2)*VLOOKUP($F$1,'Rate Card'!$B:$E,MATCH('Revenue Sheet'!F$2,'Rate Card'!$B$2:$E$2,0),0)) -> 0 | G7: =IF(A7>TODAY(),"",SUMIFS('OPs Data'!$N:$N,'OPs Data'!$F:$F,'Revenue Sheet'!F$1,'OPs Data'!$D:$D,'Revenue Sheet'!$A7,'OPs Data'!$L:$L,'Revenue Sheet'!G$2)*VLOOKUP($F$1,'Rate Card'!$B:$E,MATCH('Revenue Sheet'!G$2,'Rate Card'!$B$2:$E$2,0),0)) -> 0 | H7: =IF(A7>TODAY(),"",SUMIFS('OPs Data'!$N:$N,'OPs Data'!$F:$F,'Revenue Sheet'!F$1,'OPs Data'!$D:$D,'Revenue Sheet'!$A7,'OPs Data'!$L:$L,'Revenue Sheet'!H$2)*VLOOKUP($F$1,'Rate Card'!$B:$E,MATCH('Revenue Sheet'!H$2,'Rate Card'!$B$2:$E$2,0),0)) -> 0 | I7: =IF(A7>TODAY(),"",SUMIFS('OPs Data'!$N:$N,'OPs Data'!$F:$F,'Revenue Sheet'!I$1,'OPs Data'!$D:$D,'Revenue Sheet'!$A7,'OPs Data'!$L:$L,'Revenue Sheet'!I$2)*VLOOKUP($I$1,'Rate Card'!$B:$E,MATCH('Revenue Sheet'!I$2,'Rate Card'!$B$2:$E$2,0),0)) -> 0 | J7: =IF(A7>TODAY(),"",SUMIFS('OPs Data'!$N:$N,'OPs Data'!$F:$F,'Revenue Sheet'!I$1,'OPs Data'!$D:$D,'Revenue Sheet'!$A7,'OPs Data'!$L:$L,'Revenue Sheet'!J$2)*VLOOKUP($I$1,'Rate Card'!$B:$E,MATCH('Revenue Sheet'!J$2,'Rate Card'!$B$2:$E$2,0),0)) -> 0 | K7: =IF(A7>TODAY(),"",SUMIFS('OPs Data'!$N:$N,'OPs Data'!$F:$F,'Revenue Sheet'!I$1,'OPs Data'!$D:$D,'Revenue Sheet'!$A7,'OPs Data'!$L:$L,'Revenue Sheet'!K$2)*VLOOKUP($I$1,'Rate Card'!$B:$E,MATCH('Revenue Sheet'!K$2,'Rate Card'!$B$2:$E$2,0),0)) -> 0 | L7: =IF(A7>TODAY(),"",SUMIFS('OPs Data'!$N:$N,'OPs Data'!$F:$F,'Revenue Sheet'!L$1,'OPs Data'!$D:$D,'Revenue Sheet'!$A7,'OPs Data'!$L:$L,'Revenue Sheet'!L$2)*VLOOKUP($L$1,'Rate Card'!$B:$E,MATCH('Revenue Sheet'!L$2,'Rate Card'!$B$2:$E$2,0),0)) -> 0 | M7: =IF(A7>TODAY(),"",SUMIFS('OPs Data'!$N:$N,'OPs Data'!$F:$F,'Revenue Sheet'!L$1,'OPs Data'!$D:$D,'Revenue Sheet'!$A7,'OPs Data'!$L:$L,'Revenue Sheet'!M$2)*VLOOKUP($L$1,'Rate Card'!$B:$E,MATCH('Revenue Sheet'!M$2,'Rate Card'!$B$2:$E$2,0),0)) -> 0 | N7: =IF(A7>TODAY(),"",SUMIFS('OPs Data'!$N:$N,'OPs Data'!$F:$F,'Revenue Sheet'!L$1,'OPs Data'!$D:$D,'Revenue Sheet'!$A7,'OPs Data'!$L:$L,'Revenue Sheet'!N$2)*VLOOKUP($L$1,'Rate Card'!$B:$E,MATCH('Revenue Sheet'!N$2,'Rate Card'!$B$2:$E$2,0),0)) -> 0 | O7: =IF($A7>TODAY(),"",SUM(C7,F7,I7,L7)) -> 10500 | P7: =IF($A7>TODAY(),"",SUM(D7,G7,J7,M7)) -> 0 | Q7: =IF($A7>TODAY(),"",SUM(E7,H7,K7,N7)) -> 0 | R7: =IF($A7>TODAY(),"",SUM(O7:Q7)) -> 10500
A8: 45739 | B8: {=IF(A8>TODAY(),"",COUNTA(_xlfn.UNIQUE(_xlfn._xlws.FILTER('OPs Data'!$K:$K,'OPs Data'!$D:$D='Revenue Sheet'!A8))))} -> 1 | C8: =IF(A8>TODAY(),"",SUMIFS('OPs Data'!$N:$N,'OPs Data'!$F:$F,'Revenue Sheet'!C$1,'OPs Data'!$D:$D,'Revenue Sheet'!$A8,'OPs Data'!$L:$L,'Revenue Sheet'!C$2)*VLOOKUP($C$1,'Rate Card'!$B:$E,MATCH('Revenue Sheet'!C$2,'Rate Card'!$B$2:$E$2,0),0)) -> 0 | D8: =IF(A8>TODAY(),"",SUMIFS('OPs Data'!$N:$N,'OPs Data'!$F:$F,'Revenue Sheet'!C$1,'OPs Data'!$D:$D,'Revenue Sheet'!$A8,'OPs Data'!$L:$L,'Revenue Sheet'!D$2)*VLOOKUP($C$1,'Rate Card'!$B:$E,MATCH('Revenue Sheet'!D$2,'Rate Card'!$B$2:$E$2,0),0)) -> 0 | E8: =IF(A8>TODAY(),"",SUMIFS('OPs Data'!$N:$N,'OPs Data'!$F:$F,'Revenue Sheet'!C$1,'OPs Data'!$D:$D,'Revenue Sheet'!$A8,'OPs Data'!$L:$L,'Revenue Sheet'!E$2)*VLOOKUP($C$1,'Rate Card'!$B:$E,MATCH('Revenue Sheet'!E$2,'Rate Card'!$B$2:$E$2,0),0)) -> 0 | F8: =IF(A8>TODAY(),"",SUMIFS('OPs Data'!$N:$N,'OPs Data'!$F:$F,'Revenue Sheet'!F$1,'OPs Data'!$D:$D,'Revenue Sheet'!$A8,'OPs Data'!$L:$L,'Revenue Sheet'!F$2)*VLOOKUP($F$1,'Rate Card'!$B:$E,MATCH('Revenue Sheet'!F$2,'Rate Card'!$B$2:$E$2,0),0)) -> 0 | G8: =IF(A8>TODAY(),"",SUMIFS('OPs Data'!$N:$N,'OPs Data'!$F:$F,'Revenue Sheet'!F$1,'OPs Data'!$D:$D,'Revenue Sheet'!$A8,'OPs Data'!$L:$L,'Revenue Sheet'!G$2)*VLOOKUP($F$1,'Rate Card'!$B:$E,MATCH('Revenue Sheet'!G$2,'Rate Card'!$B$2:$E$2,0),0)) -> 0 | H8: =IF(A8>TODAY(),"",SUMIFS('OPs Data'!$N:$N,'OPs Data'!$F:$F,'Revenue Sheet'!F$1,'OPs Data'!$D:$D,'Revenue Sheet'!$A8,'OPs Data'!$L:$L,'Revenue Sheet'!H$2)*VLOOKUP($F$1,'Rate Card'!$B:$E,MATCH('Revenue Sheet'!H$2,'Rate Card'!$B$2:$E$2,0),0)) -> 0 | I8: =IF(A8>TODAY(),"",SUMIFS('OPs Data'!$N:$N,'OPs Data'!$F:$F,'Revenue Sheet'!I$1,'OPs Data'!$D:$D,'Revenue Sheet'!$A8,'OPs Data'!$L:$L,'Revenue Sheet'!I$2)*VLOOKUP($I$1,'Rate Card'!$B:$E,MATCH('Revenue Sheet'!I$2,'Rate Card'!$B$2:$E$2,0),0)) -> 0 | J8: =IF(A8>TODAY(),"",SUMIFS('OPs Data'!$N:$N,'OPs Data'!$F:$F,'Revenue Sheet'!I$1,'OPs Data'!$D:$D,'Revenue Sheet'!$A8,'OPs Data'!$L:$L,'Revenue Sheet'!J$2)*VLOOKUP($I$1,'Rate Card'!$B:$E,MATCH('Revenue Sheet'!J$2,'Rate Card'!$B$2:$E$2,0),0)) -> 0 | K8: =IF(A8>TODAY(),"",SUMIFS('OPs Data'!$N:$N,'OPs Data'!$F:$F,'Revenue Sheet'!I$1,'OPs Data'!$D:$D,'Revenue Sheet'!$A8,'OPs Data'!$L:$L,'Revenue Sheet'!K$2)*VLOOKUP($I$1,'Rate Card'!$B:$E,MATCH('Revenue Sheet'!K$2,'Rate Card'!$B$2:$E$2,0),0)) -> 0 | L8: =IF(A8>TODAY(),"",SUMIFS('OPs Data'!$N:$N,'OPs Data'!$F:$F,'Revenue Sheet'!L$1,'OPs Data'!$D:$D,'Revenue Sheet'!$A8,'OPs Data'!$L:$L,'Revenue Sheet'!L$2)*VLOOKUP($L$1,'Rate Card'!$B:$E,MATCH('Revenue Sheet'!L$2,'Rate Card'!$B$2:$E$2,0),0)) -> 0 | M8: =IF(A8>TODAY(),"",SUMIFS('OPs Data'!$N:$N,'OPs Data'!$F:$F,'Revenue Sheet'!L$1,'OPs Data'!$D:$D,'Revenue Sheet'!$A8,'OPs Data'!$L:$L,'Revenue Sheet'!M$2)*VLOOKUP($L$1,'Rate Card'!$B:$E,MATCH('Revenue Sheet'!M$2,'Rate Card'!$B$2:$E$2,0),0)) -> 0 | N8: =IF(A8>TODAY(),"",SUMIFS('OPs Data'!$N:$N,'OPs Data'!$F:$F,'Revenue Sheet'!L$1,'OPs Data'!$D:$D,'Revenue Sheet'!$A8,'OPs Data'!$L:$L,'Revenue Sheet'!N$2)*VLOOKUP($L$1,'Rate Card'!$B:$E,MATCH('Revenue Sheet'!N$2,'Rate Card'!$B$2:$E$2,0),0)) -> 0 | O8: =IF($A8>TODAY(),"",SUM(C8,F8,I8,L8)) -> 0 | P8: =IF($A8>TODAY(),"",SUM(D8,G8,J8,M8)) -> 0 | Q8: =IF($A8>TODAY(),"",SUM(E8,H8,K8,N8)) -> 0 | R8: =IF($A8>TODAY(),"",SUM(O8:Q8)) -> 0
A9: 45740 | B9: {=IF(A9>TODAY(),"",COUNTA(_xlfn.UNIQUE(_xlfn._xlws.FILTER('OPs Data'!$K:$K,'OPs Data'!$D:$D='Revenue Sheet'!A9))))} -> 3 | C9: =IF(A9>TODAY(),"",SUMIFS('OPs Data'!$N:$N,'OPs Data'!$F:$F,'Revenue Sheet'!C$1,'OPs Data'!$D:$D,'Revenue Sheet'!$A9,'OPs Data'!$L:$L,'Revenue Sheet'!C$2)*VLOOKUP($C$1,'Rate Card'!$B:$E,MATCH('Revenue Sheet'!C$2,'Rate Card'!$B$2:$E$2,0),0)) -> 6300 | D9: =IF(A9>TODAY(),"",SUMIFS('OPs Data'!$N:$N,'OPs Data'!$F:$F,'Revenue Sheet'!C$1,'OPs Data'!$D:$D,'Revenue Sheet'!$A9,'OPs Data'!$L:$L,'Revenue Sheet'!D$2)*VLOOKUP($C$1,'Rate Card'!$B:$E,MATCH('Revenue Sheet'!D$2,'Rate Card'!$B$2:$E$2,0),0)) -> 0 | E9: =IF(A9>TODAY(),"",SUMIFS('OPs Data'!$N:$N,'OPs Data'!$F:$F,'Revenue Sheet'!C$1,'OPs Data'!$D:$D,'Revenue Sheet'!$A9,'OPs Data'!$L:$L,'Revenue Sheet'!E$2)*VLOOKUP($C$1,'Rate Card'!$B:$E,MATCH('Revenue Sheet'!E$2,'Rate Card'!$B$2:$E$2,0),0)) -> 0 | F9: =IF(A9>TODAY(),"",SUMIFS('OPs Data'!$N:$N,'OPs Data'!$F:$F,'Revenue Sheet'!F$1,'OPs Data'!$D:$D,'Revenue Sheet'!$A9,'OPs Data'!$L:$L,'Revenue Sheet'!F$2)*VLOOKUP($F$1,'Rate Card'!$B:$E,MATCH('Revenue Sheet'!F$2,'Rate Card'!$B$2:$E$2,0),0)) -> 12000 | G9: =IF(A9>TODAY(),"",SUMIFS('OPs Data'!$N:$N,'OPs Data'!$F:$F,'Revenue Sheet'!F$1,'OPs Data'!$D:$D,'Revenue Sheet'!$A9,'OPs Data'!$L:$L,'Revenue Sheet'!G$2)*VLOOKUP($F$1,'Rate Card'!$B:$E,MATCH('Revenue Sheet'!G$2,'Rate Card'!$B$2:$E$2,0),0)) -> 0 | H9: =IF(A9>TODAY(),"",SUMIFS('OPs Data'!$N:$N,'OPs Data'!$F:$F,'Revenue Sheet'!F$1,'OPs Data'!$D:$D,'Revenue Sheet'!$A9,'OPs Data'!$L:$L,'Revenue Sheet'!H$2)*VLOOKUP($F$1,'Rate Card'!$B:$E,MATCH('Revenue Sheet'!H$2,'Rate Card'!$B$2:$E$2,0),0)) -> 12600 | I9: =IF(A9>TODAY(),"",SUMIFS('OPs Data'!$N:$N,'OPs Data'!$F:$F,'Revenue Sheet'!I$1,'OPs Data'!$D:$D,'Revenue Sheet'!$A9,'OPs Data'!$L:$L,'Revenue Sheet'!I$2)*VLOOKUP($I$1,'Rate Card'!$B:$E,MATCH('Revenue Sheet'!I$2,'Rate Card'!$B$2:$E$2,0),0)) -> 0 | J9: =IF(A9>TODAY(),"",SUMIFS('OPs Data'!$N:$N,'OPs Data'!$F:$F,'Revenue Sheet'!I$1,'OPs Data'!$D:$D,'Revenue Sheet'!$A9,'OPs Data'!$L:$L,'Revenue Sheet'!J$2)*VLOOKUP($I$1,'Rate Card'!$B:$E,MATCH('Revenue Sheet'!J$2,'Rate Card'!$B$2:$E$2,0),0)) -> 0 | K9: =IF(A9>TODAY(),"",SUMIFS('OPs Data'!$N:$N,'OPs Data'!$F:$F,'Revenue Sheet'!I$1,'OPs Data'!$D:$D,'Revenue Sheet'!$A9,'OPs Data'!$L:$L,'Revenue Sheet'!K$2)*VLOOKUP($I$1,'Rate Card'!$B:$E,MATCH('Revenue Sheet'!K$2,'Rate Card'!$B$2:$E$2,0),0)) -> 0 | L9: =IF(A9>TODAY(),"",SUMIFS('OPs Data'!$N:$N,'OPs Data'!$F:$F,'Revenue Sheet'!L$1,'OPs Data'!$D:$D,'Revenue Sheet'!$A9,'OPs Data'!$L:$L,'Revenue Sheet'!L$2)*VLOOKUP($L$1,'Rate Card'!$B:$E,MATCH('Revenue Sheet'!L$2,'Rate Card'!$B$2:$E$2,0),0)) -> 0 | M9: =IF(A9>TODAY(),"",SUMIFS('OPs Data'!$N:$N,'OPs Data'!$F:$F,'Revenue Sheet'!L$1,'OPs Data'!$D:$D,'Revenue Sheet'!$A9,'OPs Data'!$L:$L,'Revenue Sheet'!M$2)*VLOOKUP($L$1,'Rate Card'!$B:$E,MATCH('Revenue Sheet'!M$2,'Rate Card'!$B$2:$E$2,0),0)) -> 0 | N9: =IF(A9>TODAY(),"",SUMIFS('OPs Data'!$N:$N,'OPs Data'!$F:$F,'Revenue Sheet'!L$1,'OPs Data'!$D:$D,'Revenue Sheet'!$A9,'OPs Data'!$L:$L,'Revenue Sheet'!N$2)*VLOOKUP($L$1,'Rate Card'!$B:$E,MATCH('Revenue Sheet'!N$2,'Rate Card'!$B$2:$E$2,0),0)) -> 0 | O9: =IF($A9>TODAY(),"",SUM(C9,F9,I9,L9)) -> 18300 | P9: =IF($A9>TODAY(),"",SUM(D9,G9,J9,M9)) -> 0 | Q9: =IF($A9>TODAY(),"",SUM(E9,H9,K9,N9)) -> 12600 | R9: =IF($A9>TODAY(),"",SUM(O9:Q9)) -> 30900
